Workbook

Sheet PesoMatPrima
A1: =CONCATENATE("PESO DE MATERIA PRIMA EN GRAMOS MAS EL ",$B$62," % DE MERMA") -> PESO DE MATERIA PRIMA EN GRAMOS MAS EL 8 % DE MERMA
A2: ITEM | B2: DETALLE | C2: 2 | D2: 4 | E2: 6 | F2: 8 | G2: 10 | H2: 12 | I2: 14 | J2: 16/34 | K2: 36/XS | L2: 38/S | M2: 40/M | N2: 42/L | O2: 44/XL | P2: 46/2XL | Q2: 48/3XL | R2: 50/4XL
A3: 1 | B3: Pantalón de vestir | C3: =IF(C34>0,C34*($B$62/100+1),0) -> 0 | D3: =IF(D34>0,D34*($B$62/100+1),0) -> 0 | E3: =IF(E34>0,E34*($B$62/100+1),0) -> 0 | F3: =IF(F34>0,F34*($B$62/100+1),0) -> 0 | G3: =IF(G34>0,G34*($B$62/100+1),0) -> 0 | H3: =IF(H34>0,H34*($B$62/100+1),0) -> 0 | I3: =IF(I34>0,I34*($B$62/100+1),0) -> 0 | J3: =IF(J34>0,J34*($B$62/100+1),0) -> 340.2 | ... R3: =IF(R34>0,R34*($B$62/100+1),0) -> 464.4
A4: 2 | B4: Camisa manga corta | C4: =IF(C35>0,C35*($B$62/100+1),0) -> 104.76 | D4: =IF(D35>0,D35*($B$62/100+1),0) -> 112.32 | E4: =IF(E35>0,E35*($B$62/100+1),0) -> 119.88 | F4: =IF(F35>0,F35*($B$62/100+1),0) -> 127.44 | G4: =IF(G35>0,G35*($B$62/100+1),0) -> 135 | H4: =IF(H35>0,H35*($B$62/100+1),0) -> 142.56 | I4: =IF(I35>0,I35*($B$62/100+1),0) -> 150.12 | J4: =IF(J35>0,J35*($B$62/100+1),0) -> 157.68 | L4: =IF(L35>0,L35*($B$62/100+1),0) -> 165.24 | M4: =IF(M35>0,M35*($B$62/100+1),0) -> 172.8 | N4: =IF(N35>0,N35*($B$62/100+1),0) -> 180.36 | O4: =IF(O35>0,O35*($B$62/100+1),0) -> 187.92 | P4: =IF(P35>0,P35*($B$62/100+1),0) -> 197.64 | Q4: =IF(Q35>0,Q35*($B$62/100+1),0) -> 206.28
A5: 3 | B5: Camisa manga larga | C5: =IF(C36>0,C36*($B$62/100+1),0) -> 115.56 | D5: =IF(D36>0,D36*($B$62/100+1),0) -> 123.12 | E5: =IF(E36>0,E36*($B$62/100+1),0) -> 130.68 | F5: =IF(F36>0,F36*($B$62/100+1),0) -> 138.24 | G5: =IF(G36>0,G36*($B$62/100+1),0) -> 145.8 | H5: =IF(H36>0,H36*($B$62/100+1),0) -> 153.36 | I5: =IF(I36>0,I36*($B$62/100+1),0) -> 160.92 | J5: =IF(J36>0,J36*($B$62/100+1),0) -> 168.48 | L5: =IF(L36>0,L36*($B$62/100+1),0) -> 176.04 | M5: =IF(M36>0,M36*($B$62/100+1),0) -> 183.6 | N5: =IF(N36>0,N36*($B$62/100+1),0) -> 191.16 | O5: =IF(O36>0,O36*($B$62/100+1),0) -> 198.72 | P5: =IF(P36>0,P36*($B$62/100+1),0) -> 208.44 | Q5: =IF(Q36>0,Q36*($B$62/100+1),0) -> 217.08
A6: 4 | B6: Corbata larga | C6: =IF(C37>0,C37*($B$62/100+1),0) -> 0 | D6: =IF(D37>0,D37*($B$62/100+1),0) -> 0 | E6: =IF(E37>0,E37*($B$62/100+1),0) -> 0 | F6: =IF(F37>0,F37*($B$62/100+1),0) -> 0 | G6: =IF(G37>0,G37*($B$62/100+1),0) -> 0 | H6: =IF(H37>0,H37*($B$62/100+1),0) -> 0 | I6: =IF(I37>0,I37*($B$62/100+1),0) -> 0 | J6: =IF(J37>0,J37*($B$62/100+1),0) -> 0 | ... Q6: =IF(Q37>0,Q37*($B$62/100+1),0) -> 0
A7: 5 | B7: Pantalón con elástico | C7: =IF(C38>0,C38*($B$62/100+1),0) -> 145.8 | D7: =IF(D38>0,D38*($B$62/100+1),0) -> 168.48 | E7: =IF(E38>0,E38*($B$62/100+1),0) -> 191.16 | F7: =IF(F38>0,F38*($B$62/100+1),0) -> 214.92 | G7: =IF(G38>0,G38*($B$62/100+1),0) -> 237.6 | H7: =IF(H38>0,H38*($B$62/100+1),0) -> 257.04 | I7: =IF(I38>0,I38*($B$62/100+1),0) -> 276.48 | J7: =IF(J38>0,J38*($B$62/100+1),0) -> 295.92 | ... Q7: =IF(Q38>0,Q38*($B$62/100+1),0) -> 0
A8: 6 | B8: Bermuda | C8: =IF(C39>0,C39*($B$62/100+1),0) -> 99.36 | D8: =IF(D39>0,D39*($B$62/100+1),0) -> 108 | E8: =IF(E39>0,E39*($B$62/100+1),0) -> 119.88 | F8: =IF(F39>0,F39*($B$62/100+1),0) -> 133.92 | G8: =IF(G39>0,G39*($B$62/100+1),0) -> 153.36 | H8: =IF(H39>0,H39*($B$62/100+1),0) -> 171.72 | I8: =IF(I39>0,I39*($B$62/100+1),0) -> 178.2 | J8: =IF(J39>0,J39*($B$62/100+1),0) -> 192.24 | ... Q8: =IF(Q39>0,Q39*($B$62/100+1),0) -> 0
A9: 7 | B9: Polera manga corta | C9: =IF(C40>0,C40*($B$62/100+1),0) -> 100.44 | D9: =IF(D40>0,D40*($B$62/100+1),0) -> 108 | E9: =IF(E40>0,E40*($B$62/100+1),0) -> 115.56 | F9: =IF(F40>0,F40*($B$62/100+1),0) -> 132.84 | G9: =IF(G40>0,G40*($B$62/100+1),0) -> 150.12 | H9: =IF(H40>0,H40*($B$62/100+1),0) -> 155.52 | I9: =IF(I40>0,I40*($B$62/100+1),0) -> 160.92 | J9: =IF(J40>0,J40*($B$62/100+1),0) -> 168.48 | L9: =IF(L40>0,L40*($B$62/100+1),0) -> 176.04 | M9: =IF(M40>0,M40*($B$62/100+1),0) -> 183.6 | N9: =IF(N40>0,N40*($B$62/100+1),0) -> 191.16 | O9: =IF(O40>0,O40*($B$62/100+1),0) -> 200.88 | P9: =IF(P40>0,P40*($B$62/100+1),0) -> 210.6 | Q9: =IF(Q40>0,Q40*($B$62/100+1),0) -> 231.12
A10: 8 | B10: Polera manga larga | C10: =IF(C41>0,C41*($B$62/100+1),0) -> 116.64 | D10: =IF(D41>0,D41*($B$62/100+1),0) -> 124.2 | E10: =IF(E41>0,E41*($B$62/100+1),0) -> 131.76 | F10: =IF(F41>0,F41*($B$62/100+1),0) -> 149.04 | G10: =IF(G41>0,G41*($B$62/100+1),0) -> 177.12 | H10: =IF(H41>0,H41*($B$62/100+1),0) -> 182.52 | I10: =IF(I41>0,I41*($B$62/100+1),0) -> 187.92 | J10: =IF(J41>0,J41*($B$62/100+1),0) -> 195.48 | L10: =IF(L41>0,L41*($B$62/100+1),0) -> 208.44 | M10: =IF(M41>0,M41*($B$62/100+1),0) -> 216 | N10: =IF(N41>0,N41*($B$62/100+1),0) -> 223.56 | O10: =IF(O41>0,O41*($B$62/100+1),0) -> 233.28 | P10: =IF(P41>0,P41*($B$62/100+1),0) -> 243 | Q10: =IF(Q41>0,Q41*($B$62/100+1),0) -> 263.52
A11: 9 | B11: Short | C11: =IF(C42>0,C42*($B$62/100+1),0) -> 65.88 | D11: =IF(D42>0,D42*($B$62/100+1),0) -> 70.2 | E11: =IF(E42>0,E42*($B$62/100+1),0) -> 74.52 | F11: =IF(F42>0,F42*($B$62/100+1),0) -> 77.76 | G11: =IF(G42>0,G42*($B$62/100+1),0) -> 81 | H11: =IF(H42>0,H42*($B$62/100+1),0) -> 86.4 | I11: =IF(I42>0,I42*($B$62/100+1),0) -> 97.2 | J11: =IF(J42>0,J42*($B$62/100+1),0) -> 105.84 | L11: =IF(L42>0,L42*($B$62/100+1),0) -> 113.4 | M11: =IF(M42>0,M42*($B$62/100+1),0) -> 119.88 | N11: =IF(N42>0,N42*($B$62/100+1),0) -> 126.36 | O11: =IF(O42>0,O42*($B$62/100+1),0) -> 131.76 | P11: =IF(P42>0,P42*($B$62/100+1),0) -> 141.48 | Q11: =IF(Q42>0,Q42*($B$62/100+1),0) -> 150.12
A12: 10 | B12: Calza corta | C12: =IF(C43>0,C43*($B$62/100+1),0) -> 84.24 | D12: =IF(D43>0,D43*($B$62/100+1),0) -> 92.88 | E12: =IF(E43>0,E43*($B$62/100+1),0) -> 101.52 | F12: =IF(F43>0,F43*($B$62/100+1),0) -> 110.16 | G12: =IF(G43>0,G43*($B$62/100+1),0) -> 118.8 | H12: =IF(H43>0,H43*($B$62/100+1),0) -> 127.44 | I12: =IF(I43>0,I43*($B$62/100+1),0) -> 136.08 | J12: =IF(J43>0,J43*($B$62/100+1),0) -> 144.72 | L12: =IF(L43>0,L43*($B$62/100+1),0) -> 153.36 | M12: =IF(M43>0,M43*($B$62/100+1),0) -> 162 | N12: =IF(N43>0,N43*($B$62/100+1),0) -> 172.8 | O12: =IF(O43>0,O43*($B$62/100+1),0) -> 183.6 | P12: =IF(P43>0,P43*($B$62/100+1),0) -> 193.32 | Q12: =IF(Q43>0,Q43*($B$62/100+1),0) -> 205.2
A13: 11 | B13: Calza larga | C13: =IF(C44>0,C44*($B$62/100+1),0) -> 117.72 | D13: =IF(D44>0,D44*($B$62/100+1),0) -> 131.76 | E13: =IF(E44>0,E44*($B$62/100+1),0) -> 145.8 | F13: =IF(F44>0,F44*($B$62/100+1),0) -> 156.6 | G13: =IF(G44>0,G44*($B$62/100+1),0) -> 167.4 | H13: =IF(H44>0,H44*($B$62/100+1),0) -> 246.24 | I13: =IF(I44>0,I44*($B$62/100+1),0) -> 270 | J13: =IF(J44>0,J44*($B$62/100+1),0) -> 282.96 | L13: =IF(L44>0,L44*($B$62/100+1),0) -> 298.08 | M13: =IF(M44>0,M44*($B$62/100+1),0) -> 302.4 | N13: =IF(N44>0,N44*($B$62/100+1),0) -> 305.64 | O13: =IF(O44>0,O44*($B$62/100+1),0) -> 313.2 | P13: =IF(P44>0,P44*($B$62/100+1),0) -> 329.4 | Q13: =IF(Q44>0,Q44*($B$62/100+1),0) -> 343.44
A14: 12 | B14: Pantalón para dama | C14: =IF(C45>0,C45*($B$62/100+1),0) -> 0 | D14: =IF(D45>0,D45*($B$62/100+1),0) -> 0 | E14: =IF(E45>0,E45*($B$62/100+1),0) -> 0 | F14: =IF(F45>0,F45*($B$62/100+1),0) -> 0 | G14: =IF(G45>0,G45*($B$62/100+1),0) -> 0 | H14: =IF(H45>0,H45*($B$62/100+1),0) -> 0 | I14: =IF(I45>0,I45*($B$62/100+1),0) -> 0 | J14: =IF(J45>0,J45*($B$62/100+1),0) -> 249.48 | ... Q14: =IF(Q45>0,Q45*($B$62/100+1),0) -> 340.2
A15: 13 | B15: Blusa manga corta | C15: =IF(C46>0,C46*($B$62/100+1),0) -> 70.2 | D15: =IF(D46>0,D46*($B$62/100+1),0) -> 76.68 | E15: =IF(E46>0,E46*($B$62/100+1),0) -> 82.08 | F15: =IF(F46>0,F46*($B$62/100+1),0) -> 97.2 | G15: =IF(G46>0,G46*($B$62/100+1),0) -> 108 | H15: =IF(H46>0,H46*($B$62/100+1),0) -> 115.56 | I15: =IF(I46>0,I46*($B$62/100+1),0) -> 117.72 | J15: =IF(J46>0,J46*($B$62/100+1),0) -> 123.12 | ... Q15: =IF(Q46>0,Q46*($B$62/100+1),0) -> 156.6
A16: 14 | B16: Blusa manga larga | C16: =IF(C47>0,C47*($B$62/100+1),0) -> 74.52 | D16: =IF(D47>0,D47*($B$62/100+1),0) -> 81 | E16: =IF(E47>0,E47*($B$62/100+1),0) -> 86.4 | F16: =IF(F47>0,F47*($B$62/100+1),0) -> 101.52 | G16: =IF(G47>0,G47*($B$62/100+1),0) -> 113.4 | H16: =IF(H47>0,H47*($B$62/100+1),0) -> 120.96 | I16: =IF(I47>0,I47*($B$62/100+1),0) -> 123.12 | J16: =IF(J47>0,J47*($B$62/100+1),0) -> 128.52 | ... Q16: =IF(Q47>0,Q47*($B$62/100+1),0) -> 164.16
A17: 15 | B17: Corbata con elástico | C17: =IF(C48>0,C48*($B$62/100+1),0) -> 21.6 | D17: =IF(D48>0,D48*($B$62/100+1),0) -> 0 | E17: =IF(E48>0,E48*($B$62/100+1),0) -> 0 | F17: =IF(F48>0,F48*($B$62/100+1),0) -> 0 | G17: =IF(G48>0,G48*($B$62/100+1),0) -> 0 | H17: =IF(H48>0,H48*($B$62/100+1),0) -> 0 | I17: =IF(I48>0,I48*($B$62/100+1),0) -> 0 | J17: =IF(J48>0,J48*($B$62/100+1),0) -> 0 | ... Q17: =IF(Q48>0,Q48*($B$62/100+1),0) -> 0
A18: 16 | B18: Falda plisada | C18: =IF(C49>0,C49*($B$62/100+1),0) -> 140.4 | D18: =IF(D49>0,D49*($B$62/100+1),0) -> 149.04 | E18: =IF(E49>0,E49*($B$62/100+1),0) -> 157.68 | F18: =IF(F49>0,F49*($B$62/100+1),0) -> 166.32 | G18: =IF(G49>0,G49*($B$62/100+1),0) -> 174.96 | H18: =IF(H49>0,H49*($B$62/100+1),0) -> 183.6 | I18: =IF(I49>0,I49*($B$62/100+1),0) -> 193.32 | J18: =IF(J49>0,J49*($B$62/100+1),0) -> 201.96 | L18: =IF(L49>0,L49*($B$62/100+1),0) -> 210.6 | M18: =IF(M49>0,M49*($B$62/100+1),0) -> 219.24 | N18: =IF(N49>0,N49*($B$62/100+1),0) -> 227.88 | O18: =IF(O49>0,O49*($B$62/100+1),0) -> 236.52 | P18: =IF(P49>0,P49*($B$62/100+1),0) -> 245.16 | Q18: =IF(Q49>0,Q49*($B$62/100+1),0) -> 253.8
A19: 17 | B19: Jamper | C19: =IF(C50>0,C50*($B$62/100+1),0) -> 118.8 | D19: =IF(D50>0,D50*($B$62/100+1),0) -> 131.76 | E19: =IF(E50>0,E50*($B$62/100+1),0) -> 144.72 | F19: =IF(F50>0,F50*($B$62/100+1),0) -> 157.68 | G19: =IF(G50>0,G50*($B$62/100+1),0) -> 170.64 | H19: =IF(H50>0,H50*($B$62/100+1),0) -> 183.6 | I19: =IF(I50>0,I50*($B$62/100+1),0) -> 0 | J19: =IF(J50>0,J50*($B$62/100+1),0) -> 0 | ... Q19: =IF(Q50>0,Q50*($B$62/100+1),0) -> 0
A20: 18 | B20: Vestido | C20: =IF(C51>0,C51*($B$62/100+1),0) -> 153.36 | D20: =IF(D51>0,D51*($B$62/100+1),0) -> 173.88 | E20: =IF(E51>0,E51*($B$62/100+1),0) -> 194.4 | F20: =IF(F51>0,F51*($B$62/100+1),0) -> 214.92 | G20: =IF(G51>0,G51*($B$62/100+1),0) -> 235.44 | H20: =IF(H51>0,H51*($B$62/100+1),0) -> 255.96 | I20: =IF(I51>0,I51*($B$62/100+1),0) -> 0 | J20: =IF(J51>0,J51*($B$62/100+1),0) -> 0 | ... Q20: =IF(Q51>0,Q51*($B$62/100+1),0) -> 0
A21: 19 | B21: Chompa cuello en V | C21: =IF(C52>0,C52*($B$62/100+1),0) -> 0 | D21: =IF(D52>0,D52*($B$62/100+1),0) -> 0 | E21: =IF(E52>0,E52*($B$62/100+1),0) -> 0 | F21: =IF(F52>0,F52*($B$62/100+1),0) -> 0 | G21: =IF(G52>0,G52*($B$62/100+1),0) -> 0 | H21: =IF(H52>0,H52*($B$62/100+1),0) -> 0 | I21: =IF(I52>0,I52*($B$62/100+1),0) -> 0 | J21: =IF(J52>0,J52*($B$62/100+1),0) -> 0 | ... Q21: =IF(Q52>0,Q52*($B$62/100+1),0) -> 0
A22: 20 | B22: Chaleco cuello en V | C22: =IF(C53>0,C53*($B$62/100+1),0) -> 0 | D22: =IF(D53>0,D53*($B$62/100+1),0) -> 0 | E22: =IF(E53>0,E53*($B$62/100+1),0) -> 0 | F22: =IF(F53>0,F53*($B$62/100+1),0) -> 0 | G22: =IF(G53>0,G53*($B$62/100+1),0) -> 0 | H22: =IF(H53>0,H53*($B$62/100+1),0) -> 0 | I22: =IF(I53>0,I53*($B$62/100+1),0) -> 0 | J22: =IF(J53>0,J53*($B$62/100+1),0) -> 0 | ... Q22: =IF(Q53>0,Q53*($B$62/100+1),0) -> 0
A23: 21 | B23: Chamarra de verano | C23: =IF(C54>0,C54*($B$62/100+1),0) -> 316.44 | D23: =IF(D54>0,D54*($B$62/100+1),0) -> 328.32 | E23: =IF(E54>0,E54*($B$62/100+1),0) -> 340.2 | F23: =IF(F54>0,F54*($B$62/100+1),0) -> 352.08 | G23: =IF(G54>0,G54*($B$62/100+1),0) -> 363.96 | H23: =IF(H54>0,H54*($B$62/100+1),0) -> 375.84 | I23: =IF(I54>0,I54*($B$62/100+1),0) -> 387.72 | J23: =IF(J54>0,J54*($B$62/100+1),0) -> 399.6 | L23: =IF(L54>0,L54*($B$62/100+1),0) -> 409.32 | M23: =IF(M54>0,M54*($B$62/100+1),0) -> 419.04 | N23: =IF(N54>0,N54*($B$62/100+1),0) -> 430.92 | O23: =IF(O54>0,O54*($B$62/100+1),0) -> 439.56 | P23: =IF(P54>0,P54*($B$62/100+1),0) -> 449.28 | Q23: =IF(Q54>0,Q54*($B$62/100+1),0) -> 460.08
A24: 22 | B24: Chamarra deportiva | C24: =IF(C55>0,C55*($B$62/100+1),0) -> 316.44 | D24: =IF(D55>0,D55*($B$62/100+1),0) -> 328.32 | E24: =IF(E55>0,E55*($B$62/100+1),0) -> 340.2 | F24: =IF(F55>0,F55*($B$62/100+1),0) -> 352.08 | G24: =IF(G55>0,G55*($B$62/100+1),0) -> 363.96 | H24: =IF(H55>0,H55*($B$62/100+1),0) -> 375.84 | I24: =IF(I55>0,I55*($B$62/100+1),0) -> 387.72 | J24: =IF(J55>0,J55*($B$62/100+1),0) -> 399.6 | L24: =IF(L55>0,L55*($B$62/100+1),0) -> 409.32 | M24: =IF(M55>0,M55*($B$62/100+1),0) -> 419.04 | N24: =IF(N55>0,N55*($B$62/100+1),0) -> 430.92 | O24: =IF(O55>0,O55*($B$62/100+1),0) -> 439.56 | P24: =IF(P55>0,P55*($B$62/100+1),0) -> 449.28 | Q24: =IF(Q55>0,Q55*($B$62/100+1),0) -> 460.08
A25: 23 | B25: Chamarra de invierno | C25: =IF(C56>0,C56*($B$62/100+1),0) -> 348.084 | D25: =IF(D56>0,D56*($B$62/100+1),0) -> 361.152 | E25: =IF(E56>0,E56*($B$62/100+1),0) -> 374.22 | F25: =IF(F56>0,F56*($B$62/100+1),0) -> 387.288 | G25: =IF(G56>0,G56*($B$62/100+1),0) -> 400.356 | H25: =IF(H56>0,H56*($B$62/100+1),0) -> 413.424 | I25: =IF(I56>0,I56*($B$62/100+1),0) -> 426.492 | J25: =IF(J56>0,J56*($B$62/100+1),0) -> 439.56 | L25: =IF(L56>0,L56*($B$62/100+1),0) -> 450.252 | M25: =IF(M56>0,M56*($B$62/100+1),0) -> 460.944 | N25: =IF(N56>0,N56*($B$62/100+1),0) -> 474.012 | O25: =IF(O56>0,O56*($B$62/100+1),0) -> 483.516 | P25: =IF(P56>0,P56*($B$62/100+1),0) -> 494.208 | Q25: =IF(Q56>0,Q56*($B$62/100+1),0) -> 506.088
A26: 24 | B26: Buso Deportivo | C26: =IF(C57>0,C57*($B$62/100+1),0) -> 218.16 | D26: =IF(D57>0,D57*($B$62/100+1),0) -> 241.92 | E26: =IF(E57>0,E57*($B$62/100+1),0) -> 265.68 | F26: =IF(F57>0,F57*($B$62/100+1),0) -> 289.44 | G26: =IF(G57>0,G57*($B$62/100+1),0) -> 313.2 | H26: =IF(H57>0,H57*($B$62/100+1),0) -> 336.96 | I26: =IF(I57>0,I57*($B$62/100+1),0) -> 362.88 | J26: =IF(J57>0,J57*($B$62/100+1),0) -> 389.88 | L26: =IF(L57>0,L57*($B$62/100+1),0) -> 410.4 | M26: =IF(M57>0,M57*($B$62/100+1),0) -> 424.44 | N26: =IF(N57>0,N57*($B$62/100+1),0) -> 438.48 | O26: =IF(O57>0,O57*($B$62/100+1),0) -> 452.52 | P26: =IF(P57>0,P57*($B$62/100+1),0) -> 470.88 | Q26: =IF(Q57>0,Q57*($B$62/100+1),0) -> 487.08
A27: 25 | B27: Polera de colores | C27: =IF(C58>0,C58*($B$62/100+1),0) -> 100.44 | D27: =IF(D58>0,D58*($B$62/100+1),0) -> 108 | E27: =IF(E58>0,E58*($B$62/100+1),0) -> 115.56 | F27: =IF(F58>0,F58*($B$62/100+1),0) -> 132.84 | G27: =IF(G58>0,G58*($B$62/100+1),0) -> 150.12 | H27: =IF(H58>0,H58*($B$62/100+1),0) -> 155.52 | I27: =IF(I58>0,I58*($B$62/100+1),0) -> 160.92 | J27: =IF(J58>0,J58*($B$62/100+1),0) -> 168.48 | L27: =IF(L58>0,L58*($B$62/100+1),0) -> 0 | M27: =IF(M58>0,M58*($B$62/100+1),0) -> 0 | N27: =IF(N58>0,N58*($B$62/100+1),0) -> 0 | O27: =IF(O58>0,O58*($B$62/100+1),0) -> 0 | P27: =IF(P58>0,P58*($B$62/100+1),0) -> 0 | Q27: =IF(Q58>0,Q58*($B$62/100+1),0) -> 0
A28: 26 | B28: Polera Bullying | C28: =IF(C59>0,C59*($B$62/100+1),0) -> 129.6 | D28: =IF(D59>0,D59*($B$62/100+1),0) -> 0 | E28: =IF(E59>0,E59*($B$62/100+1),0) -> 0 | F28: =IF(F59>0,F59*($B$62/100+1),0) -> 0 | G28: =IF(G59>0,G59*($B$62/100+1),0) -> 0 | H28: =IF(H59>0,H59*($B$62/100+1),0) -> 0 | I28: =IF(I59>0,I59*($B$62/100+1),0) -> 0 | J28: =IF(J59>0,J59*($B$62/100+1),0) -> 0 | L28: =IF(L59>0,L59*($B$62/100+1),0) -> 0 | M28: =IF(M59>0,M59*($B$62/100+1),0) -> 0 | N28: =IF(N59>0,N59*($B$62/100+1),0) -> 0 | O28: =IF(O59>0,O59*($B$62/100+1),0) -> 0 | P28: =IF(P59>0,P59*($B$62/100+1),0) -> 0 | Q28: =IF(Q59>0,Q59*($B$62/100+1),0) -> 0
A29: 27 | B29: Saco | C29: =IF(C60>0,C60*($B$62/100+1),0) -> 378 | D29: =IF(D60>0,D60*($B$62/100+1),0) -> 405 | E29: =IF(E60>0,E60*($B$62/100+1),0) -> 432 | F29: =IF(F60>0,F60*($B$62/100+1),0) -> 459 | G29: =IF(G60>0,G60*($B$62/100+1),0) -> 486 | H29: =IF(H60>0,H60*($B$62/100+1),0) -> 513 | I29: =IF(I60>0,I60*($B$62/100+1),0) -> 540 | J29: =IF(J60>0,J60*($B$62/100+1),0) -> 567 | L29: =IF(L60>0,L60*($B$62/100+1),0) -> 594 | M29: =IF(M60>0,M60*($B$62/100+1),0) -> 621 | N29: =IF(N60>0,N60*($B$62/100+1),0) -> 648 | O29: =IF(O60>0,O60*($B$62/100+1),0) -> 675 | P29: =IF(P60>0,P60*($B$62/100+1),0) -> 702 | Q29: =IF(Q60>0,Q60*($B$62/100+1),0) -> 729
A32: PESO DE MATERIA PRIMA ESTIMADO EN GRAMOS
A33: ITEM | B33: DETALLE | C33: 2 | D33: 4 | E33: 6 | F33: 8 | G33: 10 | H33: 12 | I33: 14 | J33: 16/34 | K33: 36/XS | L33: 38/S | M33: 40/M | N33: 42/L | O33: 44/XL | P33: 46/2XL | Q33: 48/3XL
A34: 1 | B34: Pantalón de vestir | C34: 0 | D34: 0 | E34: 0 | F34: 0 | G34: 0 | H34: 0 | I34: 0 | J34: 315 | K34: 335 | L34: 345 | M34: 360 | N34: 375 | O34: 385 | P34: 403 | Q34: 414 | R34: 430
A35: 2 | B35: Camisa manga corta | C35: 97 | D35: 104 | E35: 111 | F35: 118 | G35: 125 | H35: 132 | I35: 139 | J35: 146 | L35: 153 | M35: 160 | N35: 167 | O35: 174 | P35: 183 | Q35: 191
A36: 3 | B36: Camisa manga larga | C36: =C35+10 -> 107 | D36: =D35+10 -> 114 | E36: =E35+10 -> 121 | F36: =F35+10 -> 128 | G36: =G35+10 -> 135 | H36: =H35+10 -> 142 | I36: =I35+10 -> 149 | J36: =J35+10 -> 156 | L36: =L35+10 -> 163 | M36: =M35+10 -> 170 | N36: =N35+10 -> 177 | O36: =O35+10 -> 184 | P36: =P35+10 -> 193 | Q36: =Q35+10 -> 201
A37: 4 | B37: Corbata larga | C37: 0 | D37: 0 | E37: 0 | F37: 0 | G37: 0 | H37: 0 | I37: 0 | J37: 0 | K37: 37 | L37: 0 | M37: 0 | N37: 0 | O37: 0 | P37: 0 | Q37: 0
A38: 5 | B38: Pantalón con elástico | C38: 135 | D38: 156 | E38: 177 | F38: 199 | G38: 220 | H38: 238 | I38: 256 | J38: 274 | L38: 290 | M38: 0 | N38: 0 | O38: 0 | P38: 0 | Q38: 0
A39: 6 | B39: Bermuda | C39: =102-10 -> 92 | D39: =112-12 -> 100 | E39: 111 | F39: 124 | G39: =158-16 -> 142 | H39: =175-16 -> 159 | I39: 165 | J39: =194-16 -> 178 | L39: 196 | M39: 0 | N39: 0 | O39: 0 | P39: 0 | Q39: 0
A40: 7 | B40: Polera manga corta | C40: 93 | D40: 100 | E40: 107 | F40: 123 | G40: 139 | H40: 144 | I40: 149 | J40: =I40+7 -> 156 | L40: 163 | M40: 170 | N40: 177 | O40: 186 | P40: 195 | Q40: 214
A41: 8 | B41: Polera manga larga | C41: =C40+15 -> 108 | D41: =D40+15 -> 115 | E41: =E40+15 -> 122 | F41: =F40+15 -> 138 | G41: =G40+25 -> 164 | H41: =H40+25 -> 169 | I41: =I40+25 -> 174 | J41: =J40+25 -> 181 | L41: =L40+30 -> 193 | M41: =M40+30 -> 200 | N41: =N40+30 -> 207 | O41: =O40+30 -> 216 | P41: =P40+30 -> 225 | Q41: =Q40+30 -> 244
A42: 9 | B42: Short | C42: 61 | D42: 65 | E42: 69 | F42: 72 | G42: 75 | H42: 80 | I42: 90 | J42: 98 | L42: 105 | M42: 111 | N42: 117 | O42: 122 | P42: 131 | Q42: 139
A43: 10 | B43: Calza corta | C43: 78 | D43: 86 | E43: 94 | F43: 102 | G43: 110 | H43: 118 | I43: =H43+8 -> 126 | J43: =I43+8 -> 134 | L43: 142 | M43: 150 | N43: 160 | O43: 170 | P43: 179 | Q43: 190
A44: 11 | B44: Calza larga | C44: 109 | D44: 122 | E44: 135 | F44: 145 | G44: 155 | H44: 228 | I44: 250 | J44: 262 | L44: 276 | M44: 280 | N44: 283 | O44: 290 | P44: 305 | Q44: 318
A45: 12 | B45: Pantalón para dama | C45: 0 | D45: 0 | E45: 0 | F45: 0 | G45: 0 | H45: 0 | I45: 0 | J45: 231 | K45: 248 | L45: 265 | M45: 280 | N45: 292 | O45: 298 | P45: 305 | Q45: 315
A46: 13 | B46: Blusa manga corta | C46: 65 | D46: 71 | E46: 76 | F46: 90 | G46: 100 | H46: 107 | I46: 109 | J46: 114 | K46: 120 | L46: 122 | M46: 125 | N46: 127 | O46: 135 | P46: 140 | Q46: 145
A47: 14 | B47: Blusa manga larga | C47: =C46+4 -> 69 | D47: =D46+4 -> 75 | E47: =E46+4 -> 80 | F47: =F46+4 -> 94 | G47: =G46+5 -> 105 | H47: =H46+5 -> 112 | I47: =I46+5 -> 114 | J47: =J46+5 -> 119 | K47: =K46+5 -> 125 | L47: =L46+7 -> 129 | M47: =M46+7 -> 132 | N47: =N46+7 -> 134 | O47: =O46+7 -> 142 | P47: =P46+7 -> 147 | Q47: =Q46+7 -> 152
A48: 15 | B48: Corbata con elástico | C48: 20 | D48: 0 | E48: 0 | F48: 0 | G48: 0 | H48: 0 | I48: 0 | J48: 0 | K48: 0 | L48: 0 | M48: 0 | N48: 0 | O48: 0 | P48: 0 | Q48: 0
A49: 16 | B49: Falda plisada | C49: 130 | D49: 138 | E49: 146 | F49: 154 | G49: 162 | H49: 170 | I49: 179 | J49: 187 | L49: 195 | M49: 203 | N49: 211 | O49: 219 | P49: 227 | Q49: 235
A50: 17 | B50: Jamper | C50: 110 | D50: 122 | E50: 134 | F50: 146 | G50: 158 | H50: 170 | I50: 0 | J50: 0 | K50: 0 | L50: 0 | M50: 0 | N50: 0 | O50: 0 | P50: 0 | Q50: 0
A51: 18 | B51: Vestido | C51: 142 | D51: 161 | E51: 180 | F51: 199 | G51: 218 | H51: 237 | I51: 0 | J51: 0 | K51: 0 | L51: 0 | M51: 0 | N51: 0 | O51: 0 | P51: 0 | Q51: 0
A52: 19 | B52: Chompa cuello en V
A53: 20 | B53: Chaleco cuello en V
A54: 21 | B54: Chamarra de verano | C54: 293 | D54: 304 | E54: 315 | F54: 326 | G54: 337 | H54: 348 | I54: 359 | J54: 370 | L54: 379 | M54: 388 | N54: 399 | O54: 407 | P54: 416 | Q54: 426
A55: 22 | B55: Chamarra deportiva | C55: 293 | D55: 304 | E55: 315 | F55: 326 | G55: 337 | H55: 348 | I55: 359 | J55: 370 | L55: 379 | M55: 388 | N55: 399 | O55: 407 | P55: 416 | Q55: 426
A56: 23 | B56: Chamarra de invierno | C56: =C54*1.1 -> 322.3 | D56: =D54*1.1 -> 334.4 | E56: =E54*1.1 -> 346.5 | F56: =F54*1.1 -> 358.6 | G56: =G54*1.1 -> 370.7 | H56: =H54*1.1 -> 382.8 | I56: =I54*1.1 -> 394.9 | J56: =J54*1.1 -> 407 | L56: =L54*1.1 -> 416.9 | M56: =M54*1.1 -> 426.8 | N56: =N54*1.1 -> 438.9 | O56: =O54*1.1 -> 447.7 | P56: =P54*1.1 -> 457.6 | Q56: =Q54*1.1 -> 468.6
A57: 24 | B57: Buso Deportivo | C57: 202 | D57: 224 | E57: 246 | F57: 268 | G57: 290 | H57: 312 | I57: 336 | J57: 361 | L57: 380 | M57: 393 | N57: 406 | O57: 419 | P57: 436 | Q57: 451
A58: 25 | B58: Polera de colores | C58: 93 | D58: 100 | E58: 107 | F58: 123 | G58: 139 | H58: 144 | I58: 149 | J58: 156
A59: 26 | B59: Polera Bullying | C59: 120
A60: 27 | B60: Saco | C60: 350 | D60: =C60+25 -> 375 | E60: =D60+25 -> 400 | F60: =E60+25 -> 425 | G60: =F60+25 -> 450 | H60: =G60+25 -> 475 | I60: =H60+25 -> 500 | J60: =I60+25 -> 525 | L60: =J60+25 -> 550 | M60: =L60+25 -> 575 | N60: =M60+25 -> 600 | O60: =N60+25 -> 625 | P60: =O60+25 -> 650 | Q60: =P60+25 -> 675
A62: Merma | B62: 8 | C62: %
B64: Peso Polar Chamarras | C64: =D64*0.95 -> 126.79549 | D64: =E64*0.95 -> 133.46894 | E64: =F64*0.95 -> 140.49362 | F64: =G64*0.95 -> 147.88802 | G64: =H64*0.95 -> 155.6716 | H64: =I64*0.95 -> 163.86485 | I64: =J64*0.95 -> 172.48931 | J64: =K64*0.95 -> 181.5677 | ... P64: =Q64*0.95 -> 247 | Q64: 260
C65: 360 | D65: 380 | E65: 400 | F65: 420 | G65: 440 | H65: 465 | I65: 490 | J65: 515 | K65: 540 | L65: 565 | M65: 590 | N65: 615 | O65: 640 | P65: 665 | Q65: 690

Sheet Acc
C1: 1 | D1: =C1+1 -> 2 | E1: =D1+1 -> 3 | F1: =E1+1 -> 4 | G1: =F1+1 -> 5 | H1: =G1+1 -> 6 | I1: =H1+1 -> 7 | J1: =I1+1 -> 8 | K1: =J1+1 -> 9 | ... AA1: =Z1+1 -> 25 | AB1: 26 | AC1: 27 | AD1: 28 | AE1: 29 | AF1: 30 | AG1: 31 | AH1: =AG1+1 -> 32 | AI1: 33 | AJ1: 34 | AK1: 35 | AL1: 36 | AM1: 37 | AN1: 38
A2: DETALLE | B2: ITEM | C2: Botamanga (par) | D2: Cuello | E2: Elastico para berm. y pant. | F2: Elastico Short o buzo | G2: Cinta Antideslizante | H2: Botones Pantalon | I2: Boton de 4 huecos para polo | J2: Boton de chamarra | K2: Entretela de chamarra | L2: Entretela de Camisa | M2: Broche | N2: Cierre corto (pantalon) | O2: Cierre Largo (Chamarra) | P2: Forro de chamarra | Q2: Malla para buzo | R2: Bordado escudo | S2: Bordado espalda Chamarra | T2: Hebilla de falda | U2: Cordon de buzo y short | V2: Campana para buso y short | W2: Bolsa de Polipropileno | X2: Etiqueta de Marca | Y2: Etiqueta de Talla | Z2: Etiqueta de cuidados | AA2: Hilo Tex 24 polyester | AB2: Vinilo para shorts | AC2: Vinilo Calzas | AD2: Serigrafia escudo polera | AE2: Serigrafia rectangulo polera, espalda | AF2: Ojal Grande | AG2: Ojal Pequeño | AH2: Serigrafía calza | AI2: Entretela para pantalon | AJ2: Elastico redondo | AK2: Atracado | AL2: Entretela Corbata | AM2: Serigrafia polera colores | AN2: Serigrafia Bullying | AP2: Total De Accesorios
A3: Pantalón de vestir | B3: 1 | G3: =$G$37 -> 0 | L3: =$G$42 -> 1.8 | M3: =$G$43 -> 0.4 | N3: =$G$44 -> 2 | W3: =$G$53 -> 0.22 | X3: =$G$54 -> 1.4 | Y3: =$G$55 -> 0.12 | Z3: =$G$56 -> 0.5 | AA3: =$G$57 -> 0.6 | AI3: =$G$65 -> 0.75 | AK3: =$G$67*3 -> 0.6 | AM3: =$G$69 -> 0 | AN3: =$G$70 -> 0 | AO3: =$G$73 -> 0 | AP3: =SUM(C3:AO3) -> 8.39
A4: Camisa manga corta | B4: =B3+1 -> 2 | I4: =$G$39*7 -> 2.9166667 | L4: =$G$42 -> 1.8 | R4: =$G$48 -> 5 | W4: =$G$53 -> 0.22 | X4: =$G$54 -> 1.4 | Y4: =$G$55 -> 0.12 | Z4: =$G$56 -> 0.5 | AA4: =$G$57 -> 0.6 | AG4: =$G$63*7 -> 2.1 | AM4: =$G$69 -> 0 | AN4: =$G$70 -> 0 | AO4: =$G$73 -> 0 | AP4: =SUM(C4:AO4) -> 14.656667
A5: Camisa manga larga | B5: 3 | I5: =$G$39*9 -> 3.75 | L5: =$G$42 -> 1.8 | R5: =$G$48 -> 5 | W5: =$G$53 -> 0.22 | X5: =$G$54 -> 1.4 | Y5: =$G$55 -> 0.12 | Z5: =$G$56 -> 0.5 | AA5: =$G$57 -> 0.6 | AG5: =$G$63*9 -> 2.7 | AM5: =$G$69 -> 0 | AN5: =$G$70 -> 0 | AO5: =$G$73 -> 0 | AP5: =SUM(C5:AO5) -> 16.09
A6: Corbata larga | B6: 4 | AL6: =$G$68 -> 0.75 | AM6: =$G$69 -> 0 | AN6: =$G$70 -> 0 | AO6: =$G$73 -> 0 | AP6: =SUM(C6:AO6) -> 0.75
A7: Pantalón con elástico | B7: =B6+1 -> 5 | E7: =$G$35 -> 0.36 | M7: =$G$43 -> 0.4 | N7: =$G$44 -> 2 | W7: =$G$53 -> 0.22 | X7: =$G$54 -> 1.4 | Y7: =$G$55 -> 0.12 | Z7: =$G$56 -> 0.5 | AA7: =$G$57 -> 0.6 | AI7: =$G$65/2 -> 0.375 | AK7: =$G$67*10 -> 2 | AM7: =$G$69 -> 0 | AN7: =$G$70 -> 0 | AO7: =$G$73 -> 0 | AP7: =SUM(C7:AO7) -> 7.975
A8: Bermuda | B8: =B7+1 -> 6 | E8: =$G$35 -> 0.36 | M8: =$G$43 -> 0.4 | N8: =$G$44 -> 2 | W8: =$G$53 -> 0.22 | X8: =$G$54 -> 1.4 | Y8: =$G$55 -> 0.12 | Z8: =$G$56 -> 0.5 | AA8: =$G$57 -> 0.6 | AI8: =$G$65 -> 0.75 | AK8: =$G$67*10 -> 2 | AM8: =$G$69 -> 0 | AN8: =$G$70 -> 0 | AO8: =$G$73 -> 0 | AP8: =SUM(C8:AO8) -> 8.35
A9: Polera manga corta/larga | B9: 7-8 | C9: =$G$33 -> 3.5 | D9: =$G$34 -> 2.7 | W9: =$G$53 -> 0.22 | X9: =$G$54 -> 1.4 | Y9: =$G$55 -> 0.12 | Z9: =$G$56 -> 0.5 | AA9: =$G$57 -> 0.6 | AD9: =$G$60 -> 5 | AE9: =$G$61 -> 7 | AM9: =$G$69 -> 0 | AN9: =$G$70 -> 0 | AO9: =$G$73 -> 0 | AP9: =SUM(C9:AO9) -> 21.04
A10: Short | B10: 9 | F10: =$G$36 -> 0.216 | W10: =$G$53 -> 0.22 | X10: =$G$54 -> 1.4 | Y10: =$G$55 -> 0.12 | Z10: =$G$56 -> 0.5 | AA10: =$G$57 -> 0.6 | AB10: =$G$58 -> 4.55 | AM10: =$G$69 -> 0 | AN10: =$G$70 -> 0 | AO10: =$G$73 -> 0 | AP10: =SUM(C10:AO10) -> 7.606
A11: Calza corta/larga | B11: 10-11 | W11: =$G$53 -> 0.22 | X11: =$G$54 -> 1.4 | Y11: =$G$55 -> 0.12 | Z11: =$G$56 -> 0.5 | AA11: =$G$57 -> 0.6 | AC11: =$G$59 -> 3.3 | AM11: =$G$69 -> 0 | AN11: =$G$70 -> 0 | AO11: =$G$73 -> 0 | AP11: =SUM(C11:AO11) -> 6.14
A12: Pantalón para dama | B12: 12 | M12: =$G$43 -> 0.4 | N12: =$G$44 -> 2 | W12: =$G$53 -> 0.22 | X12: =$G$54 -> 1.4 | Y12: =$G$55 -> 0.12 | Z12: =$G$56 -> 0.5 | AA12: =$G$57 -> 0.6 | AI12: =$G$65 -> 0.75 | AK12: =$G$67*10 -> 2 | AM12: =$G$69 -> 0 | AN12: =$G$70 -> 0 | AO12: =$G$73 -> 0 | AP12: =SUM(C12:AO12) -> 7.99
A13: Blusa manga corta | B13: =B12+1 -> 13 | I13: =$G$39*7 -> 2.9166667 | L13: =$G$42 -> 1.8 | R13: =$G$48 -> 5 | W13: =$G$53 -> 0.22 | X13: =$G$54 -> 1.4 | Y13: =$G$55 -> 0.12 | Z13: =$G$56 -> 0.5 | AA13: =$G$57 -> 0.6 | AG13: =$G$63*7 -> 2.1 | AM13: =$G$69 -> 0 | AN13: =$G$70 -> 0 | AO13: =$G$73 -> 0 | AP13: =SUM(C13:AO13) -> 14.656667
A14: Blusa manga larga | B14: =B13+1 -> 14 | I14: =$G$39*7 -> 2.9166667 | L14: =$G$42 -> 1.8 | R14: =$G$48 -> 5 | W14: =$G$53 -> 0.22 | X14: =$G$54 -> 1.4 | Y14: =$G$55 -> 0.12 | Z14: =$G$56 -> 0.5 | AA14: =$G$57 -> 0.6 | AG14: =$G$63*7 -> 2.1 | AM14: =$G$69 -> 0 | AN14: =$G$70 -> 0 | AO14: =$G$73 -> 0 | AP14: =SUM(C14:AO14) -> 14.656667
A15: Corbata con elástico | B15: =B14+1 -> 15 | W15: =$G$53 -> 0.22 | X15: =$G$54 -> 1.4 | Y15: =$G$55 -> 0.12 | Z15: =$G$56 -> 0.5 | AA15: =$G$57 -> 0.6 | AJ15: =$G$66 -> 0.36 | AL15: =$G$68 -> 0.75 | AM15: =$G$69 -> 0 | AN15: =$G$70 -> 0 | AO15: =$G$73 -> 0 | AP15: =SUM(C15:AO15) -> 3.95
A16: Falda plisada | B16: =B15+1 -> 16 | H16: =$G$38*2 -> 0.83333333 | L16: =$G$42 -> 1.8 | T16: =$G$50 -> 5.6 | W16: =$G$53 -> 0.22 | X16: =$G$54 -> 1.4 | Y16: =$G$55 -> 0.12 | Z16: =$G$56 -> 0.5 | AA16: =$G$57 -> 0.6 | AF16: =$G$62*2 -> 1.6 | AM16: =$G$69 -> 0 | AN16: =$G$70 -> 0 | AO16: =$G$73 -> 0 | AP16: =SUM(C16:AO16) -> 12.673333
A17: Jamper | B17: =B16+1 -> 17 | H17: =$G$38*2 -> 0.83333333 | R17: =$G$48 -> 5 | W17: =$G$53 -> 0.22 | X17: =$G$54 -> 1.4 | Y17: =$G$55 -> 0.12 | Z17: =$G$56 -> 0.5 | AA17: =$G$57 -> 0.6 | AF17: =$G$62*2 -> 1.6 | AM17: =$G$69 -> 0 | AN17: =$G$70 -> 0 | AO17: =$G$73 -> 0 | AP17: =SUM(C17:AO17) -> 10.273333
A18: Vestido | B18: =B17+1 -> 18 | H18: =$G$38*2 -> 0.83333333 | R18: =$G$48 -> 5 | W18: =$G$53 -> 0.22 | X18: =$G$54 -> 1.4 | Y18: =$G$55 -> 0.12 | Z18: =$G$56 -> 0.5 | AA18: =$G$57 -> 0.6 | AF18: =$G$62*2 -> 1.6 | AM18: =$G$69 -> 0 | AN18: =$G$70 -> 0 | AO18: =$G$73 -> 0 | AP18: =SUM(C18:AO18) -> 10.273333
A19: Chompa cuello en V | B19: =B18+1 -> 19 | R19: =$G$48 -> 5 | W19: =$G$53 -> 0.22 | X19: =$G$54 -> 1.4 | Y19: =$G$55 -> 0.12 | Z19: =$G$56 -> 0.5 | AA19: =$G$57 -> 0.6 | AM19: =$G$69 -> 0 | AN19: =$G$70 -> 0 | AO19: =$G$73 -> 0 | AP19: =SUM(C19:AO19) -> 7.84
A20: Chaleco cuello en V | B20: =B19+1 -> 20 | R20: =$G$48 -> 5 | W20: =$G$53 -> 0.22 | X20: =$G$54 -> 1.4 | Y20: =$G$55 -> 0.12 | Z20: =$G$56 -> 0.5 | AA20: =$G$57 -> 0.6 | AM20: =$G$69 -> 0 | AN20: =$G$70 -> 0 | AO20: =$G$73 -> 0 | AP20: =SUM(C20:AO20) -> 7.84
A21: Chamarra de verano | B21: =B20+1 -> 21 | J21: =$G$40*3 -> 3.36 | K21: =$G$41 -> 3.6 | O21: =$G$45 -> 2.9166667 | P21: =$G$46 -> 11.25 | R21: =$G$48 -> 5 | S21: =$G$49 -> 7 | U21: =$G$51 -> 1.52 | V21: =$G$52 -> 0.32 | W21: =$G$53 -> 0.22 | X21: =$G$54 -> 1.4 | Y21: =$G$55 -> 0.12 | Z21: =$G$56 -> 0.5 | AA21: =$G$57 -> 0.6 | AM21: =$G$69 -> 0 | AN21: =$G$70 -> 0 | AO21: =$G$73 -> 0 | AP21: =SUM(C21:AO21) -> 37.806667
A22: Chamarra deportiva | B22: =B21+1 -> 22 | J22: =$G$40*3 -> 3.36 | K22: =$G$41 -> 3.6 | O22: =$G$45 -> 2.9166667 | P22: =$G$46 -> 11.25 | R22: =$G$48 -> 5 | S22: =$G$49 -> 7 | U22: =$G$51 -> 1.52 | V22: =$G$52 -> 0.32 | W22: =$G$53 -> 0.22 | X22: =$G$54 -> 1.4 | Y22: =$G$55 -> 0.12 | Z22: =$G$56 -> 0.5 | AA22: =$G$57 -> 0.6 | AM22: =$G$69 -> 0 | AN22: =$G$70 -> 0 | AO22: =$G$73 -> 0 | AP22: =SUM(C22:AO22) -> 37.806667
A23: Chamarra de invierno | B23: =B22+1 -> 23 | J23: =$G$40*3 -> 3.36 | K23: =$G$41 -> 3.6 | O23: =$G$45 -> 2.9166667 | P23: =$G$46 -> 11.25 | R23: =$G$48 -> 5 | S23: =$G$49 -> 7 | U23: =$G$51 -> 1.52 | V23: =$G$52 -> 0.32 | W23: =$G$53 -> 0.22 | X23: =$G$54 -> 1.4 | Y23: =$G$55 -> 0.12 | Z23: =$G$56 -> 0.5 | AA23: =$G$57 -> 0.6 | AM23: =$G$69 -> 0 | AN23: =$G$70 -> 0 | AO23: =$G$73 -> 0 | AP23: =SUM(C23:AO23) -> 37.806667
A24: Buso Deportivo | B24: =B23+1 -> 24 | F24: =$G$36 -> 0.216 | R24: =$G$48 -> 5 | U24: =$G$51 -> 1.52 | V24: =$G$52 -> 0.32 | W24: =$G$53 -> 0.22 | X24: =$G$54 -> 1.4 | Y24: =$G$55 -> 0.12 | Z24: =$G$56 -> 0.5 | AA24: =$G$57 -> 0.6 | AM24: =$G$69 -> 0 | AN24: =$G$70 -> 0 | AO24: =$G$73 -> 0 | AP24: =SUM(C24:AO24) -> 9.896
A25: Polera de colores | B25: =B24+1 -> 25 | C25: =$G$33 -> 3.5 | D25: =$G$34 -> 2.7 | W25: =$G$53 -> 0.22 | X25: =$G$54 -> 1.4 | Y25: =$G$55 -> 0.12 | Z25: =$G$56 -> 0.5 | AA25: =$G$57 -> 0.6 | AM25: =$G$69 -> 0 | AN25: =$G$70 -> 0 | AO25: =$G$73 -> 0 | AP25: =SUM(C25:AO25) -> 9.04
A26: Polera Bullying | B26: =B25+1 -> 26 | C26: =$G$33 -> 3.5 | D26: =$G$34 -> 2.7 | W26: =$G$53 -> 0.22 | X26: =$G$54 -> 1.4 | Y26: =$G$55 -> 0.12 | Z26: =$G$56 -> 0.5 | AA26: =$G$57 -> 0.6 | AM26: =$G$69 -> 0 | AN26: =$G$70 -> 0 | AO26: =$G$73 -> 0 | AP26: =SUM(C26:AO26) -> 9.04
A27: Sacos | B27: =B26+1 -> 27 | H27: =$G$38*2 -> 0.83333333 | K27: =$G$41 -> 3.6 | P27: =$G$46 -> 11.25 | R27: =$G$48 -> 5 | W27: =$G$53 -> 0.22 | X27: =$G$54 -> 1.4 | Y27: =$G$55 -> 0.12 | Z27: =$G$56 -> 0.5 | AA27: =$G$57 -> 0.6 | AM27: =$G$69 -> 0 | AN27: =$G$70 -> 0 | AO27: =$G$73 -> 0 | AP27: =SUM(C27:AO27) -> 23.523333
C28: =$G$33 -> 3.5 | D28: =$G$34 -> 2.7 | E28: =$G$35 -> 0.36 | F28: =$G$36 -> 0.216 | G28: =$G$37 -> 0 | H28: =$G$38 -> 0.41666667 | I28: =$G$39 -> 0.41666667 | J28: =$G$40 -> 1.12 | K28: =$G$41 -> 3.6 | L28: =$G$42 -> 1.8 | M28: =$G$43 -> 0.4 | N28: =$G$44 -> 2 | O28: =$G$45 -> 2.9166667 | P28: =$G$46 -> 11.25 | Q28: =$G$47 -> 0 | R28: =$G$48 -> 5 | S28: =$G$49 -> 7 | T28: =$G$50 -> 5.6 | U28: =$G$51 -> 1.52 | V28: =$G$52 -> 0.32 | W28: =$G$53 -> 0.22 | X28: =$G$54 -> 1.4 | Y28: =$G$55 -> 0.12 | Z28: =$G$56 -> 0.5 | AA28: =$G$57 -> 0.6 | AB28: =$G$58 -> 4.55 | AC28: =$G$59 -> 3.3 | AD28: =$G$60 -> 5 | AE28: =$G$61 -> 7 | AF28: =$G$62 -> 0.8 | AG28: =$G$63 -> 0.3 | AH28: =$G$64 -> 8 | AI28: =$G$65 -> 0.75 | AJ28: =$G$66 -> 0.36 | AK28: =$G$67 -> 0.2 | AL28: =$G$68 -> 0.75 | AM28: =$G$69 -> 0 | AN28: =$G$70 -> 0 | AO28: =$G$73 -> 0 | AP28: =SUM(C28:AO28) -> 83.986
A32: DESCRIPCION | B32: CODIGO | C32: UNIDAD DE COMPRA | D32: Cantidad x "unidad de compra" | E32: COSTO "Unidad de Compra" Bs. | F32: COSTO Unitario Bs. | G32: Costo de Uso en prendas | H32: OJALES | I32: Unidades que se usan por prenda | J32: Unidades por cada metro | K32: Costo por cm2
A33: Botamanga (par) | B33: 1 | C33: PAR | D33: par | F33: 3.5 | G33: 3.5 | I33: 2
A34: Cuello | B34: =B33+1 -> 2 | D34: 1 | F34: 2.7 | G34: 2.7 | I34: 1
A35: Elastico para berm. y pant. | B35: =B34+1 -> 3 | C35: metro | D35: 1 | E35: 0.36 | F35: =E35/D35 -> 0.36 | G35: =Tabla2[[#This Row],[COSTO Unitario Bs.]]*I35 -> 0.36 | I35: 1
A36: Elastico Short o buzo | B36: =B35+1 -> 4 | C36: metro | D36: 1 | E36: 0.36 | F36: =E36/D36 -> 0.36 | G36: 0.216 | I36: 1
A37: Cinta Antideslizante | B37: =B36+1 -> 5 | C37: metro | D37: 1 | E37: 0 | F37: =E37/D37 -> 0 | G37: =Tabla2[[#This Row],[COSTO Unitario Bs.]]*I37 -> 0 | I37: 1
A38: Botones Pantalon | B38: =B37+1 -> 6 | D38: 144 | E38: 60 | F38: =Tabla2[[#This Row],[COSTO "Unidad de Compra" Bs.]]/Tabla2[[#This Row],[Cantidad x "unidad de compra"]] -> 0.41666667 | G38: =Tabla2[[#This Row],[COSTO Unitario Bs.]]*I38 -> 0.41666667 | H38: =3*1 -> 3 | I38: 1
A39: Boton de 4 huecos para polo | B39: =B38+1 -> 7 | C39: Gruesa | D39: 144 | E39: 60 | F39: =E39/D39 -> 0.41666667 | G39: =Tabla2[[#This Row],[COSTO Unitario Bs.]] -> 0.41666667 | H39: =7*1 -> 7 | I39: 7
A40: Boton de chamarra | B40: =B39+1 -> 8 | D40: 1000 | E40: 280 | F40: =E40/D40 -> 0.28 | G40: =F40*I40 -> 1.12 | I40: 4
A41: Entretela de chamarra | B41: =B40+1 -> 9 | C41: metro | D41: 1 | E41: 18 | F41: =E41/D41 -> 18 | G41: =Tabla2[[#This Row],[COSTO Unitario Bs.]]/J41 -> 3.6 | I41: 1 | J41: 5 | K41: 0.0015
A42: Entretela de Camisa | B42: =B41+1 -> 10 | C42: metro | D42: 50 | E42: 900 | F42: =E42/D42 -> 18 | G42: =Tabla2[[#This Row],[COSTO Unitario Bs.]]/J42 -> 1.8 | I42: 1 | J42: 10 | K42: 0.0015
A43: Broche | B43: =B42+1 -> 11 | C43: caja | D43: 200 | E43: 80 | F43: =E43/D43 -> 0.4 | G43: =Tabla2[[#This Row],[COSTO Unitario Bs.]]*I43 -> 0.4 | I43: 1
A44: Cierre corto (pantalon) | B44: =B43+1 -> 12 | C44: paquete | D44: 100 | E44: 200 | F44: =E44/D44 -> 2 | G44: =F44 -> 2
A45: Cierre Largo (Chamarra) | B45: =B44+1 -> 13 | C45: paquete | D45: 120 | E45: 350 | F45: =E45/D45 -> 2.9166667 | G45: =F45 -> 2.9166667 | I45: 1
A46: Forro de chamarra | B46: =B45+1 -> 14 | C46: uso | D46: 1 | E46: 7.5 | F46: =E46/D46 -> 7.5 | G46: =F46*I46 -> 11.25 | I46: 1.5
A47: Malla para buzo | B47: =B46+1 -> 15
A48: Bordado escudo | B48: =B47+1 -> 16 | C48: Unidad | D48: 1 | E48: 5 | F48: =E48/D48 -> 5 | G48: =Tabla2[[#This Row],[COSTO Unitario Bs.]]*I48 -> 5 | I48: 1
A49: Bordado espalda Chamarra | B49: =B48+1 -> 17 | D49: 1 | E49: 7 | F49: =Tabla2[[#This Row],[COSTO "Unidad de Compra" Bs.]] -> 7 | G49: =Tabla2[[#This Row],[COSTO Unitario Bs.]]*I49 -> 7 | I49: 1
A50: Hebilla de falda | B50: =B49+1 -> 18 | C50: caja | D50: 100 | E50: 280 | F50: =E50/D50 -> 2.8 | G50: =F50*I50 -> 5.6 | I50: 2
A51: Cordon de buzo y short | B51: =B50+1 -> 19 | C51: metros | D51: 25 | E51: 38 | F51: =E51/D51 -> 1.52 | G51: =F51 -> 1.52 | I51: 1
A52: Campana para buso y short | B52: =B51+1 -> 20 | C52: bolsa | D52: 1000 | E52: 160 | F52: =E52/D52 -> 0.16 | G52: =F52*I52 -> 0.32 | I52: 2
A53: Bolsa de Polipropileno | B53: =B52+1 -> 21 | C53: Ciento | D53: 100 | E53: 22 | F53: =E53/D53 -> 0.22 | G53: =F53*I53 -> 0.22 | I53: 1
A54: Etiqueta de Marca | B54: =B53+1 -> 22 | C54: Mil | D54: 1000 | E54: 1400 | F54: =E54/D54 -> 1.4 | G54: =F54 -> 1.4 | I54: 1
A55: Etiqueta de Talla | B55: =B54+1 -> 23 | C55: Mil | D55: 100 | E55: 12 | F55: =E55/D55 -> 0.12 | G55: =F55 -> 0.12 | I55: 1
A56: Etiqueta de cuidados | B56: =B55+1 -> 24 | C56: Mil | D56: 1000 | E56: 500 | F56: =E56/D56 -> 0.5 | G56: =F56 -> 0.5 | I56: 1
A57: Hilo Tex 24 polyester | B57: =B56+1 -> 25 | C57: yardas | D57: 1000 | E57: 6 | F57: =E57/D57 -> 0.006 | G57: =Tabla2[[#This Row],[COSTO Unitario Bs.]]*I57 -> 0.6 | I57: 100
A58: Vinilo para shorts | B58: 26 | C58: Unidad | F58: 0.035 | G58: =F58*130 -> 4.55 | I58: 130 cm2
A59: Vinilo Calzas | B59: 27 | C59: Unidad | F59: 0.055 | G59: =F59*60 -> 3.3 | I59: 60 cm2
A60: Serigrafia escudo polera | B60: 28 | C60: Unidad | D60: 1 | E60: 5 | F60: =E60/D60 -> 5 | G60: =F60 -> 5 | I60: 1
A61: Serigrafia rectangulo polera, espalda | B61: 29 | C61: Unidad | D61: 1 | E61: 7 | F61: =E61/D61 -> 7 | G61: =F61 -> 7 | I61: 1
A62: Ojal grande | B62: 30 | C62: Unidad | D62: 1 | E62: 0.8 | F62: =E62/D62 -> 0.8 | G62: =F62 -> 0.8 | H62: 1
A63: Ojal Pequeño | B63: 31 | C63: Unidad | D63: 1 | E63: 0.3 | F63: =E63/D63 -> 0.3 | G63: =F63 -> 0.3 | H63: 1
A64: Serigrafía calza | B64: =B63+1 -> 32 | C64: Unidad | D64: 1 | E64: 8 | F64: 8 | G64: 8 | H64: 1
A65: Entretela para pantalon | B65: 33 | C65: metro | D65: 50 | E65: 900 | F65: =E65/D65 -> 18 | G65: =500*K65 -> 0.75 | H65: =7*1 -> 7 | I65: 500 cm2 | K65: 0.0015
A66: Elastico redondo | B66: 34 | C66: metro | D66: 1 | E66: 0.36 | F66: =E66/D66 -> 0.36 | G66: =F66 -> 0.36 | I66: 1 metro
A67: Atracado | B67: 35 | C67: unidad | D67: 1 | E67: 0.2 | F67: =E67/D67 -> 0.2 | G67: =F67 -> 0.2
A68: Entretela Corbata | B68: 36 | C68: Unidad | D68: 1 | F68: 0.0015 | G68: =Tabla2[[#This Row],[COSTO Unitario Bs.]]*500 -> 0.75 | I68: 500 cm2 | K68: 0.0015
A69: Serigrafia polera colores | B69: 37 | C69: Unidad | D69: 1 | F69: =E69/D69 -> 0 | G69: =F69 -> 0
A70: Serigrafia Bullying | B70: 38 | C70: Unidad | D70: 1 | F70: =E70/D70 -> 0 | G70: =F70 -> 0
D73: =$G$33 -> 3.5
D74: =$G$34 -> 2.7
D75: =$G$35 -> 0.36
D76: =$G$36 -> 0.216
D77: =$G$37 -> 0
D78: =$G$38 -> 0.41666667
D79: =$G$39 -> 0.41666667
D80: =$G$40 -> 1.12
D81: =$G$41 -> 3.6
D82: =$G$42 -> 1.8
D83: =$G$43 -> 0.4
D84: =$G$44 -> 2
D85: =$G$45 -> 2.9166667
D86: =$G$46 -> 11.25
D87: =$G$47 -> 0
D88: =$G$48 -> 5
D89: =$G$49 -> 7
D90: =$G$50 -> 5.6
D91: =$G$51 -> 1.52
D92: =$G$52 -> 0.32
D93: =$G$53 -> 0.22
D94: =$G$54 -> 1.4
D95: =$G$55 -> 0.12
D96: =$G$56 -> 0.5
D97: =$G$57 -> 0.6
D98: =$G$58 -> 4.55
D99: =$G$59 -> 3.3
D100: =$G$60 -> 5
D101: =$G$61 -> 7
D102: =$G$62 -> 0.8
D103: =$G$63 -> 0.3
D104: =$G$64 -> 8
D105: =$G$65 -> 0.75
...

Sheet Tela
A1: Materia Prima
A2: ITEM | B2: Descripción | C2: Rendimiento m / kg | D2: Ancho Extendido/Mts | E2: Unid. | F2: Densidad Gr / mt2 | G2: Peso / mt lineal extendido | H2: Precio unidad de compra/Bs | I2: Precio Bs / Kg | J2: Precio Bs / g | K2: Datos para modificar
A3: 1 | B3: Algodón Nacional, hilo Hindú Poleras | C3: =1000/F3/D3 -> 3.0165913 | D3: 1.7 | E3: kilo | F3: 195 | G3: =F3*D3 -> 331.5 | H3: 97 | I3: =IF($E3="kilo",$H3,(($H3*1000)/$G3)) -> 97 | J3: =I3/1000 -> 0.097
A4: =A3+1 -> 2 | B4: Pique, Nacional Hilo Hindú | C4: =1000/F4/D4 -> 3.003003 | D4: 1.8 | E4: kilo | F4: 185 | G4: =F4*D4 -> 333 | H4: 97 | I4: =IF($E4="kilo",$H4,(($H4*1000)/$G4)) -> 97 | J4: =I4/1000 -> 0.097
A5: =A4+1 -> 3 | B5: Tela Casimir Indú Pantalones | C5: =1000/F5/D5 -> 3.2520325 | D5: 1.5 | E5: metro | F5: 205 | G5: =F5*D5 -> 307.5 | H5: 35 | I5: =IF($E5="kilo",$H5,(($H5*1000)/$G5)) -> 113.82114 | J5: =I5/1000 -> 0.11382114
A6: =A5+1 -> 4 | B6: Popelina Luqui Blusas y camisas | C6: =1000/F6/D6 -> 5.899705 | D6: 1.5 | E6: metro | F6: 113 | G6: =F6*D6 -> 169.5 | H6: 25 | I6: =IF($E6="kilo",$H6,(($H6*1000)/$G6)) -> 147.49263 | J6: =I6/1000 -> 0.14749263 | L6: 1000
A7: =A6+1 -> 5 | B7: Dryfit para shorts | C7: =1000/F7/D7 -> 3.805175 | D7: 1.8 | E7: metro | F7: 146 | G7: =F7*D7 -> 262.8 | H7: 16 | I7: =IF($E7="kilo",$H7,(($H7*1000)/$G7)) -> 60.882801 | J7: =I7/1000 -> 0.060882801 | L7: 182
A8: =A7+1 -> 6 | B8: Licra de algodón para Calzas | C8: =1000/F8/D8 -> 1.9201229 | D8: 1.4 | E8: kilo | F8: 372 | G8: =F8*D8 -> 520.8 | H8: 120 | I8: =IF($E8="kilo",$H8,(($H8*1000)/$G8)) -> 120 | J8: =I8/1000 -> 0.12 | L8: =L7*I6/L6 -> 26.843658
A9: =A8+1 -> 7 | B9: Taslan para chamarras y buzos | C9: =1000/F9/D9 -> 5.7471264 | D9: 1.5 | E9: metro | F9: 116 | G9: =F9*D9 -> 174 | H9: 28 | I9: =IF($E9="kilo",$H9,(($H9*1000)/$G9)) -> 160.91954 | J9: =I9/1000 -> 0.16091954
A10: 8 | B10: Tela Casimir Escoces para faldas/vestidos/corbatas/ | C10: =1000/F10/D10 -> 3.2679739 | D10: 1.5 | E10: metro | F10: 204 | G10: =F10*D10 -> 306 | H10: 60 | I10: =IF($E10="kilo",$H10,(($H10*1000)/$G10)) -> 196.07843 | J10: =I10/1000 -> 0.19607843
A11: 9 | B11: Casimir Italiano para sacos | C11: =1000/F11/D11 -> 1.7362317 | D11: 1.54 | E11: metro | F11: 374 | G11: =F11*D11 -> 575.96 | H11: 70 | I11: =IF($E11="kilo",$H11,(($H11*1000)/$G11)) -> 121.53622 | J11: =I11/1000 -> 0.12153622
A12: 10 | B12: Forro delgado para Chamarras | C12: =1000/F12/D12 -> 9.1324201 | D12: 1.5 | E12: metro | F12: 73 | G12: =F12*D12 -> 109.5 | H12: 7.5 | I12: =IF($E12="kilo",$H12,(($H12*1000)/$G12)) -> 68.493151 | J12: =I12/1000 -> 0.068493151
A13: 11 | B13: Polar | C13: =1000/F13/D13 -> 3.7878788 | D13: 1.5 | E13: metro | F13: 176 | G13: =F13*D13 -> 264 | H13: 18 | I13: =IF($E13="kilo",$H13,(($H13*1000)/$G13)) -> 68.181818 | J13: =I13/1000 -> 0.068181818
A14: 12 | B14: Deportivo para Chamarras y buzos | C14: =1000/F14/D14 -> 2.5641026 | D14: 1.5 | E14: metro | F14: 260 | G14: =F14*D14 -> 390 | H14: 18 | I14: =IF($E14="kilo",$H14,(($H14*1000)/$G14)) -> 46.153846 | J14: =I14/1000 -> 0.046153846

Sheet ManoDeObra
A1: Costo mano de obra | C1: EN BS
A2: ITEM | B2: DETALLE | C2: Tallas 42 -10 | D2: Tallas 12 - S | E2: Tallas M - 4XL
A3: 1 | B3: Pantalón de vestir | C3: 45 | D3: 50 | E3: 55
A4: 2 | B4: Camisa manga corta | C4: 18 | D4: 21 | E4: 25
A5: 3 | B5: Camisa manga larga | C5: 19 | D5: 22 | E5: 26
A6: 4 | B6: Corbata larga | C6: 3.5 | D6: 3.5 | E6: 3.5
A7: 5 | B7: Pantalón con elástico | C7: 18 | D7: 21 | E7: 25
A8: 6 | B8: Bermuda | C8: 18 | D8: 21 | E8: 25
A9: 7 | B9: Polera manga corta | C9: 5 | D9: 5 | E9: 5
A10: 8 | B10: Polera manga larga | C10: 5.5 | D10: 5.5 | E10: 5.5
A11: 9 | B11: Short | C11: 5 | D11: 5 | E11: 5
A12: 10 | B12: Calza corta | C12: 5 | D12: 7 | E12: 9
A13: 11 | B13: Calza larga | C13: 6 | D13: 8 | E13: 10
A14: 12 | B14: Pantalón para dama | C14: 25 | D14: 25 | E14: 25
... A20: 18 | B20: Vestido | C20: 20 | D20: 20 | E20: 20
A21: 19 | B21: Chompa cuello en V
A22: 20 | B22: Chaleco cuello en V
A23: 21 | B23: Chamarra de verano | C23: 25 | D23: 30 | E23: 35
A24: 22 | B24: Chamarra deportiva | C24: 25 | D24: 30 | E24: 35
A25: 23 | B25: Chamarra de invierno | C25: 27 | D25: 32 | E25: 37
A26: 24 | B26: Buso Deportivo | C26: 16 | D26: 18 | E26: 20
A27: 25 | B27: Polera de colores | C27: 5 | D27: 5 | E27: 5
A28: 26 | B28: Polera Bullying | C28: 5 | D28: 5 | E28: 5
A29: 27 | B29: Saco | C29: 100 | D29: 120 | E29: 150

Sheet fijosXprenda
A1: Costos Fijos y variables por prenda
A2: ITEM | B2: DETALLE | C2: Factor de Complejidad | D2: Costo fijo
A3: 1 | B3: Pantalón de vestir | C3: 8 | D3: =('Fij&Var'!$C$16/10)*fijosXprenda!$C3 -> 9.5466667
A4: 2 | B4: Camisa manga corta | C4: 6 | D4: =('Fij&Var'!$C$16/10)*fijosXprenda!$C4 -> 7.16
A5: 3 | B5: Camisa manga larga | C5: 7 | D5: =('Fij&Var'!$C$16/10)*fijosXprenda!$C5 -> 8.3533333
A6: 4 | B6: Corbata larga | C6: 2 | D6: =('Fij&Var'!$C$16/10)*fijosXprenda!$C6 -> 2.3866667
A7: 5 | B7: Pantalón con elástico | C7: 7 | D7: =('Fij&Var'!$C$16/10)*fijosXprenda!$C7 -> 8.3533333
A8: 6 | B8: Bermuda | C8: 6 | D8: =('Fij&Var'!$C$16/10)*fijosXprenda!$C8 -> 7.16
A9: 7 | B9: Polera manga corta | C9: 4 | D9: =('Fij&Var'!$C$16/10)*fijosXprenda!$C9 -> 4.7733333
A10: 8 | B10: Polera manga larga | C10: 4.5 | D10: =('Fij&Var'!$C$16/10)*fijosXprenda!$C10 -> 5.37
A11: 9 | B11: Short | C11: 4 | D11: =('Fij&Var'!$C$16/10)*fijosXprenda!$C11 -> 4.7733333
A12: 10 | B12: Calza corta | C12: 4 | D12: =('Fij&Var'!$C$16/10)*fijosXprenda!$C12 -> 4.7733333
A13: 11 | B13: Calza larga | C13: 4.5 | D13: =('Fij&Var'!$C$16/10)*fijosXprenda!$C13 -> 5.37
A14: 12 | B14: Pantalón para dama | C14: 7 | D14: =('Fij&Var'!$C$16/10)*fijosXprenda!$C14 -> 8.3533333
... A29: 27 | B29: Saco | C29: 10 | D29: =('Fij&Var'!$C$16/10)*fijosXprenda!$C29 -> 11.933333

Sheet Fij&Var
A1: ITEM | B1: Costos indirectos de producción | C1: Costo Mensual
A2: 1 | B2: Costos Personal de Corte | C2: 4000
A3: =A2+1 -> 2 | B3: Costos personal administrativo. | C3: 5500
A4: =A3+1 -> 3 | B4: Costos personal de limpieza, planchado y terminado. | C4: 4500
A5: =A4+1 -> 4 | B5: Mantenimiento y lubricación de maquinaria | C5: 350
A6: =A5+1 -> 5 | B6: Servicio de Electricidad | C6: 1600
A7: =A6+1 -> 6 | B7: Servicio de Agua potable | C7: 250
A8: =A7+1 -> 7 | B8: Servicio de Internet | C8: 280
A9: =A8+1 -> 8 | B9: Hipoteca | C9: 5000
A10: =A9+1 -> 9
A11: =A10+1 -> 10
A12: =A11+1 -> 11
A13: =A12+1 -> 12
B14: Total Costos Indirectos Mensuales | C14: =SUM(C2:C13) -> 21480
B15: Prendas producidas al Mes | C15: 1800
B16: Costo Indirecto por prenda | C16: =C14/C15 -> 11.933333

Sheet Semit.
A1: Costo de Fabricacion semiterminado
A2: ITEM | B2: DETALLE | C2: 2 | D2: 4 | E2: 6 | F2: 8 | G2: 10 | H2: 12 | I2: 14 | J2: 16/34 | K2: 36/XS | L2: 38/S | M2: 40/M | N2: 42/L | O2: 44/XL | P2: 46/2XL | Q2: 48/3XL
A3: 19 | B3: Chompa cuello en V | C3: 50 | D3: 50 | E3: 55 | F3: 60 | G3: 65 | H3: 70 | I3: 75 | J3: 80 | L3: 90 | M3: 100 | N3: 110 | O3: 120 | P3: 130 | Q3: 140
A4: 20 | B4: Chaleco cuello en V | C4: 45 | D4: 45 | E4: 50 | F4: 55 | G4: 60 | H4: 65 | I4: 70 | J4: 75 | L4: 85 | M4: 95 | N4: 105 | O4: 115 | P4: 125 | Q4: 135
B7: Costos anteriores | C7: 47 | D7: 47 | E7: 49 | F7: 52 | G7: 55 | H7: 57 | I7: 62 | J7: 62 | K7: ● | L7: 67 | M7: 67 | N7: 72 | O7: 72 | P7: ● | Q7: ●
C8: 37 | D8: 37 | E8: 39 | F8: 42 | G8: 45 | H8: 47 | I8: 52 | J8: 52 | K8: ● | L8: 57 | M8: 57 | N8: 62 | O8: 62 | P8: ● | Q8: ●

Sheet CostoBruto
A1: COSTO BRUTO | C1: Tela + Accesorios + Mano de obra (SIN FIJOS NI VARIABLES)
A2: ITEM | B2: DETALLE | C2: 2 | D2: 4 | E2: 6 | F2: 8 | G2: 10 | H2: 12 | I2: 14 | J2: 16/34 | K2: 36/XS | L2: 38/S | M2: 40/M | N2: 42/L | O2: 44/XL | P2: 46/2XL | Q2: 48/3XL | R2: 50/4XL
A3: 1 | B3: Pantalón de vestir | C3: =IF(PesoMatPrima!C3>0,(PesoMatPrima!C3*Tela!$J$5)+Acc!$AP$3+ManoDeObra!$C$3,0) -> 0 | D3: =IF(PesoMatPrima!D3>0,(PesoMatPrima!D3*Tela!$J$5)+Acc!$AP$3+ManoDeObra!$C$3,0) -> 0 | E3: =IF(PesoMatPrima!E3>0,(PesoMatPrima!E3*Tela!$J$5)+Acc!$AP$3+ManoDeObra!$C$3,0) -> 0 | F3: =IF(PesoMatPrima!F3>0,(PesoMatPrima!F3*Tela!$J$5)+Acc!$AP$3+ManoDeObra!$C$3,0) -> 0 | G3: =IF(PesoMatPrima!G3>0,(PesoMatPrima!G3*Tela!$J$5)+Acc!$AP$3+ManoDeObra!$C$3,0) -> 0 | H3: =IF(PesoMatPrima!H3>0,(PesoMatPrima!H3*Tela!$J$5)+Acc!$AP$3+ManoDeObra!$D$3,0) -> 0 | I3: =IF(PesoMatPrima!I3>0,(PesoMatPrima!I3*Tela!$J$5)+Acc!$AP$3+ManoDeObra!$D$3,0) -> 0 | J3: =IF(PesoMatPrima!J3>0,(PesoMatPrima!J3*Tela!$J$5)+Acc!$AP$3+ManoDeObra!$D$3,0) -> 97.111951 | K3: =IF(PesoMatPrima!K3>0,(PesoMatPrima!K3*Tela!$J$5)+Acc!$AP$3+ManoDeObra!$D$3,0) -> 99.570488 | L3: =IF(PesoMatPrima!L3>0,(PesoMatPrima!L3*Tela!$J$5)+Acc!$AP$3+ManoDeObra!$E$3,0) -> 105.79976 | M3: =IF(PesoMatPrima!M3>0,(PesoMatPrima!M3*Tela!$J$5)+Acc!$AP$3+ManoDeObra!$E$3,0) -> 107.64366 | N3: =IF(PesoMatPrima!N3>0,(PesoMatPrima!N3*Tela!$J$5)+Acc!$AP$3+ManoDeObra!$E$3,0) -> 109.48756 | O3: =IF(PesoMatPrima!O3>0,(PesoMatPrima!O3*Tela!$J$5)+Acc!$AP$3+ManoDeObra!$E$3,0) -> 110.71683 | P3: =IF(PesoMatPrima!P3>0,(PesoMatPrima!P3*Tela!$J$5)+Acc!$AP$3+ManoDeObra!$E$3,0) -> 112.92951 | Q3: =IF(PesoMatPrima!Q3>0,(PesoMatPrima!Q3*Tela!$J$5)+Acc!$AP$3+ManoDeObra!$E$3,0) -> 114.28171 | R3: =IF(PesoMatPrima!R3>0,(PesoMatPrima!R3*Tela!$J$5)+Acc!$AP$3+ManoDeObra!$E$3,0) -> 116.24854
A4: 2 | B4: Camisa manga corta | C4: =IF(PesoMatPrima!C4>0,(PesoMatPrima!C4*Tela!$J$6)+Acc!$AP$4+ManoDeObra!$C$4,0) -> 48.107994 | D4: =IF(PesoMatPrima!D4>0,(PesoMatPrima!D4*Tela!$J$6)+Acc!$AP$4+ManoDeObra!$C$4,0) -> 49.223038 | E4: =IF(PesoMatPrima!E4>0,(PesoMatPrima!E4*Tela!$J$6)+Acc!$AP$4+ManoDeObra!$C$4,0) -> 50.338083 | F4: =IF(PesoMatPrima!F4>0,(PesoMatPrima!F4*Tela!$J$6)+Acc!$AP$4+ManoDeObra!$C$4,0) -> 51.453127 | G4: =IF(PesoMatPrima!G4>0,(PesoMatPrima!G4*Tela!$J$6)+Acc!$AP$4+ManoDeObra!$C$4,0) -> 52.568171 | H4: =IF(PesoMatPrima!H4>0,(PesoMatPrima!H4*Tela!$J$6)+Acc!$AP$4+ManoDeObra!$D$4,0) -> 56.683215 | I4: =IF(PesoMatPrima!I4>0,(PesoMatPrima!I4*Tela!$J$6)+Acc!$AP$4+ManoDeObra!$D$4,0) -> 57.79826 | J4: =IF(PesoMatPrima!J4>0,(PesoMatPrima!J4*Tela!$J$6)+Acc!$AP$4+ManoDeObra!$D$4,0) -> 58.913304 | K4: =IF(PesoMatPrima!K4>0,(PesoMatPrima!K4*Tela!$J$6)+Acc!$AP$4+ManoDeObra!$D$4,0) -> 0 | L4: =IF(PesoMatPrima!L4>0,(PesoMatPrima!L4*Tela!$J$6)+Acc!$AP$4+ManoDeObra!$D$4,0) -> 60.028348 | M4: =IF(PesoMatPrima!M4>0,(PesoMatPrima!M4*Tela!$J$6)+Acc!$AP$4+ManoDeObra!$E$4,0) -> 65.143392 | N4: =IF(PesoMatPrima!N4>0,(PesoMatPrima!N4*Tela!$J$6)+Acc!$AP$4+ManoDeObra!$E$4,0) -> 66.258437 | O4: =IF(PesoMatPrima!O4>0,(PesoMatPrima!O4*Tela!$J$6)+Acc!$AP$4+ManoDeObra!$E$4,0) -> 67.373481 | P4: =IF(PesoMatPrima!P4>0,(PesoMatPrima!P4*Tela!$J$6)+Acc!$AP$4+ManoDeObra!$E$4,0) -> 68.807109 | Q4: =IF(PesoMatPrima!Q4>0,(PesoMatPrima!Q4*Tela!$J$6)+Acc!$AP$4+ManoDeObra!$E$4,0) -> 70.081445
A5: 3 | B5: Camisa manga larga | C5: =IF(PesoMatPrima!C5>0,(PesoMatPrima!C5*Tela!$J$6)+Acc!$AP$5+ManoDeObra!$C$5,0) -> 52.134248 | D5: =IF(PesoMatPrima!D5>0,(PesoMatPrima!D5*Tela!$J$6)+Acc!$AP$5+ManoDeObra!$C$5,0) -> 53.249292 | E5: =IF(PesoMatPrima!E5>0,(PesoMatPrima!E5*Tela!$J$6)+Acc!$AP$5+ManoDeObra!$C$5,0) -> 54.364336 | F5: =IF(PesoMatPrima!F5>0,(PesoMatPrima!F5*Tela!$J$6)+Acc!$AP$5+ManoDeObra!$C$5,0) -> 55.479381 | G5: =IF(PesoMatPrima!G5>0,(PesoMatPrima!G5*Tela!$J$6)+Acc!$AP$5+ManoDeObra!$C$5,0) -> 56.594425 | H5: =IF(PesoMatPrima!H5>0,(PesoMatPrima!H5*Tela!$J$6)+Acc!$AP$5+ManoDeObra!$D$5,0) -> 60.709469 | I5: =IF(PesoMatPrima!I5>0,(PesoMatPrima!I5*Tela!$J$6)+Acc!$AP$5+ManoDeObra!$D$5,0) -> 61.824513 | J5: =IF(PesoMatPrima!J5>0,(PesoMatPrima!J5*Tela!$J$6)+Acc!$AP$5+ManoDeObra!$D$5,0) -> 62.939558 | K5: =IF(PesoMatPrima!K5>0,(PesoMatPrima!K5*Tela!$J$6)+Acc!$AP$5+ManoDeObra!$D$5,0) -> 0 | L5: =IF(PesoMatPrima!L5>0,(PesoMatPrima!L5*Tela!$J$6)+Acc!$AP$5+ManoDeObra!$D$5,0) -> 64.054602 | M5: =IF(PesoMatPrima!M5>0,(PesoMatPrima!M5*Tela!$J$6)+Acc!$AP$5+ManoDeObra!$E$5,0) -> 69.169646 | N5: =IF(PesoMatPrima!N5>0,(PesoMatPrima!N5*Tela!$J$6)+Acc!$AP$5+ManoDeObra!$E$5,0) -> 70.28469 | O5: =IF(PesoMatPrima!O5>0,(PesoMatPrima!O5*Tela!$J$6)+Acc!$AP$5+ManoDeObra!$E$5,0) -> 71.399735 | P5: =IF(PesoMatPrima!P5>0,(PesoMatPrima!P5*Tela!$J$6)+Acc!$AP$5+ManoDeObra!$E$5,0) -> 72.833363 | Q5: =IF(PesoMatPrima!Q5>0,(PesoMatPrima!Q5*Tela!$J$6)+Acc!$AP$5+ManoDeObra!$E$5,0) -> 74.107699
A6: 4 | B6: Corbata larga | C6: =IF(PesoMatPrima!C6>0,(PesoMatPrima!C6*Tela!$J$10)+Acc!$AP$6+ManoDeObra!$C$6,0) -> 0 | D6: =IF(PesoMatPrima!D6>0,(PesoMatPrima!D6*Tela!$J$10)+Acc!$AP$6+ManoDeObra!$C$6,0) -> 0 | E6: =IF(PesoMatPrima!E6>0,(PesoMatPrima!E6*Tela!$J$10)+Acc!$AP$6+ManoDeObra!$C$6,0) -> 0 | F6: =IF(PesoMatPrima!F6>0,(PesoMatPrima!F6*Tela!$J$10)+Acc!$AP$6+ManoDeObra!$C$6,0) -> 0 | G6: =IF(PesoMatPrima!G6>0,(PesoMatPrima!G6*Tela!$J$10)+Acc!$AP$6+ManoDeObra!$C$6,0) -> 0 | H6: =IF(PesoMatPrima!H6>0,(PesoMatPrima!H6*Tela!$J$10)+Acc!$AP$6+ManoDeObra!$C$6,0) -> 0 | I6: =IF(PesoMatPrima!I6>0,(PesoMatPrima!I6*Tela!$J$10)+Acc!$AP$6+ManoDeObra!$C$6,0) -> 0 | J6: =IF(PesoMatPrima!J6>0,(PesoMatPrima!J6*Tela!$J$10)+Acc!$AP$6+ManoDeObra!$C$6,0) -> 0 | ... Q6: =IF(PesoMatPrima!Q6>0,(PesoMatPrima!Q6*Tela!$J$10)+Acc!$AP$6+ManoDeObra!$C$6,0) -> 0
A7: 5 | B7: Pantalón con elástico | C7: =IF(PesoMatPrima!C7>0,(PesoMatPrima!C7*Tela!$J$5)+Acc!$AP$7+ManoDeObra!$C$7,0) -> 42.570122 | D7: =IF(PesoMatPrima!D7>0,(PesoMatPrima!D7*Tela!$J$5)+Acc!$AP$7+ManoDeObra!$C$7,0) -> 45.151585 | E7: =IF(PesoMatPrima!E7>0,(PesoMatPrima!E7*Tela!$J$5)+Acc!$AP$7+ManoDeObra!$C$7,0) -> 47.733049 | F7: =IF(PesoMatPrima!F7>0,(PesoMatPrima!F7*Tela!$J$5)+Acc!$AP$7+ManoDeObra!$C$7,0) -> 50.437439 | G7: =IF(PesoMatPrima!G7>0,(PesoMatPrima!G7*Tela!$J$5)+Acc!$AP$7+ManoDeObra!$C$7,0) -> 53.018902 | H7: =IF(PesoMatPrima!H7>0,(PesoMatPrima!H7*Tela!$J$5)+Acc!$AP$7+ManoDeObra!$D$7,0) -> 58.231585 | I7: =IF(PesoMatPrima!I7>0,(PesoMatPrima!I7*Tela!$J$5)+Acc!$AP$7+ManoDeObra!$D$7,0) -> 60.444268 | J7: =IF(PesoMatPrima!J7>0,(PesoMatPrima!J7*Tela!$J$5)+Acc!$AP$7+ManoDeObra!$D$7,0) -> 62.656951 | K7: =IF(PesoMatPrima!K7>0,(PesoMatPrima!K7*Tela!$J$5)+Acc!$AP$7+ManoDeObra!$D$7,0) -> 0 | L7: =IF(PesoMatPrima!L7>0,(PesoMatPrima!L7*Tela!$J$5)+Acc!$AP$7+ManoDeObra!$E$7,0) -> 68.62378 | M7: =IF(PesoMatPrima!M7>0,(PesoMatPrima!M7*Tela!$J$5)+Acc!$AP$7+ManoDeObra!$E$7,0) -> 0 | N7: =IF(PesoMatPrima!N7>0,(PesoMatPrima!N7*Tela!$J$5)+Acc!$AP$7+ManoDeObra!$E$7,0) -> 0 | O7: =IF(PesoMatPrima!O7>0,(PesoMatPrima!O7*Tela!$J$5)+Acc!$AP$7+ManoDeObra!$E$7,0) -> 0 | P7: =IF(PesoMatPrima!P7>0,(PesoMatPrima!P7*Tela!$J$5)+Acc!$AP$7+ManoDeObra!$E$7,0) -> 0 | Q7: =IF(PesoMatPrima!Q7>0,(PesoMatPrima!Q7*Tela!$J$5)+Acc!$AP$7+ManoDeObra!$E$7,0) -> 0
A8: 6 | B8: Bermuda | C8: =IF(PesoMatPrima!C8>0,(PesoMatPrima!C8*Tela!$J$5)+Acc!$AP$8+ManoDeObra!$C$8,0) -> 37.659268 | D8: =IF(PesoMatPrima!D8>0,(PesoMatPrima!D8*Tela!$J$5)+Acc!$AP$8+ManoDeObra!$C$8,0) -> 38.642683 | E8: =IF(PesoMatPrima!E8>0,(PesoMatPrima!E8*Tela!$J$5)+Acc!$AP$8+ManoDeObra!$C$8,0) -> 39.994878 | F8: =IF(PesoMatPrima!F8>0,(PesoMatPrima!F8*Tela!$J$5)+Acc!$AP$8+ManoDeObra!$C$8,0) -> 41.592927 | G8: =IF(PesoMatPrima!G8>0,(PesoMatPrima!G8*Tela!$J$5)+Acc!$AP$8+ManoDeObra!$C$8,0) -> 43.80561 | H8: =IF(PesoMatPrima!H8>0,(PesoMatPrima!H8*Tela!$J$5)+Acc!$AP$8+ManoDeObra!$D$8,0) -> 48.895366 | I8: =IF(PesoMatPrima!I8>0,(PesoMatPrima!I8*Tela!$J$5)+Acc!$AP$8+ManoDeObra!$D$8,0) -> 49.632927 | J8: =IF(PesoMatPrima!J8>0,(PesoMatPrima!J8*Tela!$J$5)+Acc!$AP$8+ManoDeObra!$D$8,0) -> 51.230976 | K8: =IF(PesoMatPrima!K8>0,(PesoMatPrima!K8*Tela!$J$5)+Acc!$AP$8+ManoDeObra!$D$8,0) -> 0 | L8: =IF(PesoMatPrima!L8>0,(PesoMatPrima!L8*Tela!$J$5)+Acc!$AP$8+ManoDeObra!$E$8,0) -> 57.443659 | M8: =IF(PesoMatPrima!M8>0,(PesoMatPrima!M8*Tela!$J$5)+Acc!$AP$8+ManoDeObra!$C$8,0) -> 0 | N8: =IF(PesoMatPrima!N8>0,(PesoMatPrima!N8*Tela!$J$5)+Acc!$AP$8+ManoDeObra!$C$8,0) -> 0 | O8: =IF(PesoMatPrima!O8>0,(PesoMatPrima!O8*Tela!$J$5)+Acc!$AP$8+ManoDeObra!$C$8,0) -> 0 | P8: =IF(PesoMatPrima!P8>0,(PesoMatPrima!P8*Tela!$J$5)+Acc!$AP$8+ManoDeObra!$C$8,0) -> 0 | Q8: =IF(PesoMatPrima!Q8>0,(PesoMatPrima!Q8*Tela!$J$5)+Acc!$AP$8+ManoDeObra!$C$8,0) -> 0
A9: 7 | B9: Polera manga corta | C9: =IF(PesoMatPrima!C9>0,(PesoMatPrima!C9*Tela!$J$3)+Acc!$AP$9+ManoDeObra!$C$9,0) -> 35.78268 | D9: =IF(PesoMatPrima!D9>0,(PesoMatPrima!D9*Tela!$J$3)+Acc!$AP$9+ManoDeObra!$C$9,0) -> 36.516 | E9: =IF(PesoMatPrima!E9>0,(PesoMatPrima!E9*Tela!$J$3)+Acc!$AP$9+ManoDeObra!$C$9,0) -> 37.24932 | F9: =IF(PesoMatPrima!F9>0,(PesoMatPrima!F9*Tela!$J$3)+Acc!$AP$9+ManoDeObra!$C$9,0) -> 38.92548 | G9: =IF(PesoMatPrima!G9>0,(PesoMatPrima!G9*Tela!$J$3)+Acc!$AP$9+ManoDeObra!$C$9,0) -> 40.60164 | H9: =IF(PesoMatPrima!H9>0,(PesoMatPrima!H9*Tela!$J$3)+Acc!$AP$9+ManoDeObra!$D$9,0) -> 41.12544 | I9: =IF(PesoMatPrima!I9>0,(PesoMatPrima!I9*Tela!$J$3)+Acc!$AP$9+ManoDeObra!$D$9,0) -> 41.64924 | J9: =IF(PesoMatPrima!J9>0,(PesoMatPrima!J9*Tela!$J$3)+Acc!$AP$9+ManoDeObra!$D$9,0) -> 42.38256 | K9: =IF(PesoMatPrima!K9>0,(PesoMatPrima!K9*Tela!$J$3)+Acc!$AP$9+ManoDeObra!$D$9,0) -> 0 | L9: =IF(PesoMatPrima!L9>0,(PesoMatPrima!L9*Tela!$J$3)+Acc!$AP$9+ManoDeObra!$D$9,0) -> 43.11588 | M9: =IF(PesoMatPrima!M9>0,(PesoMatPrima!M9*Tela!$J$3)+Acc!$AP$9+ManoDeObra!$E$9,0) -> 43.8492 | N9: =IF(PesoMatPrima!N9>0,(PesoMatPrima!N9*Tela!$J$3)+Acc!$AP$9+ManoDeObra!$E$9,0) -> 44.58252 | O9: =IF(PesoMatPrima!O9>0,(PesoMatPrima!O9*Tela!$J$3)+Acc!$AP$9+ManoDeObra!$E$9,0) -> 45.52536 | P9: =IF(PesoMatPrima!P9>0,(PesoMatPrima!P9*Tela!$J$3)+Acc!$AP$9+ManoDeObra!$E$9,0) -> 46.4682 | Q9: =IF(PesoMatPrima!Q9>0,(PesoMatPrima!Q9*Tela!$J$3)+Acc!$AP$9+ManoDeObra!$E$9,0) -> 48.45864
A10: 8 | B10: Polera manga larga | C10: =IF(PesoMatPrima!C10>0,(PesoMatPrima!C10*Tela!$J$3)+Acc!$AP$9+ManoDeObra!$C$10,0) -> 37.85408 | D10: =IF(PesoMatPrima!D10>0,(PesoMatPrima!D10*Tela!$J$3)+Acc!$AP$9+ManoDeObra!$C$10,0) -> 38.5874 | E10: =IF(PesoMatPrima!E10>0,(PesoMatPrima!E10*Tela!$J$3)+Acc!$AP$9+ManoDeObra!$C$10,0) -> 39.32072 | F10: =IF(PesoMatPrima!F10>0,(PesoMatPrima!F10*Tela!$J$3)+Acc!$AP$9+ManoDeObra!$C$10,0) -> 40.99688 | G10: =IF(PesoMatPrima!G10>0,(PesoMatPrima!G10*Tela!$J$3)+Acc!$AP$9+ManoDeObra!$C$10,0) -> 43.72064 | H10: =IF(PesoMatPrima!H10>0,(PesoMatPrima!H10*Tela!$J$3)+Acc!$AP$9+ManoDeObra!$D$10,0) -> 44.24444 | I10: =IF(PesoMatPrima!I10>0,(PesoMatPrima!I10*Tela!$J$3)+Acc!$AP$9+ManoDeObra!$D$10,0) -> 44.76824 | J10: =IF(PesoMatPrima!J10>0,(PesoMatPrima!J10*Tela!$J$3)+Acc!$AP$9+ManoDeObra!$D$10,0) -> 45.50156 | K10: =IF(PesoMatPrima!K10>0,(PesoMatPrima!K10*Tela!$J$3)+Acc!$AP$9+ManoDeObra!$D$10,0) -> 0 | L10: =IF(PesoMatPrima!L10>0,(PesoMatPrima!L10*Tela!$J$3)+Acc!$AP$9+ManoDeObra!$D$10,0) -> 46.75868 | M10: =IF(PesoMatPrima!M10>0,(PesoMatPrima!M10*Tela!$J$3)+Acc!$AP$9+ManoDeObra!$E$10,0) -> 47.492 | N10: =IF(PesoMatPrima!N10>0,(PesoMatPrima!N10*Tela!$J$3)+Acc!$AP$9+ManoDeObra!$E$10,0) -> 48.22532 | O10: =IF(PesoMatPrima!O10>0,(PesoMatPrima!O10*Tela!$J$3)+Acc!$AP$9+ManoDeObra!$E$10,0) -> 49.16816 | P10: =IF(PesoMatPrima!P10>0,(PesoMatPrima!P10*Tela!$J$3)+Acc!$AP$9+ManoDeObra!$E$10,0) -> 50.111 | Q10: =IF(PesoMatPrima!Q10>0,(PesoMatPrima!Q10*Tela!$J$3)+Acc!$AP$9+ManoDeObra!$E$10,0) -> 52.10144
A11: 9 | B11: Short | C11: =IF(PesoMatPrima!C11>0,(PesoMatPrima!C11*Tela!$J$7)+Acc!$AP$10+ManoDeObra!$C$11,0) -> 16.616959 | D11: =IF(PesoMatPrima!D11>0,(PesoMatPrima!D11*Tela!$J$7)+Acc!$AP$10+ManoDeObra!$C$11,0) -> 16.879973 | E11: =IF(PesoMatPrima!E11>0,(PesoMatPrima!E11*Tela!$J$7)+Acc!$AP$10+ManoDeObra!$C$11,0) -> 17.142986 | F11: =IF(PesoMatPrima!F11>0,(PesoMatPrima!F11*Tela!$J$7)+Acc!$AP$10+ManoDeObra!$C$11,0) -> 17.340247 | G11: =IF(PesoMatPrima!G11>0,(PesoMatPrima!G11*Tela!$J$7)+Acc!$AP$10+ManoDeObra!$C$11,0) -> 17.537507 | H11: =IF(PesoMatPrima!H11>0,(PesoMatPrima!H11*Tela!$J$7)+Acc!$AP$10+ManoDeObra!$D$11,0) -> 17.866274 | I11: =IF(PesoMatPrima!I11>0,(PesoMatPrima!I11*Tela!$J$7)+Acc!$AP$10+ManoDeObra!$D$11,0) -> 18.523808 | J11: =IF(PesoMatPrima!J11>0,(PesoMatPrima!J11*Tela!$J$7)+Acc!$AP$10+ManoDeObra!$D$11,0) -> 19.049836 | K11: =IF(PesoMatPrima!K11>0,(PesoMatPrima!K11*Tela!$J$7)+Acc!$AP$10+ManoDeObra!$D$11,0) -> 0 | L11: =IF(PesoMatPrima!L11>0,(PesoMatPrima!L11*Tela!$J$7)+Acc!$AP$10+ManoDeObra!$D$11,0) -> 19.51011 | M11: =IF(PesoMatPrima!M11>0,(PesoMatPrima!M11*Tela!$J$7)+Acc!$AP$10+ManoDeObra!$E$11,0) -> 19.90463 | N11: =IF(PesoMatPrima!N11>0,(PesoMatPrima!N11*Tela!$J$7)+Acc!$AP$10+ManoDeObra!$E$11,0) -> 20.299151 | O11: =IF(PesoMatPrima!O11>0,(PesoMatPrima!O11*Tela!$J$7)+Acc!$AP$10+ManoDeObra!$E$11,0) -> 20.627918 | P11: =IF(PesoMatPrima!P11>0,(PesoMatPrima!P11*Tela!$J$7)+Acc!$AP$10+ManoDeObra!$E$11,0) -> 21.219699 | Q11: =IF(PesoMatPrima!Q11>0,(PesoMatPrima!Q11*Tela!$J$7)+Acc!$AP$10+ManoDeObra!$E$11,0) -> 21.745726
A12: 10 | B12: Calza corta | C12: =IF(PesoMatPrima!C12>0,(PesoMatPrima!C12*Tela!$J$8)+Acc!$AP$11+ManoDeObra!$C$12,0) -> 21.2488 | D12: =IF(PesoMatPrima!D12>0,(PesoMatPrima!D12*Tela!$J$8)+Acc!$AP$11+ManoDeObra!$C$12,0) -> 22.2856 | E12: =IF(PesoMatPrima!E12>0,(PesoMatPrima!E12*Tela!$J$8)+Acc!$AP$11+ManoDeObra!$C$12,0) -> 23.3224 | F12: =IF(PesoMatPrima!F12>0,(PesoMatPrima!F12*Tela!$J$8)+Acc!$AP$11+ManoDeObra!$C$12,0) -> 24.3592 | G12: =IF(PesoMatPrima!G12>0,(PesoMatPrima!G12*Tela!$J$8)+Acc!$AP$11+ManoDeObra!$C$12,0) -> 25.396 | H12: =IF(PesoMatPrima!H12>0,(PesoMatPrima!H12*Tela!$J$8)+Acc!$AP$11+ManoDeObra!$D$12,0) -> 28.4328 | I12: =IF(PesoMatPrima!I12>0,(PesoMatPrima!I12*Tela!$J$8)+Acc!$AP$11+ManoDeObra!$D$12,0) -> 29.4696 | J12: =IF(PesoMatPrima!J12>0,(PesoMatPrima!J12*Tela!$J$8)+Acc!$AP$11+ManoDeObra!$D$12,0) -> 30.5064 | K12: =IF(PesoMatPrima!K12>0,(PesoMatPrima!K12*Tela!$J$8)+Acc!$AP$11+ManoDeObra!$D$12,0) -> 0 | L12: =IF(PesoMatPrima!L12>0,(PesoMatPrima!L12*Tela!$J$8)+Acc!$AP$11+ManoDeObra!$D$12,0) -> 31.5432 | M12: =IF(PesoMatPrima!M12>0,(PesoMatPrima!M12*Tela!$J$8)+Acc!$AP$11+ManoDeObra!$D$12,0) -> 32.58 | N12: =IF(PesoMatPrima!N12>0,(PesoMatPrima!N12*Tela!$J$8)+Acc!$AP$11+ManoDeObra!$D$12,0) -> 33.876 | O12: =IF(PesoMatPrima!O12>0,(PesoMatPrima!O12*Tela!$J$8)+Acc!$AP$11+ManoDeObra!$D$12,0) -> 35.172 | ... Q12: =IF(PesoMatPrima!Q12>0,(PesoMatPrima!Q12*Tela!$J$8)+Acc!$AP$11+ManoDeObra!$D$12,0) -> 37.764
A13: 11 | B13: Calza larga | C13: =IF(PesoMatPrima!C13>0,(PesoMatPrima!C13*Tela!$J$8)+Acc!$AP$11+ManoDeObra!$C$13,0) -> 26.2664 | D13: =IF(PesoMatPrima!D13>0,(PesoMatPrima!D13*Tela!$J$8)+Acc!$AP$11+ManoDeObra!$C$13,0) -> 27.9512 | E13: =IF(PesoMatPrima!E13>0,(PesoMatPrima!E13*Tela!$J$8)+Acc!$AP$11+ManoDeObra!$C$13,0) -> 29.636 | F13: =IF(PesoMatPrima!F13>0,(PesoMatPrima!F13*Tela!$J$8)+Acc!$AP$11+ManoDeObra!$C$13,0) -> 30.932 | G13: =IF(PesoMatPrima!G13>0,(PesoMatPrima!G13*Tela!$J$8)+Acc!$AP$11+ManoDeObra!$C$13,0) -> 32.228 | H13: =IF(PesoMatPrima!H13>0,(PesoMatPrima!H13*Tela!$J$8)+Acc!$AP$11+ManoDeObra!$D$13,0) -> 43.6888 | I13: =IF(PesoMatPrima!I13>0,(PesoMatPrima!I13*Tela!$J$8)+Acc!$AP$11+ManoDeObra!$D$13,0) -> 46.54 | J13: =IF(PesoMatPrima!J13>0,(PesoMatPrima!J13*Tela!$J$8)+Acc!$AP$11+ManoDeObra!$D$13,0) -> 48.0952 | K13: =IF(PesoMatPrima!K13>0,(PesoMatPrima!K13*Tela!$J$8)+Acc!$AP$11+ManoDeObra!$D$13,0) -> 0 | L13: =IF(PesoMatPrima!L13>0,(PesoMatPrima!L13*Tela!$J$8)+Acc!$AP$11+ManoDeObra!$D$13,0) -> 49.9096 | M13: =IF(PesoMatPrima!M13>0,(PesoMatPrima!M13*Tela!$J$8)+Acc!$AP$11+ManoDeObra!$E$13,0) -> 52.428 | N13: =IF(PesoMatPrima!N13>0,(PesoMatPrima!N13*Tela!$J$8)+Acc!$AP$11+ManoDeObra!$E$13,0) -> 52.8168 | O13: =IF(PesoMatPrima!O13>0,(PesoMatPrima!O13*Tela!$J$8)+Acc!$AP$11+ManoDeObra!$E$13,0) -> 53.724 | P13: =IF(PesoMatPrima!P13>0,(PesoMatPrima!P13*Tela!$J$8)+Acc!$AP$11+ManoDeObra!$E$13,0) -> 55.668 | Q13: =IF(PesoMatPrima!Q13>0,(PesoMatPrima!Q13*Tela!$J$8)+Acc!$AP$11+ManoDeObra!$E$13,0) -> 57.3528
A14: 12 | B14: Pantalón para dama | C14: =IF(PesoMatPrima!C14>0,(PesoMatPrima!C14*Tela!$J$5)+Acc!$AP$12+ManoDeObra!$C$14,0) -> 0 | D14: =IF(PesoMatPrima!D14>0,(PesoMatPrima!D14*Tela!$J$5)+Acc!$AP$12+ManoDeObra!$C$14,0) -> 0 | E14: =IF(PesoMatPrima!E14>0,(PesoMatPrima!E14*Tela!$J$5)+Acc!$AP$12+ManoDeObra!$C$14,0) -> 0 | F14: =IF(PesoMatPrima!F14>0,(PesoMatPrima!F14*Tela!$J$5)+Acc!$AP$12+ManoDeObra!$C$14,0) -> 0 | G14: =IF(PesoMatPrima!G14>0,(PesoMatPrima!G14*Tela!$J$5)+Acc!$AP$12+ManoDeObra!$C$14,0) -> 0 | H14: =IF(PesoMatPrima!H14>0,(PesoMatPrima!H14*Tela!$J$5)+Acc!$AP$12+ManoDeObra!$D$14,0) -> 0 | I14: =IF(PesoMatPrima!I14>0,(PesoMatPrima!I14*Tela!$J$5)+Acc!$AP$12+ManoDeObra!$D$14,0) -> 0 | J14: =IF(PesoMatPrima!J14>0,(PesoMatPrima!J14*Tela!$J$5)+Acc!$AP$12+ManoDeObra!$D$14,0) -> 61.386098 | K14: =IF(PesoMatPrima!K14>0,(PesoMatPrima!K14*Tela!$J$5)+Acc!$AP$12+ManoDeObra!$D$14,0) -> 63.475854 | L14: =IF(PesoMatPrima!L14>0,(PesoMatPrima!L14*Tela!$J$5)+Acc!$AP$12+ManoDeObra!$E$14,0) -> 65.56561 | M14: =IF(PesoMatPrima!M14>0,(PesoMatPrima!M14*Tela!$J$5)+Acc!$AP$12+ManoDeObra!$E$14,0) -> 67.409512 | N14: =IF(PesoMatPrima!N14>0,(PesoMatPrima!N14*Tela!$J$5)+Acc!$AP$12+ManoDeObra!$E$14,0) -> 68.884634 | O14: =IF(PesoMatPrima!O14>0,(PesoMatPrima!O14*Tela!$J$5)+Acc!$AP$12+ManoDeObra!$E$14,0) -> 69.622195 | P14: =IF(PesoMatPrima!P14>0,(PesoMatPrima!P14*Tela!$J$5)+Acc!$AP$12+ManoDeObra!$E$14,0) -> 70.482683 | Q14: =IF(PesoMatPrima!Q14>0,(PesoMatPrima!Q14*Tela!$J$5)+Acc!$AP$12+ManoDeObra!$E$14,0) -> 71.711951
A15: 13 | B15: Blusa manga corta | C15: =IF(PesoMatPrima!C15>0,(PesoMatPrima!C15*Tela!$J$6)+Acc!$AP$13+ManoDeObra!$C$15,0) -> 43.010649 | D15: =IF(PesoMatPrima!D15>0,(PesoMatPrima!D15*Tela!$J$6)+Acc!$AP$13+ManoDeObra!$C$15,0) -> 43.966401 | E15: =IF(PesoMatPrima!E15>0,(PesoMatPrima!E15*Tela!$J$6)+Acc!$AP$13+ManoDeObra!$C$15,0) -> 44.762861 | F15: =IF(PesoMatPrima!F15>0,(PesoMatPrima!F15*Tela!$J$6)+Acc!$AP$13+ManoDeObra!$C$15,0) -> 46.99295 | G15: =IF(PesoMatPrima!G15>0,(PesoMatPrima!G15*Tela!$J$6)+Acc!$AP$13+ManoDeObra!$C$15,0) -> 48.58587 | H15: =IF(PesoMatPrima!H15>0,(PesoMatPrima!H15*Tela!$J$6)+Acc!$AP$13+ManoDeObra!$D$15,0) -> 52.700914 | I15: =IF(PesoMatPrima!I15>0,(PesoMatPrima!I15*Tela!$J$6)+Acc!$AP$13+ManoDeObra!$D$15,0) -> 53.019499 | J15: =IF(PesoMatPrima!J15>0,(PesoMatPrima!J15*Tela!$J$6)+Acc!$AP$13+ManoDeObra!$D$15,0) -> 53.815959 | K15: =IF(PesoMatPrima!K15>0,(PesoMatPrima!K15*Tela!$J$6)+Acc!$AP$13+ManoDeObra!$D$15,0) -> 54.771711 | L15: =IF(PesoMatPrima!L15>0,(PesoMatPrima!L15*Tela!$J$6)+Acc!$AP$13+ManoDeObra!$E$15,0) -> 59.090295 | M15: =IF(PesoMatPrima!M15>0,(PesoMatPrima!M15*Tela!$J$6)+Acc!$AP$13+ManoDeObra!$E$15,0) -> 59.568171 | N15: =IF(PesoMatPrima!N15>0,(PesoMatPrima!N15*Tela!$J$6)+Acc!$AP$13+ManoDeObra!$E$15,0) -> 59.886755 | O15: =IF(PesoMatPrima!O15>0,(PesoMatPrima!O15*Tela!$J$6)+Acc!$AP$13+ManoDeObra!$E$15,0) -> 61.161091 | P15: =IF(PesoMatPrima!P15>0,(PesoMatPrima!P15*Tela!$J$6)+Acc!$AP$13+ManoDeObra!$E$15,0) -> 61.957552 | Q15: =IF(PesoMatPrima!Q15>0,(PesoMatPrima!Q15*Tela!$J$6)+Acc!$AP$13+ManoDeObra!$E$15,0) -> 62.754012
A16: 14 | B16: Blusa manga larga | C16: =IF(PesoMatPrima!C16>0,(PesoMatPrima!C16*Tela!$J$6)+Acc!$AP$13+ManoDeObra!$C$15,0) -> 43.647817 | D16: =IF(PesoMatPrima!D16>0,(PesoMatPrima!D16*Tela!$J$6)+Acc!$AP$13+ManoDeObra!$C$15,0) -> 44.603569 | E16: =IF(PesoMatPrima!E16>0,(PesoMatPrima!E16*Tela!$J$6)+Acc!$AP$13+ManoDeObra!$C$15,0) -> 45.400029 | F16: =IF(PesoMatPrima!F16>0,(PesoMatPrima!F16*Tela!$J$6)+Acc!$AP$13+ManoDeObra!$C$15,0) -> 47.630118 | G16: =IF(PesoMatPrima!G16>0,(PesoMatPrima!G16*Tela!$J$6)+Acc!$AP$13+ManoDeObra!$C$15,0) -> 49.38233 | H16: =IF(PesoMatPrima!H16>0,(PesoMatPrima!H16*Tela!$J$6)+Acc!$AP$13+ManoDeObra!$D$15,0) -> 53.497375 | I16: =IF(PesoMatPrima!I16>0,(PesoMatPrima!I16*Tela!$J$6)+Acc!$AP$13+ManoDeObra!$D$15,0) -> 53.815959 | J16: =IF(PesoMatPrima!J16>0,(PesoMatPrima!J16*Tela!$J$6)+Acc!$AP$13+ManoDeObra!$D$15,0) -> 54.612419 | K16: =IF(PesoMatPrima!K16>0,(PesoMatPrima!K16*Tela!$J$6)+Acc!$AP$13+ManoDeObra!$D$15,0) -> 55.568171 | L16: =IF(PesoMatPrima!L16>0,(PesoMatPrima!L16*Tela!$J$6)+Acc!$AP$13+ManoDeObra!$E$15,0) -> 60.205339 | M16: =IF(PesoMatPrima!M16>0,(PesoMatPrima!M16*Tela!$J$6)+Acc!$AP$13+ManoDeObra!$E$15,0) -> 60.683215 | N16: =IF(PesoMatPrima!N16>0,(PesoMatPrima!N16*Tela!$J$6)+Acc!$AP$13+ManoDeObra!$E$15,0) -> 61.001799 | O16: =IF(PesoMatPrima!O16>0,(PesoMatPrima!O16*Tela!$J$6)+Acc!$AP$13+ManoDeObra!$E$15,0) -> 62.276136 | P16: =IF(PesoMatPrima!P16>0,(PesoMatPrima!P16*Tela!$J$6)+Acc!$AP$13+ManoDeObra!$E$15,0) -> 63.072596 | Q16: =IF(PesoMatPrima!Q16>0,(PesoMatPrima!Q16*Tela!$J$6)+Acc!$AP$13+ManoDeObra!$E$15,0) -> 63.869056
A17: 15 | B17: Corbata con elástico | C17: =IF(PesoMatPrima!C17>0,(PesoMatPrima!C17*Tela!$J$10)+Acc!$AP$15+ManoDeObra!$C$17,0) -> 11.185294 | D17: =IF(PesoMatPrima!D17>0,(PesoMatPrima!D17*Tela!$J$10)+Acc!$AP$15+ManoDeObra!$C$17,0) -> 0 | E17: =IF(PesoMatPrima!E17>0,(PesoMatPrima!E17*Tela!$J$10)+Acc!$AP$15+ManoDeObra!$C$17,0) -> 0 | F17: =IF(PesoMatPrima!F17>0,(PesoMatPrima!F17*Tela!$J$10)+Acc!$AP$15+ManoDeObra!$C$17,0) -> 0 | G17: =IF(PesoMatPrima!G17>0,(PesoMatPrima!G17*Tela!$J$10)+Acc!$AP$15+ManoDeObra!$C$17,0) -> 0 | H17: =IF(PesoMatPrima!H17>0,(PesoMatPrima!H17*Tela!$J$10)+Acc!$AP$15+ManoDeObra!$C$17,0) -> 0 | I17: =IF(PesoMatPrima!I17>0,(PesoMatPrima!I17*Tela!$J$10)+Acc!$AP$15+ManoDeObra!$C$17,0) -> 0 | J17: =IF(PesoMatPrima!J17>0,(PesoMatPrima!J17*Tela!$J$10)+Acc!$AP$15+ManoDeObra!$C$17,0) -> 0 | ... Q17: =IF(PesoMatPrima!Q17>0,(PesoMatPrima!Q17*Tela!$J$10)+Acc!$AP$15+ManoDeObra!$C$17,0) -> 0
A18: 16 | B18: Falda plisada | C18: =IF(PesoMatPrima!C18>0,(PesoMatPrima!C18*Tela!$J$10)+Acc!$AP$16+ManoDeObra!$C$18,0) -> 60.202745 | D18: =IF(PesoMatPrima!D18>0,(PesoMatPrima!D18*Tela!$J$10)+Acc!$AP$16+ManoDeObra!$C$18,0) -> 61.896863 | E18: =IF(PesoMatPrima!E18>0,(PesoMatPrima!E18*Tela!$J$10)+Acc!$AP$16+ManoDeObra!$C$18,0) -> 63.59098 | F18: =IF(PesoMatPrima!F18>0,(PesoMatPrima!F18*Tela!$J$10)+Acc!$AP$16+ManoDeObra!$C$18,0) -> 65.285098 | G18: =IF(PesoMatPrima!G18>0,(PesoMatPrima!G18*Tela!$J$10)+Acc!$AP$16+ManoDeObra!$C$18,0) -> 66.979216 | H18: =IF(PesoMatPrima!H18>0,(PesoMatPrima!H18*Tela!$J$10)+Acc!$AP$16+ManoDeObra!$D$18,0) -> 68.673333 | I18: =IF(PesoMatPrima!I18>0,(PesoMatPrima!I18*Tela!$J$10)+Acc!$AP$16+ManoDeObra!$D$18,0) -> 70.579216 | J18: =IF(PesoMatPrima!J18>0,(PesoMatPrima!J18*Tela!$J$10)+Acc!$AP$16+ManoDeObra!$D$18,0) -> 72.273333 | K18: =IF(PesoMatPrima!K18>0,(PesoMatPrima!K18*Tela!$J$10)+Acc!$AP$16+ManoDeObra!$D$18,0) -> 0 | L18: =IF(PesoMatPrima!L18>0,(PesoMatPrima!L18*Tela!$J$10)+Acc!$AP$16+ManoDeObra!$D$18,0) -> 73.967451 | M18: =IF(PesoMatPrima!M18>0,(PesoMatPrima!M18*Tela!$J$10)+Acc!$AP$16+ManoDeObra!$D$18,0) -> 75.661569 | N18: =IF(PesoMatPrima!N18>0,(PesoMatPrima!N18*Tela!$J$10)+Acc!$AP$16+ManoDeObra!$D$18,0) -> 77.355686 | O18: =IF(PesoMatPrima!O18>0,(PesoMatPrima!O18*Tela!$J$10)+Acc!$AP$16+ManoDeObra!$D$18,0) -> 79.049804 | ... Q18: =IF(PesoMatPrima!Q18>0,(PesoMatPrima!Q18*Tela!$J$10)+Acc!$AP$16+ManoDeObra!$D$18,0) -> 82.438039
A19: 17 | B19: Jamper | C19: =IF(PesoMatPrima!C19>0,(PesoMatPrima!C19*Tela!$J$10)+Acc!$AP$17+ManoDeObra!$C$19,0) -> 48.567451 | D19: =IF(PesoMatPrima!D19>0,(PesoMatPrima!D19*Tela!$J$10)+Acc!$AP$17+ManoDeObra!$C$19,0) -> 51.108627 | E19: =IF(PesoMatPrima!E19>0,(PesoMatPrima!E19*Tela!$J$10)+Acc!$AP$17+ManoDeObra!$C$19,0) -> 53.649804 | F19: =IF(PesoMatPrima!F19>0,(PesoMatPrima!F19*Tela!$J$10)+Acc!$AP$17+ManoDeObra!$C$19,0) -> 56.19098 | G19: =IF(PesoMatPrima!G19>0,(PesoMatPrima!G19*Tela!$J$10)+Acc!$AP$17+ManoDeObra!$C$19,0) -> 58.732157 | H19: =IF(PesoMatPrima!H19>0,(PesoMatPrima!H19*Tela!$J$10)+Acc!$AP$17+ManoDeObra!$D$19,0) -> 61.273333 | I19: =IF(PesoMatPrima!I19>0,(PesoMatPrima!I19*Tela!$J$10)+Acc!$AP$17+ManoDeObra!$D$19,0) -> 0 | J19: =IF(PesoMatPrima!J19>0,(PesoMatPrima!J19*Tela!$J$10)+Acc!$AP$17+ManoDeObra!$D$19,0) -> 0 | K19: =IF(PesoMatPrima!K19>0,(PesoMatPrima!K19*Tela!$J$10)+Acc!$AP$17+ManoDeObra!$D$19,0) -> 0 | L19: =IF(PesoMatPrima!L19>0,(PesoMatPrima!L19*Tela!$J$10)+Acc!$AP$17+ManoDeObra!$E$19,0) -> 0 | M19: =IF(PesoMatPrima!M19>0,(PesoMatPrima!M19*Tela!$J$10)+Acc!$AP$17+ManoDeObra!$E$19,0) -> 0 | N19: =IF(PesoMatPrima!N19>0,(PesoMatPrima!N19*Tela!$J$10)+Acc!$AP$17+ManoDeObra!$E$19,0) -> 0 | O19: =IF(PesoMatPrima!O19>0,(PesoMatPrima!O19*Tela!$J$10)+Acc!$AP$17+ManoDeObra!$E$19,0) -> 0 | P19: =IF(PesoMatPrima!P19>0,(PesoMatPrima!P19*Tela!$J$10)+Acc!$AP$17+ManoDeObra!$E$19,0) -> 0 | Q19: =IF(PesoMatPrima!Q19>0,(PesoMatPrima!Q19*Tela!$J$10)+Acc!$AP$17+ManoDeObra!$E$19,0) -> 0
A20: 18 | B20: Vestido | C20: =IF(PesoMatPrima!C20>0,(PesoMatPrima!C20*Tela!$J$10)+Acc!$AP$18+ManoDeObra!$C$20,0) -> 60.343922 | D20: =IF(PesoMatPrima!D20>0,(PesoMatPrima!D20*Tela!$J$10)+Acc!$AP$18+ManoDeObra!$C$20,0) -> 64.367451 | E20: =IF(PesoMatPrima!E20>0,(PesoMatPrima!E20*Tela!$J$10)+Acc!$AP$18+ManoDeObra!$C$20,0) -> 68.39098 | F20: =IF(PesoMatPrima!F20>0,(PesoMatPrima!F20*Tela!$J$10)+Acc!$AP$18+ManoDeObra!$C$20,0) -> 72.41451 | G20: =IF(PesoMatPrima!G20>0,(PesoMatPrima!G20*Tela!$J$10)+Acc!$AP$18+ManoDeObra!$C$20,0) -> 76.438039 | H20: =IF(PesoMatPrima!H20>0,(PesoMatPrima!H20*Tela!$J$10)+Acc!$AP$18+ManoDeObra!$C$20,0) -> 80.461569 | I20: =IF(PesoMatPrima!I20>0,(PesoMatPrima!I20*Tela!$J$10)+Acc!$AP$18+ManoDeObra!$C$20,0) -> 0 | J20: =IF(PesoMatPrima!J20>0,(PesoMatPrima!J20*Tela!$J$10)+Acc!$AP$18+ManoDeObra!$C$20,0) -> 0 | ... Q20: =IF(PesoMatPrima!Q20>0,(PesoMatPrima!Q20*Tela!$J$10)+Acc!$AP$18+ManoDeObra!$C$20,0) -> 0
A21: 19 | B21: Chompa cuello en V | C21: =IF(Semit.!C3>0,Semit.!C3+Acc!$AP$19,0) -> 57.84 | D21: =IF(Semit.!D3>0,Semit.!D3+Acc!$AP$19,0) -> 57.84 | E21: =IF(Semit.!E3>0,Semit.!E3+Acc!$AP$19,0) -> 62.84 | F21: =IF(Semit.!F3>0,Semit.!F3+Acc!$AP$19,0) -> 67.84 | G21: =IF(Semit.!G3>0,Semit.!G3+Acc!$AP$19,0) -> 72.84 | H21: =IF(Semit.!H3>0,Semit.!H3+Acc!$AP$19,0) -> 77.84 | I21: =IF(Semit.!I3>0,Semit.!I3+Acc!$AP$19,0) -> 82.84 | J21: =IF(Semit.!J3>0,Semit.!J3+Acc!$AP$19,0) -> 87.84 | ... Q21: =IF(Semit.!Q3>0,Semit.!Q3+Acc!$AP$19,0) -> 147.84
A22: 20 | B22: Chaleco cuello en V | C22: =IF(Semit.!C4>0,Semit.!C4+Acc!$AP$20,0) -> 52.84 | D22: =IF(Semit.!D4>0,Semit.!D4+Acc!$AP$20,0) -> 52.84 | E22: =IF(Semit.!E4>0,Semit.!E4+Acc!$AP$20,0) -> 57.84 | F22: =IF(Semit.!F4>0,Semit.!F4+Acc!$AP$20,0) -> 62.84 | G22: =IF(Semit.!G4>0,Semit.!G4+Acc!$AP$20,0) -> 67.84 | H22: =IF(Semit.!H4>0,Semit.!H4+Acc!$AP$20,0) -> 72.84 | I22: =IF(Semit.!I4>0,Semit.!I4+Acc!$AP$20,0) -> 77.84 | J22: =IF(Semit.!J4>0,Semit.!J4+Acc!$AP$20,0) -> 82.84 | ... Q22: =IF(Semit.!Q4>0,Semit.!Q4+Acc!$AP$20,0) -> 142.84
A23: 21 | B23: Chamarra de verano | C23: =IF(PesoMatPrima!C23>0,(PesoMatPrima!C23*Tela!$J$9)+Acc!$AP$21+ManoDeObra!$C$23,0) -> 113.72805 | D23: =IF(PesoMatPrima!D23>0,(PesoMatPrima!D23*Tela!$J$9)+Acc!$AP$21+ManoDeObra!$C$23,0) -> 115.63977 | E23: =IF(PesoMatPrima!E23>0,(PesoMatPrima!E23*Tela!$J$9)+Acc!$AP$21+ManoDeObra!$C$23,0) -> 117.55149 | F23: =IF(PesoMatPrima!F23>0,(PesoMatPrima!F23*Tela!$J$9)+Acc!$AP$21+ManoDeObra!$C$23,0) -> 119.46322 | G23: =IF(PesoMatPrima!G23>0,(PesoMatPrima!G23*Tela!$J$9)+Acc!$AP$21+ManoDeObra!$C$23,0) -> 121.37494 | H23: =IF(PesoMatPrima!H23>0,(PesoMatPrima!H23*Tela!$J$9)+Acc!$AP$21+ManoDeObra!$D$23,0) -> 128.28667 | I23: =IF(PesoMatPrima!I23>0,(PesoMatPrima!I23*Tela!$J$9)+Acc!$AP$21+ManoDeObra!$D$23,0) -> 130.19839 | J23: =IF(PesoMatPrima!J23>0,(PesoMatPrima!J23*Tela!$J$9)+Acc!$AP$21+ManoDeObra!$D$23,0) -> 132.11011 | K23: =IF(PesoMatPrima!K23>0,(PesoMatPrima!K23*Tela!$J$9)+Acc!$AP$21+ManoDeObra!$D$23,0) -> 0 | L23: =IF(PesoMatPrima!L23>0,(PesoMatPrima!L23*Tela!$J$9)+Acc!$AP$21+ManoDeObra!$D$23,0) -> 133.67425 | M23: =IF(PesoMatPrima!M23>0,(PesoMatPrima!M23*Tela!$J$9)+Acc!$AP$21+ManoDeObra!$E$23,0) -> 140.23839 | N23: =IF(PesoMatPrima!N23>0,(PesoMatPrima!N23*Tela!$J$9)+Acc!$AP$21+ManoDeObra!$E$23,0) -> 142.15011 | O23: =IF(PesoMatPrima!O23>0,(PesoMatPrima!O23*Tela!$J$9)+Acc!$AP$21+ManoDeObra!$E$23,0) -> 143.54046 | P23: =IF(PesoMatPrima!P23>0,(PesoMatPrima!P23*Tela!$J$9)+Acc!$AP$21+ManoDeObra!$E$23,0) -> 145.1046 | Q23: =IF(PesoMatPrima!Q23>0,(PesoMatPrima!Q23*Tela!$J$9)+Acc!$AP$21+ManoDeObra!$E$23,0) -> 146.84253
A24: 22 | B24: Chamarra deportiva | C24: =IF(PesoMatPrima!C24>0,(PesoMatPrima!C24*Tela!$J$9)+Acc!$AP$21+ManoDeObra!$C$23,0) -> 113.72805 | D24: =IF(PesoMatPrima!D24>0,(PesoMatPrima!D24*Tela!$J$9)+Acc!$AP$21+ManoDeObra!$C$23,0) -> 115.63977 | E24: =IF(PesoMatPrima!E24>0,(PesoMatPrima!E24*Tela!$J$9)+Acc!$AP$21+ManoDeObra!$C$23,0) -> 117.55149 | F24: =IF(PesoMatPrima!F24>0,(PesoMatPrima!F24*Tela!$J$9)+Acc!$AP$21+ManoDeObra!$C$23,0) -> 119.46322 | G24: =IF(PesoMatPrima!G24>0,(PesoMatPrima!G24*Tela!$J$9)+Acc!$AP$21+ManoDeObra!$C$23,0) -> 121.37494 | H24: =IF(PesoMatPrima!H24>0,(PesoMatPrima!H24*Tela!$J$9)+Acc!$AP$21+ManoDeObra!$D$23,0) -> 128.28667 | I24: =IF(PesoMatPrima!I24>0,(PesoMatPrima!I24*Tela!$J$9)+Acc!$AP$21+ManoDeObra!$D$23,0) -> 130.19839 | J24: =IF(PesoMatPrima!J24>0,(PesoMatPrima!J24*Tela!$J$9)+Acc!$AP$21+ManoDeObra!$D$23,0) -> 132.11011 | K24: =IF(PesoMatPrima!K24>0,(PesoMatPrima!K24*Tela!$J$9)+Acc!$AP$21+ManoDeObra!$D$23,0) -> 0 | L24: =IF(PesoMatPrima!L24>0,(PesoMatPrima!L24*Tela!$J$9)+Acc!$AP$21+ManoDeObra!$D$23,0) -> 133.67425 | M24: =IF(PesoMatPrima!M24>0,(PesoMatPrima!M24*Tela!$J$9)+Acc!$AP$21+ManoDeObra!$E$23,0) -> 140.23839 | N24: =IF(PesoMatPrima!N24>0,(PesoMatPrima!N24*Tela!$J$9)+Acc!$AP$21+ManoDeObra!$E$23,0) -> 142.15011 | O24: =IF(PesoMatPrima!O24>0,(PesoMatPrima!O24*Tela!$J$9)+Acc!$AP$21+ManoDeObra!$E$23,0) -> 143.54046 | P24: =IF(PesoMatPrima!P24>0,(PesoMatPrima!P24*Tela!$J$9)+Acc!$AP$21+ManoDeObra!$E$23,0) -> 145.1046 | Q24: =IF(PesoMatPrima!Q24>0,(PesoMatPrima!Q24*Tela!$J$9)+Acc!$AP$21+ManoDeObra!$E$23,0) -> 146.84253
A25: 23 | B25: Chamarra de invierno | C25: =IF(PesoMatPrima!C25>0,(PesoMatPrima!C25*Tela!$J$9)+Acc!$AP$23+ManoDeObra!$C$25,0) -> 120.82018 | D25: =IF(PesoMatPrima!D25>0,(PesoMatPrima!D25*Tela!$J$9)+Acc!$AP$23+ManoDeObra!$C$25,0) -> 122.92308 | E25: =IF(PesoMatPrima!E25>0,(PesoMatPrima!E25*Tela!$J$9)+Acc!$AP$23+ManoDeObra!$C$25,0) -> 125.02598 | F25: =IF(PesoMatPrima!F25>0,(PesoMatPrima!F25*Tela!$J$9)+Acc!$AP$23+ManoDeObra!$C$25,0) -> 127.12887 | G25: =IF(PesoMatPrima!G25>0,(PesoMatPrima!G25*Tela!$J$9)+Acc!$AP$23+ManoDeObra!$C$25,0) -> 129.23177 | H25: =IF(PesoMatPrima!H25>0,(PesoMatPrima!H25*Tela!$J$9)+Acc!$AP$23+ManoDeObra!$D$25,0) -> 136.33467 | I25: =IF(PesoMatPrima!I25>0,(PesoMatPrima!I25*Tela!$J$9)+Acc!$AP$23+ManoDeObra!$D$25,0) -> 138.43756 | J25: =IF(PesoMatPrima!J25>0,(PesoMatPrima!J25*Tela!$J$9)+Acc!$AP$23+ManoDeObra!$D$25,0) -> 140.54046 | K25: =IF(PesoMatPrima!K25>0,(PesoMatPrima!K25*Tela!$J$9)+Acc!$AP$23+ManoDeObra!$D$25,0) -> 0 | L25: =IF(PesoMatPrima!L25>0,(PesoMatPrima!L25*Tela!$J$9)+Acc!$AP$23+ManoDeObra!$D$25,0) -> 142.26101 | M25: =IF(PesoMatPrima!M25>0,(PesoMatPrima!M25*Tela!$J$9)+Acc!$AP$23+ManoDeObra!$E$25,0) -> 148.98156 | N25: =IF(PesoMatPrima!N25>0,(PesoMatPrima!N25*Tela!$J$9)+Acc!$AP$23+ManoDeObra!$E$25,0) -> 151.08446 | O25: =IF(PesoMatPrima!O25>0,(PesoMatPrima!O25*Tela!$J$9)+Acc!$AP$23+ManoDeObra!$E$25,0) -> 152.61384 | P25: =IF(PesoMatPrima!P25>0,(PesoMatPrima!P25*Tela!$J$9)+Acc!$AP$23+ManoDeObra!$E$25,0) -> 154.33439 | Q25: =IF(PesoMatPrima!Q25>0,(PesoMatPrima!Q25*Tela!$J$9)+Acc!$AP$23+ManoDeObra!$E$25,0) -> 156.24611
A26: 24 | B26: Buso Deportivo | C26: =IF(PesoMatPrima!C26>0,(PesoMatPrima!C26*Tela!$J$9)+Acc!$AP$24+ManoDeObra!$C$26,0) -> 61.002207 | D26: =IF(PesoMatPrima!D26>0,(PesoMatPrima!D26*Tela!$J$9)+Acc!$AP$24+ManoDeObra!$C$26,0) -> 64.825655 | E26: =IF(PesoMatPrima!E26>0,(PesoMatPrima!E26*Tela!$J$9)+Acc!$AP$24+ManoDeObra!$C$26,0) -> 68.649103 | F26: =IF(PesoMatPrima!F26>0,(PesoMatPrima!F26*Tela!$J$9)+Acc!$AP$24+ManoDeObra!$C$26,0) -> 72.472552 | G26: =IF(PesoMatPrima!G26>0,(PesoMatPrima!G26*Tela!$J$9)+Acc!$AP$24+ManoDeObra!$C$26,0) -> 76.296 | H26: =IF(PesoMatPrima!H26>0,(PesoMatPrima!H26*Tela!$J$9)+Acc!$AP$24+ManoDeObra!$D$26,0) -> 82.119448 | I26: =IF(PesoMatPrima!I26>0,(PesoMatPrima!I26*Tela!$J$9)+Acc!$AP$24+ManoDeObra!$D$26,0) -> 86.290483 | J26: =IF(PesoMatPrima!J26>0,(PesoMatPrima!J26*Tela!$J$9)+Acc!$AP$24+ManoDeObra!$D$26,0) -> 90.63531 | K26: =IF(PesoMatPrima!K26>0,(PesoMatPrima!K26*Tela!$J$9)+Acc!$AP$24+ManoDeObra!$D$26,0) -> 0 | L26: =IF(PesoMatPrima!L26>0,(PesoMatPrima!L26*Tela!$J$9)+Acc!$AP$24+ManoDeObra!$D$26,0) -> 93.937379 | M26: =IF(PesoMatPrima!M26>0,(PesoMatPrima!M26*Tela!$J$9)+Acc!$AP$24+ManoDeObra!$E$26,0) -> 98.19669 | N26: =IF(PesoMatPrima!N26>0,(PesoMatPrima!N26*Tela!$J$9)+Acc!$AP$24+ManoDeObra!$E$26,0) -> 100.456 | O26: =IF(PesoMatPrima!O26>0,(PesoMatPrima!O26*Tela!$J$9)+Acc!$AP$24+ManoDeObra!$E$26,0) -> 102.71531 | P26: =IF(PesoMatPrima!P26>0,(PesoMatPrima!P26*Tela!$J$9)+Acc!$AP$24+ManoDeObra!$E$26,0) -> 105.66979 | Q26: =IF(PesoMatPrima!Q26>0,(PesoMatPrima!Q26*Tela!$J$9)+Acc!$AP$24+ManoDeObra!$E$26,0) -> 108.27669
A27: 25 | B27: Polera de colores | C27: =IF(PesoMatPrima!C27>0,(PesoMatPrima!C27*Tela!$J$3)+Acc!$AP$25+ManoDeObra!$C$27,0) -> 23.78268 | D27: =IF(PesoMatPrima!D27>0,(PesoMatPrima!D27*Tela!$J$3)+Acc!$AP$25+ManoDeObra!$C$27,0) -> 24.516 | E27: =IF(PesoMatPrima!E27>0,(PesoMatPrima!E27*Tela!$J$3)+Acc!$AP$25+ManoDeObra!$C$27,0) -> 25.24932 | F27: =IF(PesoMatPrima!F27>0,(PesoMatPrima!F27*Tela!$J$3)+Acc!$AP$25+ManoDeObra!$C$27,0) -> 26.92548 | G27: =IF(PesoMatPrima!G27>0,(PesoMatPrima!G27*Tela!$J$3)+Acc!$AP$25+ManoDeObra!$C$27,0) -> 28.60164 | H27: =IF(PesoMatPrima!H27>0,(PesoMatPrima!H27*Tela!$J$3)+Acc!$AP$25+ManoDeObra!$D$27,0) -> 29.12544 | I27: =IF(PesoMatPrima!I27>0,(PesoMatPrima!I27*Tela!$J$3)+Acc!$AP$25+ManoDeObra!$D$27,0) -> 29.64924 | J27: =IF(PesoMatPrima!J27>0,(PesoMatPrima!J27*Tela!$J$3)+Acc!$AP$25+ManoDeObra!$D$27,0) -> 30.38256 | K27: =IF(PesoMatPrima!K27>0,(PesoMatPrima!K27*Tela!$J$3)+Acc!$AP$25+ManoDeObra!$D$27,0) -> 0 | L27: =IF(PesoMatPrima!L27>0,(PesoMatPrima!L27*Tela!$J$3)+Acc!$AP$25+ManoDeObra!$D$27,0) -> 0 | M27: =IF(PesoMatPrima!M27>0,(PesoMatPrima!M27*Tela!$J$3)+Acc!$AP$25+ManoDeObra!$E$27,0) -> 0 | N27: =IF(PesoMatPrima!N27>0,(PesoMatPrima!N27*Tela!$J$3)+Acc!$AP$25+ManoDeObra!$E$27,0) -> 0 | O27: =IF(PesoMatPrima!O27>0,(PesoMatPrima!O27*Tela!$J$3)+Acc!$AP$25+ManoDeObra!$E$27,0) -> 0 | P27: =IF(PesoMatPrima!P27>0,(PesoMatPrima!P27*Tela!$J$3)+Acc!$AP$25+ManoDeObra!$E$27,0) -> 0 | Q27: =IF(PesoMatPrima!Q27>0,(PesoMatPrima!Q27*Tela!$J$3)+Acc!$AP$25+ManoDeObra!$E$27,0) -> 0
A28: 26 | B28: Polera Bullying | C28: =IF(PesoMatPrima!C28>0,(PesoMatPrima!C28*Tela!$J$3)+Acc!$AP$26+ManoDeObra!$C$28,0) -> 26.6112
A29: 27 | B29: Saco | C29: =IF(PesoMatPrima!C29>0,(PesoMatPrima!C29*Tela!$J$11)+Acc!$AP$27+ManoDeObra!$C$29,0) -> 169.46402 | D29: =IF(PesoMatPrima!D29>0,(PesoMatPrima!D29*Tela!$J$11)+Acc!$AP$27+ManoDeObra!$C$29,0) -> 172.7455 | E29: =IF(PesoMatPrima!E29>0,(PesoMatPrima!E29*Tela!$J$11)+Acc!$AP$27+ManoDeObra!$C$29,0) -> 176.02698 | F29: =IF(PesoMatPrima!F29>0,(PesoMatPrima!F29*Tela!$J$11)+Acc!$AP$27+ManoDeObra!$C$29,0) -> 179.30846 | G29: =IF(PesoMatPrima!G29>0,(PesoMatPrima!G29*Tela!$J$11)+Acc!$AP$27+ManoDeObra!$C$29,0) -> 182.58994 | H29: =IF(PesoMatPrima!H29>0,(PesoMatPrima!H29*Tela!$J$11)+Acc!$AP$27+ManoDeObra!$D$29,0) -> 205.87141 | I29: =IF(PesoMatPrima!I29>0,(PesoMatPrima!I29*Tela!$J$11)+Acc!$AP$27+ManoDeObra!$D$29,0) -> 209.15289 | J29: =IF(PesoMatPrima!J29>0,(PesoMatPrima!J29*Tela!$J$11)+Acc!$AP$27+ManoDeObra!$D$29,0) -> 212.43437 | K29: =IF(PesoMatPrima!K29>0,(PesoMatPrima!K29*Tela!$J$11)+Acc!$AP$27+ManoDeObra!$D$29,0) -> 0 | L29: =IF(PesoMatPrima!L29>0,(PesoMatPrima!L29*Tela!$J$11)+Acc!$AP$27+ManoDeObra!$D$29,0) -> 215.71585 | M29: =IF(PesoMatPrima!M29>0,(PesoMatPrima!M29*Tela!$J$11)+Acc!$AP$27+ManoDeObra!$E$29,0) -> 248.99732 | N29: =IF(PesoMatPrima!N29>0,(PesoMatPrima!N29*Tela!$J$11)+Acc!$AP$27+ManoDeObra!$E$29,0) -> 252.2788 | O29: =IF(PesoMatPrima!O29>0,(PesoMatPrima!O29*Tela!$J$11)+Acc!$AP$27+ManoDeObra!$E$29,0) -> 255.56028 | P29: =IF(PesoMatPrima!P29>0,(PesoMatPrima!P29*Tela!$J$11)+Acc!$AP$27+ManoDeObra!$E$29,0) -> 258.84176 | Q29: =IF(PesoMatPrima!Q29>0,(PesoMatPrima!Q29*Tela!$J$11)+Acc!$AP$27+ManoDeObra!$E$29,0) -> 262.12324

Sheet PrecioDeVenta
A2: ITEM | B2: DETALLE | C2: 2 | D2: 4 | E2: 6 | F2: 8 | G2: 10 | H2: 12 | I2: 14 | J2: 16/34 | K2: 36/XS | L2: 38/S | M2: 40/M | N2: 42/L | O2: 44/XL | P2: 46/2XL | Q2: 48/3XL | R2: 50/4XL
A3: 1 | B3: Pantalón V, CC | C3: 0 | D3: 0 | E3: 0 | F3: 0 | G3: 0 | H3: 0 | I3: 0 | J3: 180 | K3: 190 | L3: 190 | M3: 200 | N3: 210 | O3: 210 | P3: 230 | Q3: 240 | R3: 250
A4: 2 | B4: Camisa m/c, CC | C4: 90 | D4: 90 | E4: 95 | F4: 100 | G4: 105 | H4: 110 | I4: 115 | J4: 120 | K4: 0 | L4: 130 | M4: 130 | N4: 135 | O4: 140 | P4: 145 | Q4: 160 | R4: 0
A5: 3 | B5: Camisa m/l, CC | C5: 100 | D5: 100 | E5: 105 | F5: 110 | G5: 115 | H5: 120 | I5: 130 | J5: 145 | K5: 0 | L5: 145 | M5: 0 | N5: 0 | O5: 0 | P5: 0 | Q5: 0 | R5: 0
A6: 4 | B6: Corbata Larga, CC | C6: 0 | D6: 0 | E6: 0 | F6: 0 | G6: 0 | H6: 0 | I6: 0 | J6: 0 | K6: 50 | L6: 0 | M6: 0 | N6: 0 | O6: 0 | P6: 0 | Q6: 0 | R6: 0
A7: 5 | B7: Pantalón c/elas, CC | C7: 100 | D7: 100 | E7: 105 | F7: 110 | G7: 115 | H7: 130 | I7: 160 | J7: 180 | K7: 0 | L7: 180 | M7: 0 | N7: 0 | O7: 0 | P7: 0 | Q7: 0 | R7: 0
A8: 6 | B8: Bermuda, CC | C8: 95 | D8: 95 | E8: 100 | F8: 105 | G8: 110 | H8: 125 | I8: 150 | J8: 170 | K8: 0 | M8: 0 | N8: 0 | O8: 0 | P8: 0 | Q8: 0 | R8: 0
A9: 7 | B9: Polera m/c, CC | C9: 70 | D9: 70 | E9: 70 | F9: 80 | G9: 80 | H9: 80 | I9: 90 | J9: 90 | K9: 0 | L9: 100 | M9: 100 | N9: 100 | O9: 105 | P9: 105 | Q9: 105 | R9: 0
A10: 8 | B10: Polera m/l, CC | C10: 80 | D10: 80 | E10: 80 | F10: 90 | G10: 90 | H10: 90 | I10: 100 | J10: 100 | K10: 0 | L10: 105 | M10: 105 | N10: 105 | O10: 115 | P10: 115 | Q10: 115 | R10: 0
A11: 9 | B11: Short, CC | C11: 65 | D11: 65 | E11: 70 | F11: 70 | G11: 75 | H11: 75 | I11: 85 | J11: 85 | K11: 0 | L11: 90 | M11: 90 | N11: 90 | O11: 95 | P11: 95 | Q11: 95 | R11: 0
A12: 10 | B12: Calza corta, CC | C12: 65 | D12: 65 | E12: 70 | F12: 70 | G12: 75 | H12: 75 | I12: 85 | J12: 85 | K12: 0 | L12: 90 | M12: 90 | N12: 90 | O12: 95 | P12: 95 | Q12: 95 | R12: 0
A13: 11 | B13: Calza larga, CC | C13: 95 | D13: 95 | E13: 95 | F13: 100 | G13: 100 | H13: 100 | I13: 105 | J13: 105 | K13: 0 | L13: 110 | M13: 110 | N13: 110 | O13: 115 | P13: 115 | Q13: 115 | R13: 0
A14: 12 | B14: Pantalón dama, CC | C14: 0 | D14: 0 | E14: 0 | F14: 0 | G14: 0 | H14: 0 | I14: 0 | J14: 180 | K14: 180 | L14: 180 | M14: 190 | N14: 200 | O14: 210 | P14: 220 | Q14: 230 | R14: 0
A15: 13 | B15: Blusa m/c, CC | C15: 90 | D15: 90 | E15: 95 | F15: 100 | G15: 105 | H15: 110 | I15: 115 | J15: 120 | K15: 125 | L15: 130 | M15: 130 | N15: 135 | O15: 140 | P15: 150 | Q15: 160 | R15: 0
A16: 14 | B16: Blusa m/l, CC | C16: 100 | D16: 100 | E16: 105 | F16: 110 | G16: 115 | H16: 120 | I16: 125 | J16: 130 | K16: 0 | L16: 0 | M16: 0 | N16: 0 | O16: 0 | P16: 0 | Q16: 0 | R16: 0
A17: 15 | B17: Corbata c/elas, CC | C17: 35 | D17: 0 | E17: 0 | F17: 0 | G17: 0 | H17: 0 | I17: 0 | J17: 0 | K17: 0 | L17: 0 | M17: 0 | N17: 0 | O17: 0 | P17: 0 | Q17: 0 | R17: 0
A18: 16 | B18: Falda Plisada, CC | C18: 105 | D18: 115 | E18: 115 | F18: 115 | G18: 120 | H18: 120 | I18: 125 | J18: 125 | K18: 0 | L18: 130 | M18: 135 | N18: 140 | O18: 145 | P18: 155 | Q18: 175 | R18: 0
A19: 17 | B19: Jamper, CC | C19: 105 | D19: 105 | E19: 115 | F19: 115 | G19: 125 | H19: 125 | I19: 0 | J19: 0 | K19: 0 | L19: 0 | M19: 0 | N19: 0 | O19: 0 | P19: 0 | Q19: 0 | R19: 0
A20: 18 | B20: Vestido, CC | C20: 0 | D20: 105 | E20: 115 | F20: 115 | G20: 0 | H20: 0 | I20: 0 | J20: 0 | K20: 0 | L20: 0 | M20: 0 | N20: 0 | O20: 0 | P20: 0 | Q20: 0 | R20: 0
... A29: 27 | B29: Saco, CC | C29: 0 | D29: 0 | E29: 0 | F29: 0 | G29: 0 | H29: 0 | I29: 0 | J29: 0 | K29: 0 | L29: 0 | M29: 0 | N29: 0 | O29: 0 | P29: 0 | Q29: 0 | R29: 0
A31: * Actualizados a diciembre de 2022

Sheet CostoAntesImp
A1: COSTO (ANTES DE IMPUESTOS) | E1: Costo bruto + Gastos Fijos/Variables x prenda
A2: ITEM | B2: DETALLE | C2: 2 | D2: 4 | E2: 6 | F2: 8 | G2: 10 | H2: 12 | I2: 14 | J2: 16/34 | K2: 36/XS | L2: 38/S | M2: 40/M | N2: 42/L | O2: 44/XL | P2: 46/2XL | Q2: 48/3XL | R2: 50/4XL
A3: 1 | B3: Pantalón de vestir | C3: =IF(CostoBruto!C3>0,CostoBruto!C3+fijosXprenda!$D$3,0) -> 0 | D3: =IF(CostoBruto!D3>0,CostoBruto!D3+fijosXprenda!$D$3,0) -> 0 | E3: =IF(CostoBruto!E3>0,CostoBruto!E3+fijosXprenda!$D$3,0) -> 0 | F3: =IF(CostoBruto!F3>0,CostoBruto!F3+fijosXprenda!$D$3,0) -> 0 | G3: =IF(CostoBruto!G3>0,CostoBruto!G3+fijosXprenda!$D$3,0) -> 0 | H3: =IF(CostoBruto!H3>0,CostoBruto!H3+fijosXprenda!$D$3,0) -> 0 | I3: =IF(CostoBruto!I3>0,CostoBruto!I3+fijosXprenda!$D$3,0) -> 0 | J3: =IF(CostoBruto!J3>0,CostoBruto!J3+fijosXprenda!$D$3,0) -> 106.65862 | ... R3: =IF(CostoBruto!R3>0,CostoBruto!R3+fijosXprenda!$D$3,0) -> 125.7952
A4: 2 | B4: Camisa manga corta | C4: =IF(CostoBruto!C4>0,CostoBruto!C4+fijosXprenda!$D$4,0) -> 55.267994 | D4: =IF(CostoBruto!D4>0,CostoBruto!D4+fijosXprenda!$D$4,0) -> 56.383038 | E4: =IF(CostoBruto!E4>0,CostoBruto!E4+fijosXprenda!$D$4,0) -> 57.498083 | F4: =IF(CostoBruto!F4>0,CostoBruto!F4+fijosXprenda!$D$4,0) -> 58.613127 | G4: =IF(CostoBruto!G4>0,CostoBruto!G4+fijosXprenda!$D$4,0) -> 59.728171 | H4: =IF(CostoBruto!H4>0,CostoBruto!H4+fijosXprenda!$D$4,0) -> 63.843215 | I4: =IF(CostoBruto!I4>0,CostoBruto!I4+fijosXprenda!$D$4,0) -> 64.95826 | J4: =IF(CostoBruto!J4>0,CostoBruto!J4+fijosXprenda!$D$4,0) -> 66.073304 | ... Q4: =IF(CostoBruto!Q4>0,CostoBruto!Q4+fijosXprenda!$D$4,0) -> 77.241445
A5: 3 | B5: Camisa manga larga | C5: =IF(CostoBruto!C5>0,CostoBruto!C5+fijosXprenda!$D$5,0) -> 60.487581 | D5: =IF(CostoBruto!D5>0,CostoBruto!D5+fijosXprenda!$D$5,0) -> 61.602625 | E5: =IF(CostoBruto!E5>0,CostoBruto!E5+fijosXprenda!$D$5,0) -> 62.71767 | F5: =IF(CostoBruto!F5>0,CostoBruto!F5+fijosXprenda!$D$5,0) -> 63.832714 | G5: =IF(CostoBruto!G5>0,CostoBruto!G5+fijosXprenda!$D$5,0) -> 64.947758 | H5: =IF(CostoBruto!H5>0,CostoBruto!H5+fijosXprenda!$D$5,0) -> 69.062802 | I5: =IF(CostoBruto!I5>0,CostoBruto!I5+fijosXprenda!$D$5,0) -> 70.177847 | J5: =IF(CostoBruto!J5>0,CostoBruto!J5+fijosXprenda!$D$5,0) -> 71.292891 | ... Q5: =IF(CostoBruto!Q5>0,CostoBruto!Q5+fijosXprenda!$D$5,0) -> 82.461032
A6: 4 | B6: Corbata larga | C6: =IF(CostoBruto!C6>0,CostoBruto!C6+fijosXprenda!$D$6,0) -> 0 | D6: =IF(CostoBruto!D6>0,CostoBruto!D6+fijosXprenda!$D$6,0) -> 0 | E6: =IF(CostoBruto!E6>0,CostoBruto!E6+fijosXprenda!$D$6,0) -> 0 | F6: =IF(CostoBruto!F6>0,CostoBruto!F6+fijosXprenda!$D$6,0) -> 0 | G6: =IF(CostoBruto!G6>0,CostoBruto!G6+fijosXprenda!$D$6,0) -> 0 | H6: =IF(CostoBruto!H6>0,CostoBruto!H6+fijosXprenda!$D$6,0) -> 0 | I6: =IF(CostoBruto!I6>0,CostoBruto!I6+fijosXprenda!$D$6,0) -> 0 | J6: =IF(CostoBruto!J6>0,CostoBruto!J6+fijosXprenda!$D$6,0) -> 0 | ... Q6: =IF(CostoBruto!Q6>0,CostoBruto!Q6+fijosXprenda!$D$6,0) -> 0
A7: 5 | B7: Pantalón con elástico | C7: =IF(CostoBruto!C7>0,CostoBruto!C7+fijosXprenda!$D$7,0) -> 50.923455 | D7: =IF(CostoBruto!D7>0,CostoBruto!D7+fijosXprenda!$D$7,0) -> 53.504919 | E7: =IF(CostoBruto!E7>0,CostoBruto!E7+fijosXprenda!$D$7,0) -> 56.086382 | F7: =IF(CostoBruto!F7>0,CostoBruto!F7+fijosXprenda!$D$7,0) -> 58.790772 | G7: =IF(CostoBruto!G7>0,CostoBruto!G7+fijosXprenda!$D$7,0) -> 61.372236 | H7: =IF(CostoBruto!H7>0,CostoBruto!H7+fijosXprenda!$D$7,0) -> 66.584919 | I7: =IF(CostoBruto!I7>0,CostoBruto!I7+fijosXprenda!$D$7,0) -> 68.797602 | J7: =IF(CostoBruto!J7>0,CostoBruto!J7+fijosXprenda!$D$7,0) -> 71.010285 | ... Q7: =IF(CostoBruto!Q7>0,CostoBruto!Q7+fijosXprenda!$D$7,0) -> 0
A8: 6 | B8: Bermuda | C8: =IF(CostoBruto!C8>0,CostoBruto!C8+fijosXprenda!$D$8,0) -> 44.819268 | D8: =IF(CostoBruto!D8>0,CostoBruto!D8+fijosXprenda!$D$8,0) -> 45.802683 | E8: =IF(CostoBruto!E8>0,CostoBruto!E8+fijosXprenda!$D$8,0) -> 47.154878 | F8: =IF(CostoBruto!F8>0,CostoBruto!F8+fijosXprenda!$D$8,0) -> 48.752927 | G8: =IF(CostoBruto!G8>0,CostoBruto!G8+fijosXprenda!$D$8,0) -> 50.96561 | H8: =IF(CostoBruto!H8>0,CostoBruto!H8+fijosXprenda!$D$8,0) -> 56.055366 | I8: =IF(CostoBruto!I8>0,CostoBruto!I8+fijosXprenda!$D$8,0) -> 56.792927 | J8: =IF(CostoBruto!J8>0,CostoBruto!J8+fijosXprenda!$D$8,0) -> 58.390976 | ... Q8: =IF(CostoBruto!Q8>0,CostoBruto!Q8+fijosXprenda!$D$8,0) -> 0
A9: 7 | B9: Polera manga corta | C9: =IF(CostoBruto!C9>0,CostoBruto!C9+fijosXprenda!$D$9,0) -> 40.556013 | D9: =IF(CostoBruto!D9>0,CostoBruto!D9+fijosXprenda!$D$9,0) -> 41.289333 | E9: =IF(CostoBruto!E9>0,CostoBruto!E9+fijosXprenda!$D$9,0) -> 42.022653 | F9: =IF(CostoBruto!F9>0,CostoBruto!F9+fijosXprenda!$D$9,0) -> 43.698813 | G9: =IF(CostoBruto!G9>0,CostoBruto!G9+fijosXprenda!$D$9,0) -> 45.374973 | H9: =IF(CostoBruto!H9>0,CostoBruto!H9+fijosXprenda!$D$9,0) -> 45.898773 | I9: =IF(CostoBruto!I9>0,CostoBruto!I9+fijosXprenda!$D$9,0) -> 46.422573 | J9: =IF(CostoBruto!J9>0,CostoBruto!J9+fijosXprenda!$D$9,0) -> 47.155893 | ... Q9: =IF(CostoBruto!Q9>0,CostoBruto!Q9+fijosXprenda!$D$9,0) -> 53.231973
A10: 8 | B10: Polera manga larga | C10: =IF(CostoBruto!C10>0,CostoBruto!C10+fijosXprenda!$D$10,0) -> 43.22408 | D10: =IF(CostoBruto!D10>0,CostoBruto!D10+fijosXprenda!$D$10,0) -> 43.9574 | E10: =IF(CostoBruto!E10>0,CostoBruto!E10+fijosXprenda!$D$10,0) -> 44.69072 | F10: =IF(CostoBruto!F10>0,CostoBruto!F10+fijosXprenda!$D$10,0) -> 46.36688 | G10: =IF(CostoBruto!G10>0,CostoBruto!G10+fijosXprenda!$D$10,0) -> 49.09064 | H10: =IF(CostoBruto!H10>0,CostoBruto!H10+fijosXprenda!$D$10,0) -> 49.61444 | I10: =IF(CostoBruto!I10>0,CostoBruto!I10+fijosXprenda!$D$10,0) -> 50.13824 | J10: =IF(CostoBruto!J10>0,CostoBruto!J10+fijosXprenda!$D$10,0) -> 50.87156 | ... Q10: =IF(CostoBruto!Q10>0,CostoBruto!Q10+fijosXprenda!$D$10,0) -> 57.47144
A11: 9 | B11: Short | C11: =IF(CostoBruto!C11>0,CostoBruto!C11+fijosXprenda!$D$11,0) -> 21.390292 | D11: =IF(CostoBruto!D11>0,CostoBruto!D11+fijosXprenda!$D$11,0) -> 21.653306 | E11: =IF(CostoBruto!E11>0,CostoBruto!E11+fijosXprenda!$D$11,0) -> 21.91632 | F11: =IF(CostoBruto!F11>0,CostoBruto!F11+fijosXprenda!$D$11,0) -> 22.11358 | G11: =IF(CostoBruto!G11>0,CostoBruto!G11+fijosXprenda!$D$11,0) -> 22.31084 | H11: =IF(CostoBruto!H11>0,CostoBruto!H11+fijosXprenda!$D$11,0) -> 22.639607 | I11: =IF(CostoBruto!I11>0,CostoBruto!I11+fijosXprenda!$D$11,0) -> 23.297142 | J11: =IF(CostoBruto!J11>0,CostoBruto!J11+fijosXprenda!$D$11,0) -> 23.823169 | ... Q11: =IF(CostoBruto!Q11>0,CostoBruto!Q11+fijosXprenda!$D$11,0) -> 26.519059
A12: 10 | B12: Calza corta | C12: =IF(CostoBruto!C12>0,CostoBruto!C12+fijosXprenda!$D$12,0) -> 26.022133 | D12: =IF(CostoBruto!D12>0,CostoBruto!D12+fijosXprenda!$D$12,0) -> 27.058933 | E12: =IF(CostoBruto!E12>0,CostoBruto!E12+fijosXprenda!$D$12,0) -> 28.095733 | F12: =IF(CostoBruto!F12>0,CostoBruto!F12+fijosXprenda!$D$12,0) -> 29.132533 | G12: =IF(CostoBruto!G12>0,CostoBruto!G12+fijosXprenda!$D$12,0) -> 30.169333 | H12: =IF(CostoBruto!H12>0,CostoBruto!H12+fijosXprenda!$D$12,0) -> 33.206133 | I12: =IF(CostoBruto!I12>0,CostoBruto!I12+fijosXprenda!$D$12,0) -> 34.242933 | J12: =IF(CostoBruto!J12>0,CostoBruto!J12+fijosXprenda!$D$12,0) -> 35.279733 | ... Q12: =IF(CostoBruto!Q12>0,CostoBruto!Q12+fijosXprenda!$D$12,0) -> 42.537333
A13: 11 | B13: Calza larga | C13: =IF(CostoBruto!C13>0,CostoBruto!C13+fijosXprenda!$D$13,0) -> 31.6364 | D13: =IF(CostoBruto!D13>0,CostoBruto!D13+fijosXprenda!$D$13,0) -> 33.3212 | E13: =IF(CostoBruto!E13>0,CostoBruto!E13+fijosXprenda!$D$13,0) -> 35.006 | F13: =IF(CostoBruto!F13>0,CostoBruto!F13+fijosXprenda!$D$13,0) -> 36.302 | G13: =IF(CostoBruto!G13>0,CostoBruto!G13+fijosXprenda!$D$13,0) -> 37.598 | H13: =IF(CostoBruto!H13>0,CostoBruto!H13+fijosXprenda!$D$13,0) -> 49.0588 | I13: =IF(CostoBruto!I13>0,CostoBruto!I13+fijosXprenda!$D$13,0) -> 51.91 | J13: =IF(CostoBruto!J13>0,CostoBruto!J13+fijosXprenda!$D$13,0) -> 53.4652 | ... Q13: =IF(CostoBruto!Q13>0,CostoBruto!Q13+fijosXprenda!$D$13,0) -> 62.7228
A14: 12 | B14: Pantalón para dama | C14: =IF(CostoBruto!C14>0,CostoBruto!C14+fijosXprenda!$D$14,0) -> 0 | D14: =IF(CostoBruto!D14>0,CostoBruto!D14+fijosXprenda!$D$14,0) -> 0 | E14: =IF(CostoBruto!E14>0,CostoBruto!E14+fijosXprenda!$D$14,0) -> 0 | F14: =IF(CostoBruto!F14>0,CostoBruto!F14+fijosXprenda!$D$14,0) -> 0 | G14: =IF(CostoBruto!G14>0,CostoBruto!G14+fijosXprenda!$D$14,0) -> 0 | H14: =IF(CostoBruto!H14>0,CostoBruto!H14+fijosXprenda!$D$14,0) -> 0 | I14: =IF(CostoBruto!I14>0,CostoBruto!I14+fijosXprenda!$D$14,0) -> 0 | J14: =IF(CostoBruto!J14>0,CostoBruto!J14+fijosXprenda!$D$14,0) -> 69.739431 | ... Q14: =IF(CostoBruto!Q14>0,CostoBruto!Q14+fijosXprenda!$D$14,0) -> 80.065285
A15: 13 | B15: Blusa manga corta | C15: =IF(CostoBruto!C15>0,CostoBruto!C15+fijosXprenda!$D$15,0) -> 50.170649 | D15: =IF(CostoBruto!D15>0,CostoBruto!D15+fijosXprenda!$D$15,0) -> 51.126401 | E15: =IF(CostoBruto!E15>0,CostoBruto!E15+fijosXprenda!$D$15,0) -> 51.922861 | F15: =IF(CostoBruto!F15>0,CostoBruto!F15+fijosXprenda!$D$15,0) -> 54.15295 | G15: =IF(CostoBruto!G15>0,CostoBruto!G15+fijosXprenda!$D$15,0) -> 55.74587 | H15: =IF(CostoBruto!H15>0,CostoBruto!H15+fijosXprenda!$D$15,0) -> 59.860914 | I15: =IF(CostoBruto!I15>0,CostoBruto!I15+fijosXprenda!$D$15,0) -> 60.179499 | J15: =IF(CostoBruto!J15>0,CostoBruto!J15+fijosXprenda!$D$15,0) -> 60.975959 | ... Q15: =IF(CostoBruto!Q15>0,CostoBruto!Q15+fijosXprenda!$D$15,0) -> 69.914012
A16: 14 | B16: Blusa manga larga | C16: =IF(CostoBruto!C16>0,CostoBruto!C16+fijosXprenda!$D$16,0) -> 52.00115 | D16: =IF(CostoBruto!D16>0,CostoBruto!D16+fijosXprenda!$D$16,0) -> 52.956903 | E16: =IF(CostoBruto!E16>0,CostoBruto!E16+fijosXprenda!$D$16,0) -> 53.753363 | F16: =IF(CostoBruto!F16>0,CostoBruto!F16+fijosXprenda!$D$16,0) -> 55.983451 | G16: =IF(CostoBruto!G16>0,CostoBruto!G16+fijosXprenda!$D$16,0) -> 57.735664 | H16: =IF(CostoBruto!H16>0,CostoBruto!H16+fijosXprenda!$D$16,0) -> 61.850708 | I16: =IF(CostoBruto!I16>0,CostoBruto!I16+fijosXprenda!$D$16,0) -> 62.169292 | J16: =IF(CostoBruto!J16>0,CostoBruto!J16+fijosXprenda!$D$16,0) -> 62.965752 | ... Q16: =IF(CostoBruto!Q16>0,CostoBruto!Q16+fijosXprenda!$D$16,0) -> 72.222389
A17: 15 | B17: Corbata con elástico | C17: =IF(CostoBruto!C17>0,CostoBruto!C17+fijosXprenda!$D$17,0) -> 13.571961 | D17: =IF(CostoBruto!D17>0,CostoBruto!D17+fijosXprenda!$D$17,0) -> 0 | E17: =IF(CostoBruto!E17>0,CostoBruto!E17+fijosXprenda!$D$17,0) -> 0 | F17: =IF(CostoBruto!F17>0,CostoBruto!F17+fijosXprenda!$D$17,0) -> 0 | G17: =IF(CostoBruto!G17>0,CostoBruto!G17+fijosXprenda!$D$17,0) -> 0 | H17: =IF(CostoBruto!H17>0,CostoBruto!H17+fijosXprenda!$D$17,0) -> 0 | I17: =IF(CostoBruto!I17>0,CostoBruto!I17+fijosXprenda!$D$17,0) -> 0 | J17: =IF(CostoBruto!J17>0,CostoBruto!J17+fijosXprenda!$D$17,0) -> 0 | ... Q17: =IF(CostoBruto!Q17>0,CostoBruto!Q17+fijosXprenda!$D$17,0) -> 0
A18: 16 | B18: Falda plisada | C18: =IF(CostoBruto!C18>0,CostoBruto!C18+fijosXprenda!$D$18,0) -> 68.556078 | D18: =IF(CostoBruto!D18>0,CostoBruto!D18+fijosXprenda!$D$18,0) -> 70.250196 | E18: =IF(CostoBruto!E18>0,CostoBruto!E18+fijosXprenda!$D$18,0) -> 71.944314 | F18: =IF(CostoBruto!F18>0,CostoBruto!F18+fijosXprenda!$D$18,0) -> 73.638431 | G18: =IF(CostoBruto!G18>0,CostoBruto!G18+fijosXprenda!$D$18,0) -> 75.332549 | H18: =IF(CostoBruto!H18>0,CostoBruto!H18+fijosXprenda!$D$18,0) -> 77.026667 | I18: =IF(CostoBruto!I18>0,CostoBruto!I18+fijosXprenda!$D$18,0) -> 78.932549 | J18: =IF(CostoBruto!J18>0,CostoBruto!J18+fijosXprenda!$D$18,0) -> 80.626667 | ... Q18: =IF(CostoBruto!Q18>0,CostoBruto!Q18+fijosXprenda!$D$18,0) -> 90.791373
A19: 17 | B19: Jamper | C19: =IF(CostoBruto!C19>0,CostoBruto!C19+fijosXprenda!$D$19,0) -> 54.534118 | D19: =IF(CostoBruto!D19>0,CostoBruto!D19+fijosXprenda!$D$19,0) -> 57.075294 | E19: =IF(CostoBruto!E19>0,CostoBruto!E19+fijosXprenda!$D$19,0) -> 59.616471 | F19: =IF(CostoBruto!F19>0,CostoBruto!F19+fijosXprenda!$D$19,0) -> 62.157647 | G19: =IF(CostoBruto!G19>0,CostoBruto!G19+fijosXprenda!$D$19,0) -> 64.698824 | H19: =IF(CostoBruto!H19>0,CostoBruto!H19+fijosXprenda!$D$19,0) -> 67.24 | I19: =IF(CostoBruto!I19>0,CostoBruto!I19+fijosXprenda!$D$19,0) -> 0 | J19: =IF(CostoBruto!J19>0,CostoBruto!J19+fijosXprenda!$D$19,0) -> 0 | ... Q19: =IF(CostoBruto!Q19>0,CostoBruto!Q19+fijosXprenda!$D$19,0) -> 0
A20: 18 | B20: Vestido | C20: =IF(CostoBruto!C20>0,CostoBruto!C20+fijosXprenda!$D$20,0) -> 66.310588 | D20: =IF(CostoBruto!D20>0,CostoBruto!D20+fijosXprenda!$D$20,0) -> 70.334118 | E20: =IF(CostoBruto!E20>0,CostoBruto!E20+fijosXprenda!$D$20,0) -> 74.357647 | F20: =IF(CostoBruto!F20>0,CostoBruto!F20+fijosXprenda!$D$20,0) -> 78.381176 | G20: =IF(CostoBruto!G20>0,CostoBruto!G20+fijosXprenda!$D$20,0) -> 82.404706 | H20: =IF(CostoBruto!H20>0,CostoBruto!H20+fijosXprenda!$D$20,0) -> 86.428235 | I20: =IF(CostoBruto!I20>0,CostoBruto!I20+fijosXprenda!$D$20,0) -> 0 | J20: =IF(CostoBruto!J20>0,CostoBruto!J20+fijosXprenda!$D$20,0) -> 0 | ... Q20: =IF(CostoBruto!Q20>0,CostoBruto!Q20+fijosXprenda!$D$20,0) -> 0
A21: 19 | B21: Chompa cuello en V | C21: =IF(CostoBruto!C21>0,CostoBruto!C21+fijosXprenda!$D$21,0) -> 59.033333 | D21: =IF(CostoBruto!D21>0,CostoBruto!D21+fijosXprenda!$D$21,0) -> 59.033333 | E21: =IF(CostoBruto!E21>0,CostoBruto!E21+fijosXprenda!$D$21,0) -> 64.033333 | F21: =IF(CostoBruto!F21>0,CostoBruto!F21+fijosXprenda!$D$21,0) -> 69.033333 | G21: =IF(CostoBruto!G21>0,CostoBruto!G21+fijosXprenda!$D$21,0) -> 74.033333 | H21: =IF(CostoBruto!H21>0,CostoBruto!H21+fijosXprenda!$D$21,0) -> 79.033333 | I21: =IF(CostoBruto!I21>0,CostoBruto!I21+fijosXprenda!$D$21,0) -> 84.033333 | J21: =IF(CostoBruto!J21>0,CostoBruto!J21+fijosXprenda!$D$21,0) -> 89.033333 | ... Q21: =IF(CostoBruto!Q21>0,CostoBruto!Q21+fijosXprenda!$D$21,0) -> 149.03333
A22: 20 | B22: Chaleco cuello en V | C22: =IF(CostoBruto!C22>0,CostoBruto!C22+fijosXprenda!$D$22,0) -> 54.033333 | D22: =IF(CostoBruto!D22>0,CostoBruto!D22+fijosXprenda!$D$22,0) -> 54.033333 | E22: =IF(CostoBruto!E22>0,CostoBruto!E22+fijosXprenda!$D$22,0) -> 59.033333 | F22: =IF(CostoBruto!F22>0,CostoBruto!F22+fijosXprenda!$D$22,0) -> 64.033333 | G22: =IF(CostoBruto!G22>0,CostoBruto!G22+fijosXprenda!$D$22,0) -> 69.033333 | H22: =IF(CostoBruto!H22>0,CostoBruto!H22+fijosXprenda!$D$22,0) -> 74.033333 | I22: =IF(CostoBruto!I22>0,CostoBruto!I22+fijosXprenda!$D$22,0) -> 79.033333 | J22: =IF(CostoBruto!J22>0,CostoBruto!J22+fijosXprenda!$D$22,0) -> 84.033333 | ... Q22: =IF(CostoBruto!Q22>0,CostoBruto!Q22+fijosXprenda!$D$22,0) -> 144.03333
A23: 21 | B23: Chamarra de verano | C23: =IF(CostoBruto!C23>0,CostoBruto!C23+fijosXprenda!$D$23,0) -> 124.46805 | D23: =IF(CostoBruto!D23>0,CostoBruto!D23+fijosXprenda!$D$23,0) -> 126.37977 | E23: =IF(CostoBruto!E23>0,CostoBruto!E23+fijosXprenda!$D$23,0) -> 128.29149 | F23: =IF(CostoBruto!F23>0,CostoBruto!F23+fijosXprenda!$D$23,0) -> 130.20322 | G23: =IF(CostoBruto!G23>0,CostoBruto!G23+fijosXprenda!$D$23,0) -> 132.11494 | H23: =IF(CostoBruto!H23>0,CostoBruto!H23+fijosXprenda!$D$23,0) -> 139.02667 | I23: =IF(CostoBruto!I23>0,CostoBruto!I23+fijosXprenda!$D$23,0) -> 140.93839 | J23: =IF(CostoBruto!J23>0,CostoBruto!J23+fijosXprenda!$D$23,0) -> 142.85011 | ... Q23: =IF(CostoBruto!Q23>0,CostoBruto!Q23+fijosXprenda!$D$23,0) -> 157.58253
A24: 22 | B24: Chamarra deportiva | C24: =IF(CostoBruto!C24>0,CostoBruto!C24+fijosXprenda!$D$24,0) -> 124.70671 | D24: =IF(CostoBruto!D24>0,CostoBruto!D24+fijosXprenda!$D$24,0) -> 126.61844 | E24: =IF(CostoBruto!E24>0,CostoBruto!E24+fijosXprenda!$D$24,0) -> 128.53016 | F24: =IF(CostoBruto!F24>0,CostoBruto!F24+fijosXprenda!$D$24,0) -> 130.44189 | G24: =IF(CostoBruto!G24>0,CostoBruto!G24+fijosXprenda!$D$24,0) -> 132.35361 | H24: =IF(CostoBruto!H24>0,CostoBruto!H24+fijosXprenda!$D$24,0) -> 139.26533 | I24: =IF(CostoBruto!I24>0,CostoBruto!I24+fijosXprenda!$D$24,0) -> 141.17706 | J24: =IF(CostoBruto!J24>0,CostoBruto!J24+fijosXprenda!$D$24,0) -> 143.08878 | ... Q24: =IF(CostoBruto!Q24>0,CostoBruto!Q24+fijosXprenda!$D$24,0) -> 157.8212
A25: 23 | B25: Chamarra de invierno | C25: =IF(CostoBruto!C25>0,CostoBruto!C25+fijosXprenda!$D$25,0) -> 132.15685 | D25: =IF(CostoBruto!D25>0,CostoBruto!D25+fijosXprenda!$D$25,0) -> 134.25975 | E25: =IF(CostoBruto!E25>0,CostoBruto!E25+fijosXprenda!$D$25,0) -> 136.36264 | F25: =IF(CostoBruto!F25>0,CostoBruto!F25+fijosXprenda!$D$25,0) -> 138.46554 | G25: =IF(CostoBruto!G25>0,CostoBruto!G25+fijosXprenda!$D$25,0) -> 140.56844 | H25: =IF(CostoBruto!H25>0,CostoBruto!H25+fijosXprenda!$D$25,0) -> 147.67133 | I25: =IF(CostoBruto!I25>0,CostoBruto!I25+fijosXprenda!$D$25,0) -> 149.77423 | J25: =IF(CostoBruto!J25>0,CostoBruto!J25+fijosXprenda!$D$25,0) -> 151.87713 | ... Q25: =IF(CostoBruto!Q25>0,CostoBruto!Q25+fijosXprenda!$D$25,0) -> 167.58278
A26: 24 | B26: Buso Deportivo | C26: =IF(CostoBruto!C26>0,CostoBruto!C26+fijosXprenda!$D$26,0) -> 69.35554 | D26: =IF(CostoBruto!D26>0,CostoBruto!D26+fijosXprenda!$D$26,0) -> 73.178989 | E26: =IF(CostoBruto!E26>0,CostoBruto!E26+fijosXprenda!$D$26,0) -> 77.002437 | F26: =IF(CostoBruto!F26>0,CostoBruto!F26+fijosXprenda!$D$26,0) -> 80.825885 | G26: =IF(CostoBruto!G26>0,CostoBruto!G26+fijosXprenda!$D$26,0) -> 84.649333 | H26: =IF(CostoBruto!H26>0,CostoBruto!H26+fijosXprenda!$D$26,0) -> 90.472782 | I26: =IF(CostoBruto!I26>0,CostoBruto!I26+fijosXprenda!$D$26,0) -> 94.643816 | J26: =IF(CostoBruto!J26>0,CostoBruto!J26+fijosXprenda!$D$26,0) -> 98.988644 | ... Q26: =IF(CostoBruto!Q26>0,CostoBruto!Q26+fijosXprenda!$D$26,0) -> 116.63002
A27: 25 | B27: Polera de colores | C27: =IF(CostoBruto!C27>0,CostoBruto!C27+fijosXprenda!$D$27,0) -> 28.556013 | D27: =IF(CostoBruto!D27>0,CostoBruto!D27+fijosXprenda!$D$27,0) -> 29.289333 | E27: =IF(CostoBruto!E27>0,CostoBruto!E27+fijosXprenda!$D$27,0) -> 30.022653 | F27: =IF(CostoBruto!F27>0,CostoBruto!F27+fijosXprenda!$D$27,0) -> 31.698813 | G27: =IF(CostoBruto!G27>0,CostoBruto!G27+fijosXprenda!$D$27,0) -> 33.374973 | H27: =IF(CostoBruto!H27>0,CostoBruto!H27+fijosXprenda!$D$27,0) -> 33.898773 | I27: =IF(CostoBruto!I27>0,CostoBruto!I27+fijosXprenda!$D$27,0) -> 34.422573 | J27: =IF(CostoBruto!J27>0,CostoBruto!J27+fijosXprenda!$D$27,0) -> 35.155893 | ... Q27: =IF(CostoBruto!Q27>0,CostoBruto!Q27+fijosXprenda!$D$27,0) -> 0
A28: 26 | B28: Polera Bullying | C28: =IF(CostoBruto!C28>0,CostoBruto!C28+fijosXprenda!$D$28,0) -> 31.384533 | D28: =IF(CostoBruto!D28>0,CostoBruto!D28+fijosXprenda!$D$28,0) -> 0 | E28: =IF(CostoBruto!E28>0,CostoBruto!E28+fijosXprenda!$D$28,0) -> 0 | F28: =IF(CostoBruto!F28>0,CostoBruto!F28+fijosXprenda!$D$28,0) -> 0 | G28: =IF(CostoBruto!G28>0,CostoBruto!G28+fijosXprenda!$D$28,0) -> 0 | H28: =IF(CostoBruto!H28>0,CostoBruto!H28+fijosXprenda!$D$28,0) -> 0 | I28: =IF(CostoBruto!I28>0,CostoBruto!I28+fijosXprenda!$D$28,0) -> 0 | J28: =IF(CostoBruto!J28>0,CostoBruto!J28+fijosXprenda!$D$28,0) -> 0 | ... Q28: =IF(CostoBruto!Q28>0,CostoBruto!Q28+fijosXprenda!$D$28,0) -> 0
A29: 27 | B29: Saco | C29: =IF(CostoBruto!C29>0,CostoBruto!C29+fijosXprenda!$D$29,0) -> 181.39736 | D29: =IF(CostoBruto!D29>0,CostoBruto!D29+fijosXprenda!$D$29,0) -> 184.67883 | E29: =IF(CostoBruto!E29>0,CostoBruto!E29+fijosXprenda!$D$29,0) -> 187.96031 | F29: =IF(CostoBruto!F29>0,CostoBruto!F29+fijosXprenda!$D$29,0) -> 191.24179 | G29: =IF(CostoBruto!G29>0,CostoBruto!G29+fijosXprenda!$D$29,0) -> 194.52327 | H29: =IF(CostoBruto!H29>0,CostoBruto!H29+fijosXprenda!$D$29,0) -> 217.80475 | I29: =IF(CostoBruto!I29>0,CostoBruto!I29+fijosXprenda!$D$29,0) -> 221.08622 | J29: =IF(CostoBruto!J29>0,CostoBruto!J29+fijosXprenda!$D$29,0) -> 224.3677 | ... Q29: =IF(CostoBruto!Q29>0,CostoBruto!Q29+fijosXprenda!$D$29,0) -> 274.05657
B31: Impuesto % | C31: 13

Sheet CostoTotal
A1: COSTO (CON IMPUESTOS) | E1: Costo + 13%
A2: ITEM | B2: DETALLE | C2: 2 | D2: 4 | E2: 6 | F2: 8 | G2: 10 | H2: 12 | I2: 14 | J2: 16/34 | K2: 36/XS | L2: 38/S | M2: 40/M | N2: 42/L | O2: 44/XL | P2: 46/2XL | Q2: 48/3XL | R2: 50/4XL
A3: 1 | B3: Pantalón de vestir | C3: =IF(CostoAntesImp!C3>0,CostoAntesImp!C3+(CostoAntesImp!C3*$C$31/100),0) -> 0 | D3: =IF(CostoAntesImp!D3>0,CostoAntesImp!D3+(CostoAntesImp!D3*$C$31/100),0) -> 0 | E3: =IF(CostoAntesImp!E3>0,CostoAntesImp!E3+(CostoAntesImp!E3*$C$31/100),0) -> 0 | F3: =IF(CostoAntesImp!F3>0,CostoAntesImp!F3+(CostoAntesImp!F3*$C$31/100),0) -> 0 | G3: =IF(CostoAntesImp!G3>0,CostoAntesImp!G3+(CostoAntesImp!G3*$C$31/100),0) -> 0 | H3: =IF(CostoAntesImp!H3>0,CostoAntesImp!H3+(CostoAntesImp!H3*$C$31/100),0) -> 0 | I3: =IF(CostoAntesImp!I3>0,CostoAntesImp!I3+(CostoAntesImp!I3*$C$31/100),0) -> 0 | J3: =IF(CostoAntesImp!J3>0,CostoAntesImp!J3+(CostoAntesImp!J3*$C$31/100),0) -> 120.52424 | ... R3: =IF(CostoAntesImp!R3>0,CostoAntesImp!R3+(CostoAntesImp!R3*$C$31/100),0) -> 142.14858
A4: 2 | B4: Camisa manga corta | C4: =IF(CostoAntesImp!C4>0,CostoAntesImp!C4+(CostoAntesImp!C4*$C$31/100),0) -> 62.452833 | D4: =IF(CostoAntesImp!D4>0,CostoAntesImp!D4+(CostoAntesImp!D4*$C$31/100),0) -> 63.712833 | E4: =IF(CostoAntesImp!E4>0,CostoAntesImp!E4+(CostoAntesImp!E4*$C$31/100),0) -> 64.972833 | F4: =IF(CostoAntesImp!F4>0,CostoAntesImp!F4+(CostoAntesImp!F4*$C$31/100),0) -> 66.232833 | G4: =IF(CostoAntesImp!G4>0,CostoAntesImp!G4+(CostoAntesImp!G4*$C$31/100),0) -> 67.492833 | H4: =IF(CostoAntesImp!H4>0,CostoAntesImp!H4+(CostoAntesImp!H4*$C$31/100),0) -> 72.142833 | I4: =IF(CostoAntesImp!I4>0,CostoAntesImp!I4+(CostoAntesImp!I4*$C$31/100),0) -> 73.402833 | J4: =IF(CostoAntesImp!J4>0,CostoAntesImp!J4+(CostoAntesImp!J4*$C$31/100),0) -> 74.662833 | ... Q4: =IF(CostoAntesImp!Q4>0,CostoAntesImp!Q4+(CostoAntesImp!Q4*$C$31/100),0) -> 87.282833
A5: 3 | B5: Camisa manga larga | C5: =IF(CostoAntesImp!C5>0,CostoAntesImp!C5+(CostoAntesImp!C5*$C$31/100),0) -> 68.350967 | D5: =IF(CostoAntesImp!D5>0,CostoAntesImp!D5+(CostoAntesImp!D5*$C$31/100),0) -> 69.610967 | E5: =IF(CostoAntesImp!E5>0,CostoAntesImp!E5+(CostoAntesImp!E5*$C$31/100),0) -> 70.870967 | F5: =IF(CostoAntesImp!F5>0,CostoAntesImp!F5+(CostoAntesImp!F5*$C$31/100),0) -> 72.130967 | G5: =IF(CostoAntesImp!G5>0,CostoAntesImp!G5+(CostoAntesImp!G5*$C$31/100),0) -> 73.390967 | H5: =IF(CostoAntesImp!H5>0,CostoAntesImp!H5+(CostoAntesImp!H5*$C$31/100),0) -> 78.040967 | I5: =IF(CostoAntesImp!I5>0,CostoAntesImp!I5+(CostoAntesImp!I5*$C$31/100),0) -> 79.300967 | J5: =IF(CostoAntesImp!J5>0,CostoAntesImp!J5+(CostoAntesImp!J5*$C$31/100),0) -> 80.560967 | ... Q5: =IF(CostoAntesImp!Q5>0,CostoAntesImp!Q5+(CostoAntesImp!Q5*$C$31/100),0) -> 93.180967
A6: 4 | B6: Corbata larga | C6: =IF(CostoAntesImp!C6>0,CostoAntesImp!C6+(CostoAntesImp!C6*$C$31/100),0) -> 0 | D6: =IF(CostoAntesImp!D6>0,CostoAntesImp!D6+(CostoAntesImp!D6*$C$31/100),0) -> 0 | E6: =IF(CostoAntesImp!E6>0,CostoAntesImp!E6+(CostoAntesImp!E6*$C$31/100),0) -> 0 | F6: =IF(CostoAntesImp!F6>0,CostoAntesImp!F6+(CostoAntesImp!F6*$C$31/100),0) -> 0 | G6: =IF(CostoAntesImp!G6>0,CostoAntesImp!G6+(CostoAntesImp!G6*$C$31/100),0) -> 0 | H6: =IF(CostoAntesImp!H6>0,CostoAntesImp!H6+(CostoAntesImp!H6*$C$31/100),0) -> 0 | I6: =IF(CostoAntesImp!I6>0,CostoAntesImp!I6+(CostoAntesImp!I6*$C$31/100),0) -> 0 | J6: =IF(CostoAntesImp!J6>0,CostoAntesImp!J6+(CostoAntesImp!J6*$C$31/100),0) -> 0 | ... Q6: =IF(CostoAntesImp!Q6>0,CostoAntesImp!Q6+(CostoAntesImp!Q6*$C$31/100),0) -> 0
A7: 5 | B7: Pantalón con elástico | C7: =IF(CostoAntesImp!C7>0,CostoAntesImp!C7+(CostoAntesImp!C7*$C$31/100),0) -> 57.543504 | D7: =IF(CostoAntesImp!D7>0,CostoAntesImp!D7+(CostoAntesImp!D7*$C$31/100),0) -> 60.460558 | E7: =IF(CostoAntesImp!E7>0,CostoAntesImp!E7+(CostoAntesImp!E7*$C$31/100),0) -> 63.377612 | F7: =IF(CostoAntesImp!F7>0,CostoAntesImp!F7+(CostoAntesImp!F7*$C$31/100),0) -> 66.433573 | G7: =IF(CostoAntesImp!G7>0,CostoAntesImp!G7+(CostoAntesImp!G7*$C$31/100),0) -> 69.350626 | H7: =IF(CostoAntesImp!H7>0,CostoAntesImp!H7+(CostoAntesImp!H7*$C$31/100),0) -> 75.240958 | I7: =IF(CostoAntesImp!I7>0,CostoAntesImp!I7+(CostoAntesImp!I7*$C$31/100),0) -> 77.74129 | J7: =IF(CostoAntesImp!J7>0,CostoAntesImp!J7+(CostoAntesImp!J7*$C$31/100),0) -> 80.241622 | ... Q7: =IF(CostoAntesImp!Q7>0,CostoAntesImp!Q7+(CostoAntesImp!Q7*$C$31/100),0) -> 0
A8: 6 | B8: Bermuda | C8: =IF(CostoAntesImp!C8>0,CostoAntesImp!C8+(CostoAntesImp!C8*$C$31/100),0) -> 50.645773 | D8: =IF(CostoAntesImp!D8>0,CostoAntesImp!D8+(CostoAntesImp!D8*$C$31/100),0) -> 51.757032 | E8: =IF(CostoAntesImp!E8>0,CostoAntesImp!E8+(CostoAntesImp!E8*$C$31/100),0) -> 53.285012 | F8: =IF(CostoAntesImp!F8>0,CostoAntesImp!F8+(CostoAntesImp!F8*$C$31/100),0) -> 55.090807 | G8: =IF(CostoAntesImp!G8>0,CostoAntesImp!G8+(CostoAntesImp!G8*$C$31/100),0) -> 57.591139 | H8: =IF(CostoAntesImp!H8>0,CostoAntesImp!H8+(CostoAntesImp!H8*$C$31/100),0) -> 63.342563 | I8: =IF(CostoAntesImp!I8>0,CostoAntesImp!I8+(CostoAntesImp!I8*$C$31/100),0) -> 64.176007 | J8: =IF(CostoAntesImp!J8>0,CostoAntesImp!J8+(CostoAntesImp!J8*$C$31/100),0) -> 65.981802 | ... Q8: =IF(CostoAntesImp!Q8>0,CostoAntesImp!Q8+(CostoAntesImp!Q8*$C$31/100),0) -> 0
A9: 7 | B9: Polera manga corta | C9: =IF(CostoAntesImp!C9>0,CostoAntesImp!C9+(CostoAntesImp!C9*$C$31/100),0) -> 45.828295 | D9: =IF(CostoAntesImp!D9>0,CostoAntesImp!D9+(CostoAntesImp!D9*$C$31/100),0) -> 46.656947 | E9: =IF(CostoAntesImp!E9>0,CostoAntesImp!E9+(CostoAntesImp!E9*$C$31/100),0) -> 47.485598 | F9: =IF(CostoAntesImp!F9>0,CostoAntesImp!F9+(CostoAntesImp!F9*$C$31/100),0) -> 49.379659 | G9: =IF(CostoAntesImp!G9>0,CostoAntesImp!G9+(CostoAntesImp!G9*$C$31/100),0) -> 51.27372 | H9: =IF(CostoAntesImp!H9>0,CostoAntesImp!H9+(CostoAntesImp!H9*$C$31/100),0) -> 51.865614 | I9: =IF(CostoAntesImp!I9>0,CostoAntesImp!I9+(CostoAntesImp!I9*$C$31/100),0) -> 52.457508 | J9: =IF(CostoAntesImp!J9>0,CostoAntesImp!J9+(CostoAntesImp!J9*$C$31/100),0) -> 53.286159 | ... Q9: =IF(CostoAntesImp!Q9>0,CostoAntesImp!Q9+(CostoAntesImp!Q9*$C$31/100),0) -> 60.15213
A10: 8 | B10: Polera manga larga | C10: =IF(CostoAntesImp!C10>0,CostoAntesImp!C10+(CostoAntesImp!C10*$C$31/100),0) -> 48.84321 | D10: =IF(CostoAntesImp!D10>0,CostoAntesImp!D10+(CostoAntesImp!D10*$C$31/100),0) -> 49.671862 | E10: =IF(CostoAntesImp!E10>0,CostoAntesImp!E10+(CostoAntesImp!E10*$C$31/100),0) -> 50.500514 | F10: =IF(CostoAntesImp!F10>0,CostoAntesImp!F10+(CostoAntesImp!F10*$C$31/100),0) -> 52.394574 | G10: =IF(CostoAntesImp!G10>0,CostoAntesImp!G10+(CostoAntesImp!G10*$C$31/100),0) -> 55.472423 | H10: =IF(CostoAntesImp!H10>0,CostoAntesImp!H10+(CostoAntesImp!H10*$C$31/100),0) -> 56.064317 | I10: =IF(CostoAntesImp!I10>0,CostoAntesImp!I10+(CostoAntesImp!I10*$C$31/100),0) -> 56.656211 | J10: =IF(CostoAntesImp!J10>0,CostoAntesImp!J10+(CostoAntesImp!J10*$C$31/100),0) -> 57.484863 | ... Q10: =IF(CostoAntesImp!Q10>0,CostoAntesImp!Q10+(CostoAntesImp!Q10*$C$31/100),0) -> 64.942727
A11: 9 | B11: Short | C11: =IF(CostoAntesImp!C11>0,CostoAntesImp!C11+(CostoAntesImp!C11*$C$31/100),0) -> 24.17103 | D11: =IF(CostoAntesImp!D11>0,CostoAntesImp!D11+(CostoAntesImp!D11*$C$31/100),0) -> 24.468236 | E11: =IF(CostoAntesImp!E11>0,CostoAntesImp!E11+(CostoAntesImp!E11*$C$31/100),0) -> 24.765441 | F11: =IF(CostoAntesImp!F11>0,CostoAntesImp!F11+(CostoAntesImp!F11*$C$31/100),0) -> 24.988345 | G11: =IF(CostoAntesImp!G11>0,CostoAntesImp!G11+(CostoAntesImp!G11*$C$31/100),0) -> 25.211249 | H11: =IF(CostoAntesImp!H11>0,CostoAntesImp!H11+(CostoAntesImp!H11*$C$31/100),0) -> 25.582756 | I11: =IF(CostoAntesImp!I11>0,CostoAntesImp!I11+(CostoAntesImp!I11*$C$31/100),0) -> 26.32577 | J11: =IF(CostoAntesImp!J11>0,CostoAntesImp!J11+(CostoAntesImp!J11*$C$31/100),0) -> 26.920181 | ... Q11: =IF(CostoAntesImp!Q11>0,CostoAntesImp!Q11+(CostoAntesImp!Q11*$C$31/100),0) -> 29.966537
A12: 10 | B12: Calza corta | C12: =IF(CostoAntesImp!C12>0,CostoAntesImp!C12+(CostoAntesImp!C12*$C$31/100),0) -> 29.405011 | D12: =IF(CostoAntesImp!D12>0,CostoAntesImp!D12+(CostoAntesImp!D12*$C$31/100),0) -> 30.576595 | E12: =IF(CostoAntesImp!E12>0,CostoAntesImp!E12+(CostoAntesImp!E12*$C$31/100),0) -> 31.748179 | F12: =IF(CostoAntesImp!F12>0,CostoAntesImp!F12+(CostoAntesImp!F12*$C$31/100),0) -> 32.919763 | G12: =IF(CostoAntesImp!G12>0,CostoAntesImp!G12+(CostoAntesImp!G12*$C$31/100),0) -> 34.091347 | H12: =IF(CostoAntesImp!H12>0,CostoAntesImp!H12+(CostoAntesImp!H12*$C$31/100),0) -> 37.522931 | I12: =IF(CostoAntesImp!I12>0,CostoAntesImp!I12+(CostoAntesImp!I12*$C$31/100),0) -> 38.694515 | J12: =IF(CostoAntesImp!J12>0,CostoAntesImp!J12+(CostoAntesImp!J12*$C$31/100),0) -> 39.866099 | ... Q12: =IF(CostoAntesImp!Q12>0,CostoAntesImp!Q12+(CostoAntesImp!Q12*$C$31/100),0) -> 48.067187
A13: 11 | B13: Calza larga | C13: =IF(CostoAntesImp!C13>0,CostoAntesImp!C13+(CostoAntesImp!C13*$C$31/100),0) -> 35.749132 | D13: =IF(CostoAntesImp!D13>0,CostoAntesImp!D13+(CostoAntesImp!D13*$C$31/100),0) -> 37.652956 | E13: =IF(CostoAntesImp!E13>0,CostoAntesImp!E13+(CostoAntesImp!E13*$C$31/100),0) -> 39.55678 | F13: =IF(CostoAntesImp!F13>0,CostoAntesImp!F13+(CostoAntesImp!F13*$C$31/100),0) -> 41.02126 | G13: =IF(CostoAntesImp!G13>0,CostoAntesImp!G13+(CostoAntesImp!G13*$C$31/100),0) -> 42.48574 | H13: =IF(CostoAntesImp!H13>0,CostoAntesImp!H13+(CostoAntesImp!H13*$C$31/100),0) -> 55.436444 | I13: =IF(CostoAntesImp!I13>0,CostoAntesImp!I13+(CostoAntesImp!I13*$C$31/100),0) -> 58.6583 | J13: =IF(CostoAntesImp!J13>0,CostoAntesImp!J13+(CostoAntesImp!J13*$C$31/100),0) -> 60.415676 | ... Q13: =IF(CostoAntesImp!Q13>0,CostoAntesImp!Q13+(CostoAntesImp!Q13*$C$31/100),0) -> 70.876764
A14: 12 | B14: Pantalón para dama | C14: =IF(CostoAntesImp!C14>0,CostoAntesImp!C14+(CostoAntesImp!C14*$C$31/100),0) -> 0 | D14: =IF(CostoAntesImp!D14>0,CostoAntesImp!D14+(CostoAntesImp!D14*$C$31/100),0) -> 0 | E14: =IF(CostoAntesImp!E14>0,CostoAntesImp!E14+(CostoAntesImp!E14*$C$31/100),0) -> 0 | F14: =IF(CostoAntesImp!F14>0,CostoAntesImp!F14+(CostoAntesImp!F14*$C$31/100),0) -> 0 | G14: =IF(CostoAntesImp!G14>0,CostoAntesImp!G14+(CostoAntesImp!G14*$C$31/100),0) -> 0 | H14: =IF(CostoAntesImp!H14>0,CostoAntesImp!H14+(CostoAntesImp!H14*$C$31/100),0) -> 0 | I14: =IF(CostoAntesImp!I14>0,CostoAntesImp!I14+(CostoAntesImp!I14*$C$31/100),0) -> 0 | J14: =IF(CostoAntesImp!J14>0,CostoAntesImp!J14+(CostoAntesImp!J14*$C$31/100),0) -> 78.805557 | ... Q14: =IF(CostoAntesImp!Q14>0,CostoAntesImp!Q14+(CostoAntesImp!Q14*$C$31/100),0) -> 90.473772
A15: 13 | B15: Blusa manga corta | C15: =IF(CostoAntesImp!C15>0,CostoAntesImp!C15+(CostoAntesImp!C15*$C$31/100),0) -> 56.692833 | D15: =IF(CostoAntesImp!D15>0,CostoAntesImp!D15+(CostoAntesImp!D15*$C$31/100),0) -> 57.772833 | E15: =IF(CostoAntesImp!E15>0,CostoAntesImp!E15+(CostoAntesImp!E15*$C$31/100),0) -> 58.672833 | F15: =IF(CostoAntesImp!F15>0,CostoAntesImp!F15+(CostoAntesImp!F15*$C$31/100),0) -> 61.192833 | G15: =IF(CostoAntesImp!G15>0,CostoAntesImp!G15+(CostoAntesImp!G15*$C$31/100),0) -> 62.992833 | H15: =IF(CostoAntesImp!H15>0,CostoAntesImp!H15+(CostoAntesImp!H15*$C$31/100),0) -> 67.642833 | I15: =IF(CostoAntesImp!I15>0,CostoAntesImp!I15+(CostoAntesImp!I15*$C$31/100),0) -> 68.002833 | J15: =IF(CostoAntesImp!J15>0,CostoAntesImp!J15+(CostoAntesImp!J15*$C$31/100),0) -> 68.902833 | ... Q15: =IF(CostoAntesImp!Q15>0,CostoAntesImp!Q15+(CostoAntesImp!Q15*$C$31/100),0) -> 79.002833
... A29: 27 | B29: Saco | C29: =IF(CostoAntesImp!C29>0,CostoAntesImp!C29+(CostoAntesImp!C29*$C$31/100),0) -> 204.97901 | D29: =IF(CostoAntesImp!D29>0,CostoAntesImp!D29+(CostoAntesImp!D29*$C$31/100),0) -> 208.68708 | E29: =IF(CostoAntesImp!E29>0,CostoAntesImp!E29+(CostoAntesImp!E29*$C$31/100),0) -> 212.39515 | F29: =IF(CostoAntesImp!F29>0,CostoAntesImp!F29+(CostoAntesImp!F29*$C$31/100),0) -> 216.10322 | G29: =IF(CostoAntesImp!G29>0,CostoAntesImp!G29+(CostoAntesImp!G29*$C$31/100),0) -> 219.81129 | H29: =IF(CostoAntesImp!H29>0,CostoAntesImp!H29+(CostoAntesImp!H29*$C$31/100),0) -> 246.11936 | I29: =IF(CostoAntesImp!I29>0,CostoAntesImp!I29+(CostoAntesImp!I29*$C$31/100),0) -> 249.82743 | J29: =IF(CostoAntesImp!J29>0,CostoAntesImp!J29+(CostoAntesImp!J29*$C$31/100),0) -> 253.5355 | ... Q29: =IF(CostoAntesImp!Q29>0,CostoAntesImp!Q29+(CostoAntesImp!Q29*$C$31/100),0) -> 309.68392
B31: Impuesto % | C31: 13

Sheet UtilidadNeta
A1: UTILIDAD NETA | C1: Precio de Venta - Costo Total
A2: ITEM | B2: DETALLE | C2: 2 | D2: 4 | E2: 6 | F2: 8 | G2: 10 | H2: 12 | I2: 14 | J2: 16/34 | K2: 36/XS | L2: 38/S | M2: 40/M | N2: 42/L | O2: 44/XL | P2: 46/2XL | Q2: 48/3XL | R2: 50/4XL
A3: 1 | B3: Pantalón de vestir | C3: =IF(PrecioDeVenta!C3>0,PrecioDeVenta!C3-CostoTotal!C3,0) -> 0 | D3: =IF(PrecioDeVenta!D3>0,PrecioDeVenta!D3-CostoTotal!D3,0) -> 0 | E3: =IF(PrecioDeVenta!E3>0,PrecioDeVenta!E3-CostoTotal!E3,0) -> 0 | F3: =IF(PrecioDeVenta!F3>0,PrecioDeVenta!F3-CostoTotal!F3,0) -> 0 | G3: =IF(PrecioDeVenta!G3>0,PrecioDeVenta!G3-CostoTotal!G3,0) -> 0 | H3: =IF(PrecioDeVenta!H3>0,PrecioDeVenta!H3-CostoTotal!H3,0) -> 0 | I3: =IF(PrecioDeVenta!I3>0,PrecioDeVenta!I3-CostoTotal!I3,0) -> 0 | J3: =IF(PrecioDeVenta!J3>0,PrecioDeVenta!J3-CostoTotal!J3,0) -> 59.475762 | ... R3: =IF(PrecioDeVenta!R3>0,PrecioDeVenta!R3-CostoTotal!R3,0) -> 107.85142
A4: 2 | B4: Camisa manga corta | C4: =IF(PrecioDeVenta!C4>0,PrecioDeVenta!C4-CostoTotal!C4,0) -> 27.547167 | D4: =IF(PrecioDeVenta!D4>0,PrecioDeVenta!D4-CostoTotal!D4,0) -> 26.287167 | E4: =IF(PrecioDeVenta!E4>0,PrecioDeVenta!E4-CostoTotal!E4,0) -> 30.027167 | F4: =IF(PrecioDeVenta!F4>0,PrecioDeVenta!F4-CostoTotal!F4,0) -> 33.767167 | G4: =IF(PrecioDeVenta!G4>0,PrecioDeVenta!G4-CostoTotal!G4,0) -> 37.507167 | H4: =IF(PrecioDeVenta!H4>0,PrecioDeVenta!H4-CostoTotal!H4,0) -> 37.857167 | I4: =IF(PrecioDeVenta!I4>0,PrecioDeVenta!I4-CostoTotal!I4,0) -> 41.597167 | J4: =IF(PrecioDeVenta!J4>0,PrecioDeVenta!J4-CostoTotal!J4,0) -> 45.337167 | ... R4: =IF(PrecioDeVenta!R4>0,PrecioDeVenta!R4-CostoTotal!R4,0) -> 0
A5: 3 | B5: Camisa manga larga | C5: =IF(PrecioDeVenta!C5>0,PrecioDeVenta!C5-CostoTotal!C5,0) -> 31.649033 | D5: =IF(PrecioDeVenta!D5>0,PrecioDeVenta!D5-CostoTotal!D5,0) -> 30.389033 | E5: =IF(PrecioDeVenta!E5>0,PrecioDeVenta!E5-CostoTotal!E5,0) -> 34.129033 | F5: =IF(PrecioDeVenta!F5>0,PrecioDeVenta!F5-CostoTotal!F5,0) -> 37.869033 | G5: =IF(PrecioDeVenta!G5>0,PrecioDeVenta!G5-CostoTotal!G5,0) -> 41.609033 | H5: =IF(PrecioDeVenta!H5>0,PrecioDeVenta!H5-CostoTotal!H5,0) -> 41.959033 | I5: =IF(PrecioDeVenta!I5>0,PrecioDeVenta!I5-CostoTotal!I5,0) -> 50.699033 | J5: =IF(PrecioDeVenta!J5>0,PrecioDeVenta!J5-CostoTotal!J5,0) -> 64.439033 | ... R5: =IF(PrecioDeVenta!R5>0,PrecioDeVenta!R5-CostoTotal!R5,0) -> 0
A6: 4 | B6: Corbata larga | C6: =IF(PrecioDeVenta!C6>0,PrecioDeVenta!C6-CostoTotal!C6,0) -> 0 | D6: =IF(PrecioDeVenta!D6>0,PrecioDeVenta!D6-CostoTotal!D6,0) -> 0 | E6: =IF(PrecioDeVenta!E6>0,PrecioDeVenta!E6-CostoTotal!E6,0) -> 0 | F6: =IF(PrecioDeVenta!F6>0,PrecioDeVenta!F6-CostoTotal!F6,0) -> 0 | G6: =IF(PrecioDeVenta!G6>0,PrecioDeVenta!G6-CostoTotal!G6,0) -> 0 | H6: =IF(PrecioDeVenta!H6>0,PrecioDeVenta!H6-CostoTotal!H6,0) -> 0 | I6: =IF(PrecioDeVenta!I6>0,PrecioDeVenta!I6-CostoTotal!I6,0) -> 0 | J6: =IF(PrecioDeVenta!J6>0,PrecioDeVenta!J6-CostoTotal!J6,0) -> 0 | ... R6: =IF(PrecioDeVenta!R6>0,PrecioDeVenta!R6-CostoTotal!R6,0) -> 0
A7: 5 | B7: Pantalón con elástico | C7: =IF(PrecioDeVenta!C7>0,PrecioDeVenta!C7-CostoTotal!C7,0) -> 42.456496 | D7: =IF(PrecioDeVenta!D7>0,PrecioDeVenta!D7-CostoTotal!D7,0) -> 39.539442 | E7: =IF(PrecioDeVenta!E7>0,PrecioDeVenta!E7-CostoTotal!E7,0) -> 41.622388 | F7: =IF(PrecioDeVenta!F7>0,PrecioDeVenta!F7-CostoTotal!F7,0) -> 43.566427 | G7: =IF(PrecioDeVenta!G7>0,PrecioDeVenta!G7-CostoTotal!G7,0) -> 45.649374 | H7: =IF(PrecioDeVenta!H7>0,PrecioDeVenta!H7-CostoTotal!H7,0) -> 54.759042 | I7: =IF(PrecioDeVenta!I7>0,PrecioDeVenta!I7-CostoTotal!I7,0) -> 82.25871 | J7: =IF(PrecioDeVenta!J7>0,PrecioDeVenta!J7-CostoTotal!J7,0) -> 99.758378 | ... R7: =IF(PrecioDeVenta!R7>0,PrecioDeVenta!R7-CostoTotal!R7,0) -> 0
A8: 6 | B8: Bermuda | C8: =IF(PrecioDeVenta!C8>0,PrecioDeVenta!C8-CostoTotal!C8,0) -> 44.354227 | D8: =IF(PrecioDeVenta!D8>0,PrecioDeVenta!D8-CostoTotal!D8,0) -> 43.242968 | E8: =IF(PrecioDeVenta!E8>0,PrecioDeVenta!E8-CostoTotal!E8,0) -> 46.714988 | F8: =IF(PrecioDeVenta!F8>0,PrecioDeVenta!F8-CostoTotal!F8,0) -> 49.909193 | G8: =IF(PrecioDeVenta!G8>0,PrecioDeVenta!G8-CostoTotal!G8,0) -> 52.408861 | H8: =IF(PrecioDeVenta!H8>0,PrecioDeVenta!H8-CostoTotal!H8,0) -> 61.657437 | I8: =IF(PrecioDeVenta!I8>0,PrecioDeVenta!I8-CostoTotal!I8,0) -> 85.823993 | J8: =IF(PrecioDeVenta!J8>0,PrecioDeVenta!J8-CostoTotal!J8,0) -> 104.0182 | ... R8: =IF(PrecioDeVenta!R8>0,PrecioDeVenta!R8-CostoTotal!R8,0) -> 0
A9: 7 | B9: Polera manga corta | C9: =IF(PrecioDeVenta!C9>0,PrecioDeVenta!C9-CostoTotal!C9,0) -> 24.171705 | D9: =IF(PrecioDeVenta!D9>0,PrecioDeVenta!D9-CostoTotal!D9,0) -> 23.343053 | E9: =IF(PrecioDeVenta!E9>0,PrecioDeVenta!E9-CostoTotal!E9,0) -> 22.514402 | F9: =IF(PrecioDeVenta!F9>0,PrecioDeVenta!F9-CostoTotal!F9,0) -> 30.620341 | G9: =IF(PrecioDeVenta!G9>0,PrecioDeVenta!G9-CostoTotal!G9,0) -> 28.72628 | H9: =IF(PrecioDeVenta!H9>0,PrecioDeVenta!H9-CostoTotal!H9,0) -> 28.134386 | I9: =IF(PrecioDeVenta!I9>0,PrecioDeVenta!I9-CostoTotal!I9,0) -> 37.542492 | J9: =IF(PrecioDeVenta!J9>0,PrecioDeVenta!J9-CostoTotal!J9,0) -> 36.713841 | ... R9: =IF(PrecioDeVenta!R9>0,PrecioDeVenta!R9-CostoTotal!R9,0) -> 0
A10: 8 | B10: Polera manga larga | C10: =IF(PrecioDeVenta!C10>0,PrecioDeVenta!C10-CostoTotal!C10,0) -> 31.15679 | D10: =IF(PrecioDeVenta!D10>0,PrecioDeVenta!D10-CostoTotal!D10,0) -> 30.328138 | E10: =IF(PrecioDeVenta!E10>0,PrecioDeVenta!E10-CostoTotal!E10,0) -> 29.499486 | F10: =IF(PrecioDeVenta!F10>0,PrecioDeVenta!F10-CostoTotal!F10,0) -> 37.605426 | G10: =IF(PrecioDeVenta!G10>0,PrecioDeVenta!G10-CostoTotal!G10,0) -> 34.527577 | H10: =IF(PrecioDeVenta!H10>0,PrecioDeVenta!H10-CostoTotal!H10,0) -> 33.935683 | I10: =IF(PrecioDeVenta!I10>0,PrecioDeVenta!I10-CostoTotal!I10,0) -> 43.343789 | J10: =IF(PrecioDeVenta!J10>0,PrecioDeVenta!J10-CostoTotal!J10,0) -> 42.515137 | ... R10: =IF(PrecioDeVenta!R10>0,PrecioDeVenta!R10-CostoTotal!R10,0) -> 0
A11: 9 | B11: Short | C11: =IF(PrecioDeVenta!C11>0,PrecioDeVenta!C11-CostoTotal!C11,0) -> 40.82897 | D11: =IF(PrecioDeVenta!D11>0,PrecioDeVenta!D11-CostoTotal!D11,0) -> 40.531764 | E11: =IF(PrecioDeVenta!E11>0,PrecioDeVenta!E11-CostoTotal!E11,0) -> 45.234559 | F11: =IF(PrecioDeVenta!F11>0,PrecioDeVenta!F11-CostoTotal!F11,0) -> 45.011655 | G11: =IF(PrecioDeVenta!G11>0,PrecioDeVenta!G11-CostoTotal!G11,0) -> 49.788751 | H11: =IF(PrecioDeVenta!H11>0,PrecioDeVenta!H11-CostoTotal!H11,0) -> 49.417244 | I11: =IF(PrecioDeVenta!I11>0,PrecioDeVenta!I11-CostoTotal!I11,0) -> 58.67423 | J11: =IF(PrecioDeVenta!J11>0,PrecioDeVenta!J11-CostoTotal!J11,0) -> 58.079819 | ... R11: =IF(PrecioDeVenta!R11>0,PrecioDeVenta!R11-CostoTotal!R11,0) -> 0
A12: 10 | B12: Calza corta | C12: =IF(PrecioDeVenta!C12>0,PrecioDeVenta!C12-CostoTotal!C12,0) -> 35.594989 | D12: =IF(PrecioDeVenta!D12>0,PrecioDeVenta!D12-CostoTotal!D12,0) -> 34.423405 | E12: =IF(PrecioDeVenta!E12>0,PrecioDeVenta!E12-CostoTotal!E12,0) -> 38.251821 | F12: =IF(PrecioDeVenta!F12>0,PrecioDeVenta!F12-CostoTotal!F12,0) -> 37.080237 | G12: =IF(PrecioDeVenta!G12>0,PrecioDeVenta!G12-CostoTotal!G12,0) -> 40.908653 | H12: =IF(PrecioDeVenta!H12>0,PrecioDeVenta!H12-CostoTotal!H12,0) -> 37.477069 | I12: =IF(PrecioDeVenta!I12>0,PrecioDeVenta!I12-CostoTotal!I12,0) -> 46.305485 | J12: =IF(PrecioDeVenta!J12>0,PrecioDeVenta!J12-CostoTotal!J12,0) -> 45.133901 | ... R12: =IF(PrecioDeVenta!R12>0,PrecioDeVenta!R12-CostoTotal!R12,0) -> 0
A13: 11 | B13: Calza larga | C13: =IF(PrecioDeVenta!C13>0,PrecioDeVenta!C13-CostoTotal!C13,0) -> 59.250868 | D13: =IF(PrecioDeVenta!D13>0,PrecioDeVenta!D13-CostoTotal!D13,0) -> 57.347044 | E13: =IF(PrecioDeVenta!E13>0,PrecioDeVenta!E13-CostoTotal!E13,0) -> 55.44322 | F13: =IF(PrecioDeVenta!F13>0,PrecioDeVenta!F13-CostoTotal!F13,0) -> 58.97874 | G13: =IF(PrecioDeVenta!G13>0,PrecioDeVenta!G13-CostoTotal!G13,0) -> 57.51426 | H13: =IF(PrecioDeVenta!H13>0,PrecioDeVenta!H13-CostoTotal!H13,0) -> 44.563556 | I13: =IF(PrecioDeVenta!I13>0,PrecioDeVenta!I13-CostoTotal!I13,0) -> 46.3417 | J13: =IF(PrecioDeVenta!J13>0,PrecioDeVenta!J13-CostoTotal!J13,0) -> 44.584324 | ... R13: =IF(PrecioDeVenta!R13>0,PrecioDeVenta!R13-CostoTotal!R13,0) -> 0
A14: 12 | B14: Pantalón para dama | C14: =IF(PrecioDeVenta!C14>0,PrecioDeVenta!C14-CostoTotal!C14,0) -> 0 | D14: =IF(PrecioDeVenta!D14>0,PrecioDeVenta!D14-CostoTotal!D14,0) -> 0 | E14: =IF(PrecioDeVenta!E14>0,PrecioDeVenta!E14-CostoTotal!E14,0) -> 0 | F14: =IF(PrecioDeVenta!F14>0,PrecioDeVenta!F14-CostoTotal!F14,0) -> 0 | G14: =IF(PrecioDeVenta!G14>0,PrecioDeVenta!G14-CostoTotal!G14,0) -> 0 | H14: =IF(PrecioDeVenta!H14>0,PrecioDeVenta!H14-CostoTotal!H14,0) -> 0 | I14: =IF(PrecioDeVenta!I14>0,PrecioDeVenta!I14-CostoTotal!I14,0) -> 0 | J14: =IF(PrecioDeVenta!J14>0,PrecioDeVenta!J14-CostoTotal!J14,0) -> 101.19444 | ... R14: =IF(PrecioDeVenta!R14>0,PrecioDeVenta!R14-CostoTotal!R14,0) -> 0
... A29: 27 | B29: Saco | C29: =IF(PrecioDeVenta!C29>0,PrecioDeVenta!C29-CostoTotal!C29,0) -> 0 | D29: =IF(PrecioDeVenta!D29>0,PrecioDeVenta!D29-CostoTotal!D29,0) -> 0 | E29: =IF(PrecioDeVenta!E29>0,PrecioDeVenta!E29-CostoTotal!E29,0) -> 0 | F29: =IF(PrecioDeVenta!F29>0,PrecioDeVenta!F29-CostoTotal!F29,0) -> 0 | G29: =IF(PrecioDeVenta!G29>0,PrecioDeVenta!G29-CostoTotal!G29,0) -> 0 | H29: =IF(PrecioDeVenta!H29>0,PrecioDeVenta!H29-CostoTotal!H29,0) -> 0 | I29: =IF(PrecioDeVenta!I29>0,PrecioDeVenta!I29-CostoTotal!I29,0) -> 0 | J29: =IF(PrecioDeVenta!J29>0,PrecioDeVenta!J29-CostoTotal!J29,0) -> 0 | ... R29: =IF(PrecioDeVenta!R29>0,PrecioDeVenta!R29-CostoTotal!R29,0) -> 0
B31: Impuesto % | C31: 13

Sheet %Ganancia
A1: MARGEN DE UTILIDAD NETA %
A2: ITEM | B2: DETALLE | C2: 2 | D2: 4 | E2: 6 | F2: 8 | G2: 10 | H2: 12 | I2: 14 | J2: 16/34 | K2: 36/XS | L2: 38/S | M2: 40/M | N2: 42/L | O2: 44/XL | P2: 46/2XL | Q2: 48/3XL | R2: 50/4XL
A3: 1 | B3: Pantalón de vestir | C3: =IF(PrecioDeVenta!C3>0,(UtilidadNeta!C3*100)/PrecioDeVenta!C3,0) -> 0 | D3: =IF(PrecioDeVenta!D3>0,(UtilidadNeta!D3*100)/PrecioDeVenta!D3,0) -> 0 | E3: =IF(PrecioDeVenta!E3>0,(UtilidadNeta!E3*100)/PrecioDeVenta!E3,0) -> 0 | F3: =IF(PrecioDeVenta!F3>0,(UtilidadNeta!F3*100)/PrecioDeVenta!F3,0) -> 0 | G3: =IF(PrecioDeVenta!G3>0,(UtilidadNeta!G3*100)/PrecioDeVenta!G3,0) -> 0 | H3: =IF(PrecioDeVenta!H3>0,(UtilidadNeta!H3*100)/PrecioDeVenta!H3,0) -> 0 | I3: =IF(PrecioDeVenta!I3>0,(UtilidadNeta!I3*100)/PrecioDeVenta!I3,0) -> 0 | J3: =IF(PrecioDeVenta!J3>0,(UtilidadNeta!J3*100)/PrecioDeVenta!J3,0) -> 33.04209 | ... R3: =IF(PrecioDeVenta!R3>0,(UtilidadNeta!R3*100)/PrecioDeVenta!R3,0) -> 43.140568
A4: 2 | B4: Camisa manga corta | C4: =IF(PrecioDeVenta!C4>0,(UtilidadNeta!C4*100)/PrecioDeVenta!C4,0) -> 30.607963 | D4: =IF(PrecioDeVenta!D4>0,(UtilidadNeta!D4*100)/PrecioDeVenta!D4,0) -> 29.207963 | E4: =IF(PrecioDeVenta!E4>0,(UtilidadNeta!E4*100)/PrecioDeVenta!E4,0) -> 31.607544 | F4: =IF(PrecioDeVenta!F4>0,(UtilidadNeta!F4*100)/PrecioDeVenta!F4,0) -> 33.767167 | G4: =IF(PrecioDeVenta!G4>0,(UtilidadNeta!G4*100)/PrecioDeVenta!G4,0) -> 35.721111 | H4: =IF(PrecioDeVenta!H4>0,(UtilidadNeta!H4*100)/PrecioDeVenta!H4,0) -> 34.415606 | I4: =IF(PrecioDeVenta!I4>0,(UtilidadNeta!I4*100)/PrecioDeVenta!I4,0) -> 36.171449 | J4: =IF(PrecioDeVenta!J4>0,(UtilidadNeta!J4*100)/PrecioDeVenta!J4,0) -> 37.780972 | ... Q4: =IF(PrecioDeVenta!Q4>0,(UtilidadNeta!Q4*100)/PrecioDeVenta!Q4,0) -> 45.448229
A5: 3 | B5: Camisa manga larga | C5: =IF(PrecioDeVenta!C5>0,(UtilidadNeta!C5*100)/PrecioDeVenta!C5,0) -> 31.649033 | D5: =IF(PrecioDeVenta!D5>0,(UtilidadNeta!D5*100)/PrecioDeVenta!D5,0) -> 30.389033 | E5: =IF(PrecioDeVenta!E5>0,(UtilidadNeta!E5*100)/PrecioDeVenta!E5,0) -> 32.503841 | F5: =IF(PrecioDeVenta!F5>0,(UtilidadNeta!F5*100)/PrecioDeVenta!F5,0) -> 34.426394 | G5: =IF(PrecioDeVenta!G5>0,(UtilidadNeta!G5*100)/PrecioDeVenta!G5,0) -> 36.181768 | H5: =IF(PrecioDeVenta!H5>0,(UtilidadNeta!H5*100)/PrecioDeVenta!H5,0) -> 34.965861 | I5: =IF(PrecioDeVenta!I5>0,(UtilidadNeta!I5*100)/PrecioDeVenta!I5,0) -> 38.999256 | J5: =IF(PrecioDeVenta!J5>0,(UtilidadNeta!J5*100)/PrecioDeVenta!J5,0) -> 44.440713 | ... Q5: =IF(PrecioDeVenta!Q5>0,(UtilidadNeta!Q5*100)/PrecioDeVenta!Q5,0) -> 0
A6: 4 | B6: Corbata larga | C6: =IF(PrecioDeVenta!C6>0,(UtilidadNeta!C6*100)/PrecioDeVenta!C6,0) -> 0 | D6: =IF(PrecioDeVenta!D6>0,(UtilidadNeta!D6*100)/PrecioDeVenta!D6,0) -> 0 | E6: =IF(PrecioDeVenta!E6>0,(UtilidadNeta!E6*100)/PrecioDeVenta!E6,0) -> 0 | F6: =IF(PrecioDeVenta!F6>0,(UtilidadNeta!F6*100)/PrecioDeVenta!F6,0) -> 0 | G6: =IF(PrecioDeVenta!G6>0,(UtilidadNeta!G6*100)/PrecioDeVenta!G6,0) -> 0 | H6: =IF(PrecioDeVenta!H6>0,(UtilidadNeta!H6*100)/PrecioDeVenta!H6,0) -> 0 | I6: =IF(PrecioDeVenta!I6>0,(UtilidadNeta!I6*100)/PrecioDeVenta!I6,0) -> 0 | J6: =IF(PrecioDeVenta!J6>0,(UtilidadNeta!J6*100)/PrecioDeVenta!J6,0) -> 0 | ... Q6: =IF(PrecioDeVenta!Q6>0,(UtilidadNeta!Q6*100)/PrecioDeVenta!Q6,0) -> 0
A7: 5 | B7: Pantalón con elástico | C7: =IF(PrecioDeVenta!C7>0,(UtilidadNeta!C7*100)/PrecioDeVenta!C7,0) -> 42.456496 | D7: =IF(PrecioDeVenta!D7>0,(UtilidadNeta!D7*100)/PrecioDeVenta!D7,0) -> 39.539442 | E7: =IF(PrecioDeVenta!E7>0,(UtilidadNeta!E7*100)/PrecioDeVenta!E7,0) -> 39.64037 | F7: =IF(PrecioDeVenta!F7>0,(UtilidadNeta!F7*100)/PrecioDeVenta!F7,0) -> 39.605843 | G7: =IF(PrecioDeVenta!G7>0,(UtilidadNeta!G7*100)/PrecioDeVenta!G7,0) -> 39.695107 | H7: =IF(PrecioDeVenta!H7>0,(UtilidadNeta!H7*100)/PrecioDeVenta!H7,0) -> 42.12234 | I7: =IF(PrecioDeVenta!I7>0,(UtilidadNeta!I7*100)/PrecioDeVenta!I7,0) -> 51.411694 | J7: =IF(PrecioDeVenta!J7>0,(UtilidadNeta!J7*100)/PrecioDeVenta!J7,0) -> 55.421321 | ... Q7: =IF(PrecioDeVenta!Q7>0,(UtilidadNeta!Q7*100)/PrecioDeVenta!Q7,0) -> 0
A8: 6 | B8: Bermuda | C8: =IF(PrecioDeVenta!C8>0,(UtilidadNeta!C8*100)/PrecioDeVenta!C8,0) -> 46.68866 | D8: =IF(PrecioDeVenta!D8>0,(UtilidadNeta!D8*100)/PrecioDeVenta!D8,0) -> 45.518914 | E8: =IF(PrecioDeVenta!E8>0,(UtilidadNeta!E8*100)/PrecioDeVenta!E8,0) -> 46.714988 | F8: =IF(PrecioDeVenta!F8>0,(UtilidadNeta!F8*100)/PrecioDeVenta!F8,0) -> 47.532564 | G8: =IF(PrecioDeVenta!G8>0,(UtilidadNeta!G8*100)/PrecioDeVenta!G8,0) -> 47.644419 | H8: =IF(PrecioDeVenta!H8>0,(UtilidadNeta!H8*100)/PrecioDeVenta!H8,0) -> 49.325949 | I8: =IF(PrecioDeVenta!I8>0,(UtilidadNeta!I8*100)/PrecioDeVenta!I8,0) -> 57.215995 | J8: =IF(PrecioDeVenta!J8>0,(UtilidadNeta!J8*100)/PrecioDeVenta!J8,0) -> 61.187175 | ... Q8: =IF(PrecioDeVenta!Q8>0,(UtilidadNeta!Q8*100)/PrecioDeVenta!Q8,0) -> 0
A9: 7 | B9: Polera manga corta | C9: =IF(PrecioDeVenta!C9>0,(UtilidadNeta!C9*100)/PrecioDeVenta!C9,0) -> 34.531007 | D9: =IF(PrecioDeVenta!D9>0,(UtilidadNeta!D9*100)/PrecioDeVenta!D9,0) -> 33.347219 | E9: =IF(PrecioDeVenta!E9>0,(UtilidadNeta!E9*100)/PrecioDeVenta!E9,0) -> 32.163431 | F9: =IF(PrecioDeVenta!F9>0,(UtilidadNeta!F9*100)/PrecioDeVenta!F9,0) -> 38.275426 | G9: =IF(PrecioDeVenta!G9>0,(UtilidadNeta!G9*100)/PrecioDeVenta!G9,0) -> 35.90785 | H9: =IF(PrecioDeVenta!H9>0,(UtilidadNeta!H9*100)/PrecioDeVenta!H9,0) -> 35.167983 | I9: =IF(PrecioDeVenta!I9>0,(UtilidadNeta!I9*100)/PrecioDeVenta!I9,0) -> 41.71388 | J9: =IF(PrecioDeVenta!J9>0,(UtilidadNeta!J9*100)/PrecioDeVenta!J9,0) -> 40.793156 | ... Q9: =IF(PrecioDeVenta!Q9>0,(UtilidadNeta!Q9*100)/PrecioDeVenta!Q9,0) -> 42.712257
A10: 8 | B10: Polera manga larga | C10: =IF(PrecioDeVenta!C10>0,(UtilidadNeta!C10*100)/PrecioDeVenta!C10,0) -> 38.945987 | D10: =IF(PrecioDeVenta!D10>0,(UtilidadNeta!D10*100)/PrecioDeVenta!D10,0) -> 37.910173 | E10: =IF(PrecioDeVenta!E10>0,(UtilidadNeta!E10*100)/PrecioDeVenta!E10,0) -> 36.874358 | F10: =IF(PrecioDeVenta!F10>0,(UtilidadNeta!F10*100)/PrecioDeVenta!F10,0) -> 41.783806 | G10: =IF(PrecioDeVenta!G10>0,(UtilidadNeta!G10*100)/PrecioDeVenta!G10,0) -> 38.363974 | H10: =IF(PrecioDeVenta!H10>0,(UtilidadNeta!H10*100)/PrecioDeVenta!H10,0) -> 37.706314 | I10: =IF(PrecioDeVenta!I10>0,(UtilidadNeta!I10*100)/PrecioDeVenta!I10,0) -> 43.343789 | J10: =IF(PrecioDeVenta!J10>0,(UtilidadNeta!J10*100)/PrecioDeVenta!J10,0) -> 42.515137 | ... Q10: =IF(PrecioDeVenta!Q10>0,(UtilidadNeta!Q10*100)/PrecioDeVenta!Q10,0) -> 43.528063
A11: 9 | B11: Short | C11: =IF(PrecioDeVenta!C11>0,(UtilidadNeta!C11*100)/PrecioDeVenta!C11,0) -> 62.8138 | D11: =IF(PrecioDeVenta!D11>0,(UtilidadNeta!D11*100)/PrecioDeVenta!D11,0) -> 62.35656 | E11: =IF(PrecioDeVenta!E11>0,(UtilidadNeta!E11*100)/PrecioDeVenta!E11,0) -> 64.620798 | F11: =IF(PrecioDeVenta!F11>0,(UtilidadNeta!F11*100)/PrecioDeVenta!F11,0) -> 64.302364 | G11: =IF(PrecioDeVenta!G11>0,(UtilidadNeta!G11*100)/PrecioDeVenta!G11,0) -> 66.385001 | H11: =IF(PrecioDeVenta!H11>0,(UtilidadNeta!H11*100)/PrecioDeVenta!H11,0) -> 65.889658 | I11: =IF(PrecioDeVenta!I11>0,(UtilidadNeta!I11*100)/PrecioDeVenta!I11,0) -> 69.028506 | J11: =IF(PrecioDeVenta!J11>0,(UtilidadNeta!J11*100)/PrecioDeVenta!J11,0) -> 68.329199 | ... Q11: =IF(PrecioDeVenta!Q11>0,(UtilidadNeta!Q11*100)/PrecioDeVenta!Q11,0) -> 68.456277
A12: 10 | B12: Calza corta | C12: =IF(PrecioDeVenta!C12>0,(UtilidadNeta!C12*100)/PrecioDeVenta!C12,0) -> 54.761522 | D12: =IF(PrecioDeVenta!D12>0,(UtilidadNeta!D12*100)/PrecioDeVenta!D12,0) -> 52.959085 | E12: =IF(PrecioDeVenta!E12>0,(UtilidadNeta!E12*100)/PrecioDeVenta!E12,0) -> 54.645459 | F12: =IF(PrecioDeVenta!F12>0,(UtilidadNeta!F12*100)/PrecioDeVenta!F12,0) -> 52.971768 | G12: =IF(PrecioDeVenta!G12>0,(UtilidadNeta!G12*100)/PrecioDeVenta!G12,0) -> 54.544871 | H12: =IF(PrecioDeVenta!H12>0,(UtilidadNeta!H12*100)/PrecioDeVenta!H12,0) -> 49.969426 | I12: =IF(PrecioDeVenta!I12>0,(UtilidadNeta!I12*100)/PrecioDeVenta!I12,0) -> 54.477042 | J12: =IF(PrecioDeVenta!J12>0,(UtilidadNeta!J12*100)/PrecioDeVenta!J12,0) -> 53.098707 | ... Q12: =IF(PrecioDeVenta!Q12>0,(UtilidadNeta!Q12*100)/PrecioDeVenta!Q12,0) -> 49.402961
A13: 11 | B13: Calza larga | C13: =IF(PrecioDeVenta!C13>0,(UtilidadNeta!C13*100)/PrecioDeVenta!C13,0) -> 62.369335 | D13: =IF(PrecioDeVenta!D13>0,(UtilidadNeta!D13*100)/PrecioDeVenta!D13,0) -> 60.365309 | E13: =IF(PrecioDeVenta!E13>0,(UtilidadNeta!E13*100)/PrecioDeVenta!E13,0) -> 58.361284 | F13: =IF(PrecioDeVenta!F13>0,(UtilidadNeta!F13*100)/PrecioDeVenta!F13,0) -> 58.97874 | G13: =IF(PrecioDeVenta!G13>0,(UtilidadNeta!G13*100)/PrecioDeVenta!G13,0) -> 57.51426 | H13: =IF(PrecioDeVenta!H13>0,(UtilidadNeta!H13*100)/PrecioDeVenta!H13,0) -> 44.563556 | I13: =IF(PrecioDeVenta!I13>0,(UtilidadNeta!I13*100)/PrecioDeVenta!I13,0) -> 44.134952 | J13: =IF(PrecioDeVenta!J13>0,(UtilidadNeta!J13*100)/PrecioDeVenta!J13,0) -> 42.461261 | ... Q13: =IF(PrecioDeVenta!Q13>0,(UtilidadNeta!Q13*100)/PrecioDeVenta!Q13,0) -> 38.368031
A14: 12 | B14: Pantalón para dama | C14: =IF(PrecioDeVenta!C14>0,(UtilidadNeta!C14*100)/PrecioDeVenta!C14,0) -> 0 | D14: =IF(PrecioDeVenta!D14>0,(UtilidadNeta!D14*100)/PrecioDeVenta!D14,0) -> 0 | E14: =IF(PrecioDeVenta!E14>0,(UtilidadNeta!E14*100)/PrecioDeVenta!E14,0) -> 0 | F14: =IF(PrecioDeVenta!F14>0,(UtilidadNeta!F14*100)/PrecioDeVenta!F14,0) -> 0 | G14: =IF(PrecioDeVenta!G14>0,(UtilidadNeta!G14*100)/PrecioDeVenta!G14,0) -> 0 | H14: =IF(PrecioDeVenta!H14>0,(UtilidadNeta!H14*100)/PrecioDeVenta!H14,0) -> 0 | I14: =IF(PrecioDeVenta!I14>0,(UtilidadNeta!I14*100)/PrecioDeVenta!I14,0) -> 0 | J14: =IF(PrecioDeVenta!J14>0,(UtilidadNeta!J14*100)/PrecioDeVenta!J14,0) -> 56.219135 | ... Q14: =IF(PrecioDeVenta!Q14>0,(UtilidadNeta!Q14*100)/PrecioDeVenta!Q14,0) -> 60.663578
A15: 13 | B15: Blusa manga corta | C15: =IF(PrecioDeVenta!C15>0,(UtilidadNeta!C15*100)/PrecioDeVenta!C15,0) -> 37.007963 | D15: =IF(PrecioDeVenta!D15>0,(UtilidadNeta!D15*100)/PrecioDeVenta!D15,0) -> 35.807963 | E15: =IF(PrecioDeVenta!E15>0,(UtilidadNeta!E15*100)/PrecioDeVenta!E15,0) -> 38.239123 | F15: =IF(PrecioDeVenta!F15>0,(UtilidadNeta!F15*100)/PrecioDeVenta!F15,0) -> 38.807167 | G15: =IF(PrecioDeVenta!G15>0,(UtilidadNeta!G15*100)/PrecioDeVenta!G15,0) -> 40.006825 | H15: =IF(PrecioDeVenta!H15>0,(UtilidadNeta!H15*100)/PrecioDeVenta!H15,0) -> 38.506515 | I15: =IF(PrecioDeVenta!I15>0,(UtilidadNeta!I15*100)/PrecioDeVenta!I15,0) -> 40.867101 | J15: =IF(PrecioDeVenta!J15>0,(UtilidadNeta!J15*100)/PrecioDeVenta!J15,0) -> 42.580972 | ... Q15: =IF(PrecioDeVenta!Q15>0,(UtilidadNeta!Q15*100)/PrecioDeVenta!Q15,0) -> 50.623229
... A29: 27 | B29: Saco | C29: =IF(PrecioDeVenta!C29>0,(UtilidadNeta!C29*100)/PrecioDeVenta!C29,0) -> 0 | D29: =IF(PrecioDeVenta!D29>0,(UtilidadNeta!D29*100)/PrecioDeVenta!D29,0) -> 0 | E29: =IF(PrecioDeVenta!E29>0,(UtilidadNeta!E29*100)/PrecioDeVenta!E29,0) -> 0 | F29: =IF(PrecioDeVenta!F29>0,(UtilidadNeta!F29*100)/PrecioDeVenta!F29,0) -> 0 | G29: =IF(PrecioDeVenta!G29>0,(UtilidadNeta!G29*100)/PrecioDeVenta!G29,0) -> 0 | H29: =IF(PrecioDeVenta!H29>0,(UtilidadNeta!H29*100)/PrecioDeVenta!H29,0) -> 0 | I29: =IF(PrecioDeVenta!I29>0,(UtilidadNeta!I29*100)/PrecioDeVenta!I29,0) -> 0 | J29: =IF(PrecioDeVenta!J29>0,(UtilidadNeta!J29*100)/PrecioDeVenta!J29,0) -> 0 | ... Q29: =IF(PrecioDeVenta!Q29>0,(UtilidadNeta!Q29*100)/PrecioDeVenta!Q29,0) -> 0

Sheet INVENTARIO
A1: INVENTARIO AL 11/11/2022
A2: ITEM | B2: DETALLE | C2: 2 | D2: 4 | E2: 6 | F2: 8 | G2: 10 | H2: 12 | I2: 14 | J2: 16/34 | K2: 36/XS | L2: 38/S | M2: 40/M | N2: 42/L | O2: 44/XL | P2: 46/2XL | Q2: 48/3XL | R2: 50/4XL
A3: 1 | B3: Pantalón de vestir | J3: 21 | K3: 15 | L3: 18 | M3: 13 | N3: 11 | O3: 18 | P3: 16 | Q3: 12 | R3: 21
A4: 2 | B4: Camisa manga corta | C4: 80 | D4: 98 | E4: 50 | F4: 64 | G4: 76 | H4: 64 | I4: 27 | J4: 32 | L4: 12 | M4: 70 | N4: 55 | O4: 23 | P4: 37 | Q4: 71
A5: 3 | B5: Camisa manga larga | F5: 2 | H5: 4 | J5: 17
A6: 4 | B6: Corbata larga
A7: 5 | B7: Pantalón con elástico | C7: 28 | D7: 25 | E7: 23 | F7: 18 | G7: 16 | H7: 15 | I7: 23 | J7: 18 | L7: 4
A8: 6 | B8: Bermuda | C8: 28 | D8: 14 | E8: 8 | F8: 21 | G8: 15 | H8: 14 | I8: 13 | J8: 16
A9: 7 | B9: Polera manga corta | C9: 7 | E9: 1 | G9: 22 | H9: 94 | I9: 10 | J9: 2 | M9: 16 | N9: 16 | O9: 76 | P9: 20 | Q9: 35
A10: 8 | B10: Polera manga larga | C10: 15 | D10: 31 | E10: 23 | F10: 27 | G10: 21 | H10: 22 | I10: 35 | J10: 19
A11: 9 | B11: Short | C11: 24 | D11: 22 | E11: 17 | F11: 26 | G11: 15 | H11: 26 | I11: 24 | J11: 10 | L11: 15 | M11: 29 | N11: 39 | O11: 40 | P11: 7 | Q11: 8
A12: 10 | B12: Calza corta | F12: 19 | G12: 1 | H12: 11 | I12: 15
A13: 11 | B13: Calza larga | C13: 14 | D13: 19 | E13: 10 | F13: 13 | G13: 12 | H13: 9 | I13: 14 | J13: 18 | L13: 1
A14: 12 | B14: Pantalón para dama | K14: 25 | L14: 26 | M14: 8 | N14: 12 | O14: 30
A15: 13 | B15: Blusa manga corta | C15: 46 | D15: 78 | E15: 56 | F15: 47 | G15: 22 | H15: 58 | I15: 5 | J15: 46 | L15: 27 | M15: 5 | N15: 9 | O15: 38
A16: 14 | B16: Blusa manga larga
A17: 15 | B17: Corbata con elástico
A18: 16 | B18: Falda plisada | D18: 52 | E18: 84 | F18: 54 | G18: 73 | H18: 33 | I18: 12 | J18: 12 | M18: 9 | N18: 18 | P18: 16 | Q18: 15
A19: 17 | B19: Jamper | D19: 31 | E19: 35 | F19: 62 | G19: 14 | H19: 11
A20: 18 | B20: Vestido | D20: 8 | E20: 24 | F20: 49
A21: 19 | B21: Chompa cuello en V | D21: 73 | E21: 59 | F21: 51 | G21: 68 | H21: 20 | I21: 28 | K21: 1 | L21: 17 | M21: 25 | N21: 1
A22: 20 | B22: Chaleco cuello en V | D22: 35 | E22: 6 | F22: 13 | G22: 15 | H22: 21 | I22: 18 | L22: 9 | N22: 14 | O22: 6
A23: 21 | B23: Chamarra de verano | C23: 44 | D23: 2 | E23: 2 | F23: 5 | G23: 61 | H23: 59 | J23: 69 | L23: 53 | M23: 95 | N23: 82 | O23: 32
A24: 22 | B24: Chamarra deportiva | C24: 23 | D24: 49 | E24: 26 | F24: 16 | G24: 29 | H24: 43 | I24: 49 | J24: 18 | L24: 10 | M24: 67 | N24: 83 | O24: 42 | P24: 32 | Q24: 7
A25: 23 | B25: Chamarra de invierno | C25: 35 | D25: 12 | E25: 74 | F25: 17 | G25: 32 | H25: 27 | I25: 104 | J25: 61 | L25: 19 | M25: 23 | N25: 15 | O25: 44
A26: 24 | B26: Buso Deportivo | C26: 9 | D26: 18 | F26: 16 | G26: 32 | H26: 33 | I26: 19 | J26: 62 | L26: 146 | M26: 39 | N26: 48 | O26: 24 | P26: 4
A27: 25 | B27: Polera de colores
A28: 26 | B28: Polera Bullying | D28: 42 | E28: 42 | F28: 42 | G28: 60 | H28: 43 | I28: 40 | J28: 40
A29: 27 | B29: Saco

Sheet CostoInventario
A1: COSTO INVENTARIO
A2: ITEM | B2: DETALLE | C2: 2 | D2: 4 | E2: 6 | F2: 8 | G2: 10 | H2: 12 | I2: 14 | J2: 16/34 | K2: 36/XS | L2: 38/S | M2: 40/M | N2: 42/L | O2: 44/XL | P2: 46/2XL | Q2: 48/3XL | R2: 50/4XL
A3: 1 | B3: Pantalón de vestir | C3: =IF(CostoTotal!C3>0,CostoTotal!C3*INVENTARIO!C3,0) -> 0 | D3: =IF(CostoTotal!D3>0,CostoTotal!D3*INVENTARIO!D3,0) -> 0 | E3: =IF(CostoTotal!E3>0,CostoTotal!E3*INVENTARIO!E3,0) -> 0 | F3: =IF(CostoTotal!F3>0,CostoTotal!F3*INVENTARIO!F3,0) -> 0 | G3: =IF(CostoTotal!G3>0,CostoTotal!G3*INVENTARIO!G3,0) -> 0 | H3: =IF(CostoTotal!H3>0,CostoTotal!H3*INVENTARIO!H3,0) -> 0 | I3: =IF(CostoTotal!I3>0,CostoTotal!I3*INVENTARIO!I3,0) -> 0 | J3: =IF(CostoTotal!J3>0,CostoTotal!J3*INVENTARIO!J3,0) -> 2531.009 | ... R3: =IF(CostoTotal!R3>0,CostoTotal!R3*INVENTARIO!R3,0) -> 2985.1202 | S3: =SUM(C3:R3) -> 19252.574
A4: 2 | B4: Camisa manga corta | C4: =IF(CostoTotal!C4>0,CostoTotal!C4*INVENTARIO!C4,0) -> 4996.2267 | D4: =IF(CostoTotal!D4>0,CostoTotal!D4*INVENTARIO!D4,0) -> 6243.8577 | E4: =IF(CostoTotal!E4>0,CostoTotal!E4*INVENTARIO!E4,0) -> 3248.6417 | F4: =IF(CostoTotal!F4>0,CostoTotal!F4*INVENTARIO!F4,0) -> 4238.9013 | G4: =IF(CostoTotal!G4>0,CostoTotal!G4*INVENTARIO!G4,0) -> 5129.4553 | H4: =IF(CostoTotal!H4>0,CostoTotal!H4*INVENTARIO!H4,0) -> 4617.1413 | I4: =IF(CostoTotal!I4>0,CostoTotal!I4*INVENTARIO!I4,0) -> 1981.8765 | J4: =IF(CostoTotal!J4>0,CostoTotal!J4*INVENTARIO!J4,0) -> 2389.2107 | ... Q4: =IF(CostoTotal!Q4>0,CostoTotal!Q4*INVENTARIO!Q4,0) -> 6197.0812 | S4: =SUM(C4:R4) -> 55348.93
A5: 3 | B5: Camisa manga larga | C5: =IF(CostoTotal!C5>0,CostoTotal!C5*INVENTARIO!C5,0) -> 0 | D5: =IF(CostoTotal!D5>0,CostoTotal!D5*INVENTARIO!D5,0) -> 0 | E5: =IF(CostoTotal!E5>0,CostoTotal!E5*INVENTARIO!E5,0) -> 0 | F5: =IF(CostoTotal!F5>0,CostoTotal!F5*INVENTARIO!F5,0) -> 144.26193 | G5: =IF(CostoTotal!G5>0,CostoTotal!G5*INVENTARIO!G5,0) -> 0 | H5: =IF(CostoTotal!H5>0,CostoTotal!H5*INVENTARIO!H5,0) -> 312.16387 | I5: =IF(CostoTotal!I5>0,CostoTotal!I5*INVENTARIO!I5,0) -> 0 | J5: =IF(CostoTotal!J5>0,CostoTotal!J5*INVENTARIO!J5,0) -> 1369.5364 | ... Q5: =IF(CostoTotal!Q5>0,CostoTotal!Q5*INVENTARIO!Q5,0) -> 0 | S5: =SUM(C5:R5) -> 1825.9622
A6: 4 | B6: Corbata larga | C6: =IF(CostoTotal!C6>0,CostoTotal!C6*INVENTARIO!C6,0) -> 0 | D6: =IF(CostoTotal!D6>0,CostoTotal!D6*INVENTARIO!D6,0) -> 0 | E6: =IF(CostoTotal!E6>0,CostoTotal!E6*INVENTARIO!E6,0) -> 0 | F6: =IF(CostoTotal!F6>0,CostoTotal!F6*INVENTARIO!F6,0) -> 0 | G6: =IF(CostoTotal!G6>0,CostoTotal!G6*INVENTARIO!G6,0) -> 0 | H6: =IF(CostoTotal!H6>0,CostoTotal!H6*INVENTARIO!H6,0) -> 0 | I6: =IF(CostoTotal!I6>0,CostoTotal!I6*INVENTARIO!I6,0) -> 0 | J6: =IF(CostoTotal!J6>0,CostoTotal!J6*INVENTARIO!J6,0) -> 0 | ... Q6: =IF(CostoTotal!Q6>0,CostoTotal!Q6*INVENTARIO!Q6,0) -> 0 | S6: =SUM(C6:R6) -> 0
A7: 5 | B7: Pantalón con elástico | C7: =IF(CostoTotal!C7>0,CostoTotal!C7*INVENTARIO!C7,0) -> 1611.2181 | D7: =IF(CostoTotal!D7>0,CostoTotal!D7*INVENTARIO!D7,0) -> 1511.514 | E7: =IF(CostoTotal!E7>0,CostoTotal!E7*INVENTARIO!E7,0) -> 1457.6851 | F7: =IF(CostoTotal!F7>0,CostoTotal!F7*INVENTARIO!F7,0) -> 1195.8043 | G7: =IF(CostoTotal!G7>0,CostoTotal!G7*INVENTARIO!G7,0) -> 1109.61 | H7: =IF(CostoTotal!H7>0,CostoTotal!H7*INVENTARIO!H7,0) -> 1128.6144 | I7: =IF(CostoTotal!I7>0,CostoTotal!I7*INVENTARIO!I7,0) -> 1788.0497 | J7: =IF(CostoTotal!J7>0,CostoTotal!J7*INVENTARIO!J7,0) -> 1444.3492 | ... Q7: =IF(CostoTotal!Q7>0,CostoTotal!Q7*INVENTARIO!Q7,0) -> 0 | S7: =SUM(C7:R7) -> 11594.781
A8: 6 | B8: Bermuda | C8: =IF(CostoTotal!C8>0,CostoTotal!C8*INVENTARIO!C8,0) -> 1418.0816 | D8: =IF(CostoTotal!D8>0,CostoTotal!D8*INVENTARIO!D8,0) -> 724.59844 | E8: =IF(CostoTotal!E8>0,CostoTotal!E8*INVENTARIO!E8,0) -> 426.2801 | F8: =IF(CostoTotal!F8>0,CostoTotal!F8*INVENTARIO!F8,0) -> 1156.907 | G8: =IF(CostoTotal!G8>0,CostoTotal!G8*INVENTARIO!G8,0) -> 863.86709 | H8: =IF(CostoTotal!H8>0,CostoTotal!H8*INVENTARIO!H8,0) -> 886.79589 | I8: =IF(CostoTotal!I8>0,CostoTotal!I8*INVENTARIO!I8,0) -> 834.2881 | J8: =IF(CostoTotal!J8>0,CostoTotal!J8*INVENTARIO!J8,0) -> 1055.7088 | ... Q8: =IF(CostoTotal!Q8>0,CostoTotal!Q8*INVENTARIO!Q8,0) -> 0 | S8: =SUM(C8:R8) -> 7366.5271
A9: 7 | B9: Polera manga corta | C9: =IF(CostoTotal!C9>0,CostoTotal!C9*INVENTARIO!C9,0) -> 320.79807 | D9: =IF(CostoTotal!D9>0,CostoTotal!D9*INVENTARIO!D9,0) -> 0 | E9: =IF(CostoTotal!E9>0,CostoTotal!E9*INVENTARIO!E9,0) -> 47.485598 | F9: =IF(CostoTotal!F9>0,CostoTotal!F9*INVENTARIO!F9,0) -> 0 | G9: =IF(CostoTotal!G9>0,CostoTotal!G9*INVENTARIO!G9,0) -> 1128.0218 | H9: =IF(CostoTotal!H9>0,CostoTotal!H9*INVENTARIO!H9,0) -> 4875.3677 | I9: =IF(CostoTotal!I9>0,CostoTotal!I9*INVENTARIO!I9,0) -> 524.57508 | J9: =IF(CostoTotal!J9>0,CostoTotal!J9*INVENTARIO!J9,0) -> 106.57232 | ... Q9: =IF(CostoTotal!Q9>0,CostoTotal!Q9*INVENTARIO!Q9,0) -> 2105.3245 | S9: =SUM(C9:R9) -> 16357.305
A10: 8 | B10: Polera manga larga | C10: =IF(CostoTotal!C10>0,CostoTotal!C10*INVENTARIO!C10,0) -> 732.64816 | D10: =IF(CostoTotal!D10>0,CostoTotal!D10*INVENTARIO!D10,0) -> 1539.8277 | E10: =IF(CostoTotal!E10>0,CostoTotal!E10*INVENTARIO!E10,0) -> 1161.5118 | F10: =IF(CostoTotal!F10>0,CostoTotal!F10*INVENTARIO!F10,0) -> 1414.6535 | G10: =IF(CostoTotal!G10>0,CostoTotal!G10*INVENTARIO!G10,0) -> 1164.9209 | H10: =IF(CostoTotal!H10>0,CostoTotal!H10*INVENTARIO!H10,0) -> 1233.415 | I10: =IF(CostoTotal!I10>0,CostoTotal!I10*INVENTARIO!I10,0) -> 1982.9674 | J10: =IF(CostoTotal!J10>0,CostoTotal!J10*INVENTARIO!J10,0) -> 1092.2124 | ... Q10: =IF(CostoTotal!Q10>0,CostoTotal!Q10*INVENTARIO!Q10,0) -> 0 | S10: =SUM(C10:R10) -> 10322.157
A11: 9 | B11: Short | C11: =IF(CostoTotal!C11>0,CostoTotal!C11*INVENTARIO!C11,0) -> 580.10473 | D11: =IF(CostoTotal!D11>0,CostoTotal!D11*INVENTARIO!D11,0) -> 538.30119 | E11: =IF(CostoTotal!E11>0,CostoTotal!E11*INVENTARIO!E11,0) -> 421.0125 | F11: =IF(CostoTotal!F11>0,CostoTotal!F11*INVENTARIO!F11,0) -> 649.69698 | G11: =IF(CostoTotal!G11>0,CostoTotal!G11*INVENTARIO!G11,0) -> 378.16874 | H11: =IF(CostoTotal!H11>0,CostoTotal!H11*INVENTARIO!H11,0) -> 665.15166 | I11: =IF(CostoTotal!I11>0,CostoTotal!I11*INVENTARIO!I11,0) -> 631.81848 | J11: =IF(CostoTotal!J11>0,CostoTotal!J11*INVENTARIO!J11,0) -> 269.20181 | ... Q11: =IF(CostoTotal!Q11>0,CostoTotal!Q11*INVENTARIO!Q11,0) -> 239.7323 | S11: =SUM(C11:R11) -> 8052.1754
A12: 10 | B12: Calza corta | C12: =IF(CostoTotal!C12>0,CostoTotal!C12*INVENTARIO!C12,0) -> 0 | D12: =IF(CostoTotal!D12>0,CostoTotal!D12*INVENTARIO!D12,0) -> 0 | E12: =IF(CostoTotal!E12>0,CostoTotal!E12*INVENTARIO!E12,0) -> 0 | F12: =IF(CostoTotal!F12>0,CostoTotal!F12*INVENTARIO!F12,0) -> 625.47549 | G12: =IF(CostoTotal!G12>0,CostoTotal!G12*INVENTARIO!G12,0) -> 34.091347 | H12: =IF(CostoTotal!H12>0,CostoTotal!H12*INVENTARIO!H12,0) -> 412.75224 | I12: =IF(CostoTotal!I12>0,CostoTotal!I12*INVENTARIO!I12,0) -> 580.41772 | J12: =IF(CostoTotal!J12>0,CostoTotal!J12*INVENTARIO!J12,0) -> 0 | ... Q12: =IF(CostoTotal!Q12>0,CostoTotal!Q12*INVENTARIO!Q12,0) -> 0 | S12: =SUM(C12:R12) -> 1652.7368
A13: 11 | B13: Calza larga | C13: =IF(CostoTotal!C13>0,CostoTotal!C13*INVENTARIO!C13,0) -> 500.48785 | D13: =IF(CostoTotal!D13>0,CostoTotal!D13*INVENTARIO!D13,0) -> 715.40616 | E13: =IF(CostoTotal!E13>0,CostoTotal!E13*INVENTARIO!E13,0) -> 395.5678 | F13: =IF(CostoTotal!F13>0,CostoTotal!F13*INVENTARIO!F13,0) -> 533.27638 | G13: =IF(CostoTotal!G13>0,CostoTotal!G13*INVENTARIO!G13,0) -> 509.82888 | H13: =IF(CostoTotal!H13>0,CostoTotal!H13*INVENTARIO!H13,0) -> 498.928 | I13: =IF(CostoTotal!I13>0,CostoTotal!I13*INVENTARIO!I13,0) -> 821.2162 | J13: =IF(CostoTotal!J13>0,CostoTotal!J13*INVENTARIO!J13,0) -> 1087.4822 | ... Q13: =IF(CostoTotal!Q13>0,CostoTotal!Q13*INVENTARIO!Q13,0) -> 0 | S13: =SUM(C13:R13) -> 5124.6594
A14: 12 | B14: Pantalón para dama | C14: =IF(CostoTotal!C14>0,CostoTotal!C14*INVENTARIO!C14,0) -> 0 | D14: =IF(CostoTotal!D14>0,CostoTotal!D14*INVENTARIO!D14,0) -> 0 | E14: =IF(CostoTotal!E14>0,CostoTotal!E14*INVENTARIO!E14,0) -> 0 | F14: =IF(CostoTotal!F14>0,CostoTotal!F14*INVENTARIO!F14,0) -> 0 | G14: =IF(CostoTotal!G14>0,CostoTotal!G14*INVENTARIO!G14,0) -> 0 | H14: =IF(CostoTotal!H14>0,CostoTotal!H14*INVENTARIO!H14,0) -> 0 | I14: =IF(CostoTotal!I14>0,CostoTotal!I14*INVENTARIO!I14,0) -> 0 | J14: =IF(CostoTotal!J14>0,CostoTotal!J14*INVENTARIO!J14,0) -> 0 | ... Q14: =IF(CostoTotal!Q14>0,CostoTotal!Q14*INVENTARIO!Q14,0) -> 0 | S14: =SUM(C14:R14) -> 8576.5265
A15: 13 | B15: Blusa manga corta | C15: =IF(CostoTotal!C15>0,CostoTotal!C15*INVENTARIO!C15,0) -> 2607.8703 | D15: =IF(CostoTotal!D15>0,CostoTotal!D15*INVENTARIO!D15,0) -> 4506.281 | E15: =IF(CostoTotal!E15>0,CostoTotal!E15*INVENTARIO!E15,0) -> 3285.6787 | F15: =IF(CostoTotal!F15>0,CostoTotal!F15*INVENTARIO!F15,0) -> 2876.0632 | G15: =IF(CostoTotal!G15>0,CostoTotal!G15*INVENTARIO!G15,0) -> 1385.8423 | H15: =IF(CostoTotal!H15>0,CostoTotal!H15*INVENTARIO!H15,0) -> 3923.2843 | I15: =IF(CostoTotal!I15>0,CostoTotal!I15*INVENTARIO!I15,0) -> 340.01417 | J15: =IF(CostoTotal!J15>0,CostoTotal!J15*INVENTARIO!J15,0) -> 3169.5303 | ... Q15: =IF(CostoTotal!Q15>0,CostoTotal!Q15*INVENTARIO!Q15,0) -> 0 | S15: =SUM(C15:R15) -> 28108.448
A16: 14 | B16: Blusa manga larga | C16: =IF(CostoTotal!C16>0,CostoTotal!C16*INVENTARIO!C16,0) -> 0 | D16: =IF(CostoTotal!D16>0,CostoTotal!D16*INVENTARIO!D16,0) -> 0 | E16: =IF(CostoTotal!E16>0,CostoTotal!E16*INVENTARIO!E16,0) -> 0 | F16: =IF(CostoTotal!F16>0,CostoTotal!F16*INVENTARIO!F16,0) -> 0 | G16: =IF(CostoTotal!G16>0,CostoTotal!G16*INVENTARIO!G16,0) -> 0 | H16: =IF(CostoTotal!H16>0,CostoTotal!H16*INVENTARIO!H16,0) -> 0 | I16: =IF(CostoTotal!I16>0,CostoTotal!I16*INVENTARIO!I16,0) -> 0 | J16: =IF(CostoTotal!J16>0,CostoTotal!J16*INVENTARIO!J16,0) -> 0 | ... R16: =IF(CostoTotal!R16>0,CostoTotal!R16*INVENTARIO!R16,0) -> 0 | S16: =SUM(C16:R16) -> 0
A17: 15 | B17: Corbata con elástico | C17: =IF(CostoTotal!C17>0,CostoTotal!C17*INVENTARIO!C17,0) -> 0 | D17: =IF(CostoTotal!D17>0,CostoTotal!D17*INVENTARIO!D17,0) -> 0 | E17: =IF(CostoTotal!E17>0,CostoTotal!E17*INVENTARIO!E17,0) -> 0 | F17: =IF(CostoTotal!F17>0,CostoTotal!F17*INVENTARIO!F17,0) -> 0 | G17: =IF(CostoTotal!G17>0,CostoTotal!G17*INVENTARIO!G17,0) -> 0 | H17: =IF(CostoTotal!H17>0,CostoTotal!H17*INVENTARIO!H17,0) -> 0 | I17: =IF(CostoTotal!I17>0,CostoTotal!I17*INVENTARIO!I17,0) -> 0 | J17: =IF(CostoTotal!J17>0,CostoTotal!J17*INVENTARIO!J17,0) -> 0 | ... Q17: =IF(CostoTotal!Q17>0,CostoTotal!Q17*INVENTARIO!Q17,0) -> 0 | S17: =SUM(C17:R17) -> 0
A18: 16 | B18: Falda plisada | C18: =IF(CostoTotal!C18>0,CostoTotal!C18*INVENTARIO!C18,0) -> 0 | D18: =IF(CostoTotal!D18>0,CostoTotal!D18*INVENTARIO!D18,0) -> 4127.9015 | E18: =IF(CostoTotal!E18>0,CostoTotal!E18*INVENTARIO!E18,0) -> 6828.9543 | F18: =IF(CostoTotal!F18>0,CostoTotal!F18*INVENTARIO!F18,0) -> 4493.4171 | G18: =IF(CostoTotal!G18>0,CostoTotal!G18*INVENTARIO!G18,0) -> 6214.182 | H18: =IF(CostoTotal!H18>0,CostoTotal!H18*INVENTARIO!H18,0) -> 2872.3244 | I18: =IF(CostoTotal!I18>0,CostoTotal!I18*INVENTARIO!I18,0) -> 1070.3254 | J18: =IF(CostoTotal!J18>0,CostoTotal!J18*INVENTARIO!J18,0) -> 1093.2976 | ... Q18: =IF(CostoTotal!Q18>0,CostoTotal!Q18*INVENTARIO!Q18,0) -> 1538.9138 | S18: =SUM(C18:R18) -> 32447.947
A19: 17 | B19: Jamper | C19: =IF(CostoTotal!C19>0,CostoTotal!C19*INVENTARIO!C19,0) -> 0 | D19: =IF(CostoTotal!D19>0,CostoTotal!D19*INVENTARIO!D19,0) -> 1999.3476 | E19: =IF(CostoTotal!E19>0,CostoTotal!E19*INVENTARIO!E19,0) -> 2357.8314 | F19: =IF(CostoTotal!F19>0,CostoTotal!F19*INVENTARIO!F19,0) -> 4354.7648 | G19: =IF(CostoTotal!G19>0,CostoTotal!G19*INVENTARIO!G19,0) -> 1023.5354 | H19: =IF(CostoTotal!H19>0,CostoTotal!H19*INVENTARIO!H19,0) -> 835.7932 | I19: =IF(CostoTotal!I19>0,CostoTotal!I19*INVENTARIO!I19,0) -> 0 | J19: =IF(CostoTotal!J19>0,CostoTotal!J19*INVENTARIO!J19,0) -> 0 | ... Q19: =IF(CostoTotal!Q19>0,CostoTotal!Q19*INVENTARIO!Q19,0) -> 0 | S19: =SUM(C19:R19) -> 10571.272
A20: 18 | B20: Vestido | C20: =IF(CostoTotal!C20>0,CostoTotal!C20*INVENTARIO!C20,0) -> 0 | D20: =IF(CostoTotal!D20>0,CostoTotal!D20*INVENTARIO!D20,0) -> 635.82042 | E20: =IF(CostoTotal!E20>0,CostoTotal!E20*INVENTARIO!E20,0) -> 2016.5794 | F20: =IF(CostoTotal!F20>0,CostoTotal!F20*INVENTARIO!F20,0) -> 4339.9657 | G20: =IF(CostoTotal!G20>0,CostoTotal!G20*INVENTARIO!G20,0) -> 0 | H20: =IF(CostoTotal!H20>0,CostoTotal!H20*INVENTARIO!H20,0) -> 0 | I20: =IF(CostoTotal!I20>0,CostoTotal!I20*INVENTARIO!I20,0) -> 0 | J20: =IF(CostoTotal!J20>0,CostoTotal!J20*INVENTARIO!J20,0) -> 0 | ... Q20: =IF(CostoTotal!Q20>0,CostoTotal!Q20*INVENTARIO!Q20,0) -> 0 | S20: =SUM(C20:R20) -> 6992.3656
A21: 19 | B21: Chompa cuello en V | C21: =IF(CostoTotal!C21>0,CostoTotal!C21*INVENTARIO!C21,0) -> 0 | D21: =IF(CostoTotal!D21>0,CostoTotal!D21*INVENTARIO!D21,0) -> 4869.6597 | E21: =IF(CostoTotal!E21>0,CostoTotal!E21*INVENTARIO!E21,0) -> 4269.1023 | F21: =IF(CostoTotal!F21>0,CostoTotal!F21*INVENTARIO!F21,0) -> 3978.391 | G21: =IF(CostoTotal!G21>0,CostoTotal!G21*INVENTARIO!G21,0) -> 5688.7213 | H21: =IF(CostoTotal!H21>0,CostoTotal!H21*INVENTARIO!H21,0) -> 1786.1533 | I21: =IF(CostoTotal!I21>0,CostoTotal!I21*INVENTARIO!I21,0) -> 2658.8147 | J21: =IF(CostoTotal!J21>0,CostoTotal!J21*INVENTARIO!J21,0) -> 0 | ... Q21: =IF(CostoTotal!Q21>0,CostoTotal!Q21*INVENTARIO!Q21,0) -> 0 | S21: =SUM(C21:R21) -> 28367.972
A22: 20 | B22: Chaleco cuello en V | C22: =IF(CostoTotal!C22>0,CostoTotal!C22*INVENTARIO!C22,0) -> 0 | D22: =IF(CostoTotal!D22>0,CostoTotal!D22*INVENTARIO!D22,0) -> 2137.0183 | E22: =IF(CostoTotal!E22>0,CostoTotal!E22*INVENTARIO!E22,0) -> 400.246 | F22: =IF(CostoTotal!F22>0,CostoTotal!F22*INVENTARIO!F22,0) -> 940.64967 | G22: =IF(CostoTotal!G22>0,CostoTotal!G22*INVENTARIO!G22,0) -> 1170.115 | H22: =IF(CostoTotal!H22>0,CostoTotal!H22*INVENTARIO!H22,0) -> 1756.811 | I22: =IF(CostoTotal!I22>0,CostoTotal!I22*INVENTARIO!I22,0) -> 1607.538 | J22: =IF(CostoTotal!J22>0,CostoTotal!J22*INVENTARIO!J22,0) -> 0 | ... Q22: =IF(CostoTotal!Q22>0,CostoTotal!Q22*INVENTARIO!Q22,0) -> 0 | S22: =SUM(C22:R22) -> 11613.65
A23: 21 | B23: Chamarra de verano | C23: =IF(CostoTotal!C23>0,CostoTotal!C23*INVENTARIO!C23,0) -> 6188.5512 | D23: =IF(CostoTotal!D23>0,CostoTotal!D23*INVENTARIO!D23,0) -> 285.61828 | E23: =IF(CostoTotal!E23>0,CostoTotal!E23*INVENTARIO!E23,0) -> 289.93878 | F23: =IF(CostoTotal!F23>0,CostoTotal!F23*INVENTARIO!F23,0) -> 735.64818 | G23: =IF(CostoTotal!G23>0,CostoTotal!G23*INVENTARIO!G23,0) -> 9106.683 | H23: =IF(CostoTotal!H23>0,CostoTotal!H23*INVENTARIO!H23,0) -> 9268.9079 | I23: =IF(CostoTotal!I23>0,CostoTotal!I23*INVENTARIO!I23,0) -> 0 | J23: =IF(CostoTotal!J23>0,CostoTotal!J23*INVENTARIO!J23,0) -> 11138.023 | ... Q23: =IF(CostoTotal!Q23>0,CostoTotal!Q23*INVENTARIO!Q23,0) -> 0 | S23: =SUM(C23:R23) -> 81615.45
A24: 22 | B24: Chamarra deportiva | C24: =IF(CostoTotal!C24>0,CostoTotal!C24*INVENTARIO!C24,0) -> 3241.1275 | D24: =IF(CostoTotal!D24>0,CostoTotal!D24*INVENTARIO!D24,0) -> 7010.8628 | E24: =IF(CostoTotal!E24>0,CostoTotal!E24*INVENTARIO!E24,0) -> 3776.2161 | F24: =IF(CostoTotal!F24>0,CostoTotal!F24*INVENTARIO!F24,0) -> 2358.3893 | G24: =IF(CostoTotal!G24>0,CostoTotal!G24*INVENTARIO!G24,0) -> 4337.2278 | H24: =IF(CostoTotal!H24>0,CostoTotal!H24*INVENTARIO!H24,0) -> 6766.9025 | I24: =IF(CostoTotal!I24>0,CostoTotal!I24*INVENTARIO!I24,0) -> 7816.9737 | J24: =IF(CostoTotal!J24>0,CostoTotal!J24*INVENTARIO!J24,0) -> 2910.4258 | ... R24: =IF(CostoTotal!R24>0,CostoTotal!R24*INVENTARIO!R24,0) -> 0 | S24: =SUM(C24:R24) -> 79889.11
A25: 23 | B25: Chamarra de invierno | C25: =IF(CostoTotal!C25>0,CostoTotal!C25*INVENTARIO!C25,0) -> 5226.8034 | D25: =IF(CostoTotal!D25>0,CostoTotal!D25*INVENTARIO!D25,0) -> 1820.5622 | E25: =IF(CostoTotal!E25>0,CostoTotal!E25*INVENTARIO!E25,0) -> 11402.644 | F25: =IF(CostoTotal!F25>0,CostoTotal!F25*INVENTARIO!F25,0) -> 2659.923 | G25: =IF(CostoTotal!G25>0,CostoTotal!G25*INVENTARIO!G25,0) -> 5082.9547 | H25: =IF(CostoTotal!H25>0,CostoTotal!H25*INVENTARIO!H25,0) -> 4505.4524 | I25: =IF(CostoTotal!I25>0,CostoTotal!I25*INVENTARIO!I25,0) -> 17601.467 | J25: =IF(CostoTotal!J25>0,CostoTotal!J25*INVENTARIO!J25,0) -> 10468.89 | ... Q25: =IF(CostoTotal!Q25>0,CostoTotal!Q25*INVENTARIO!Q25,0) -> 0 | S25: =SUM(C25:R25) -> 77137.768
A26: 24 | B26: Buso Deportivo | C26: =IF(CostoTotal!C26>0,CostoTotal!C26*INVENTARIO!C26,0) -> 705.34584 | D26: =IF(CostoTotal!D26>0,CostoTotal!D26*INVENTARIO!D26,0) -> 1488.4606 | E26: =IF(CostoTotal!E26>0,CostoTotal!E26*INVENTARIO!E26,0) -> 0 | F26: =IF(CostoTotal!F26>0,CostoTotal!F26*INVENTARIO!F26,0) -> 1461.332 | G26: =IF(CostoTotal!G26>0,CostoTotal!G26*INVENTARIO!G26,0) -> 3060.9199 | H26: =IF(CostoTotal!H26>0,CostoTotal!H26*INVENTARIO!H26,0) -> 3373.73 | I26: =IF(CostoTotal!I26>0,CostoTotal!I26*INVENTARIO!I26,0) -> 2032.0027 | J26: =IF(CostoTotal!J26>0,CostoTotal!J26*INVENTARIO!J26,0) -> 6935.1444 | ... Q26: =IF(CostoTotal!Q26>0,CostoTotal!Q26*INVENTARIO!Q26,0) -> 0 | S26: =SUM(C26:R26) -> 50057.901
A27: 25 | B27: Polera de colores | C27: =IF(CostoTotal!C27>0,CostoTotal!C27*INVENTARIO!C27,0) -> 0 | D27: =IF(CostoTotal!D27>0,CostoTotal!D27*INVENTARIO!D27,0) -> 0 | E27: =IF(CostoTotal!E27>0,CostoTotal!E27*INVENTARIO!E27,0) -> 0 | F27: =IF(CostoTotal!F27>0,CostoTotal!F27*INVENTARIO!F27,0) -> 0 | G27: =IF(CostoTotal!G27>0,CostoTotal!G27*INVENTARIO!G27,0) -> 0 | H27: =IF(CostoTotal!H27>0,CostoTotal!H27*INVENTARIO!H27,0) -> 0 | I27: =IF(CostoTotal!I27>0,CostoTotal!I27*INVENTARIO!I27,0) -> 0 | J27: =IF(CostoTotal!J27>0,CostoTotal!J27*INVENTARIO!J27,0) -> 0 | ... Q27: =IF(CostoTotal!Q27>0,CostoTotal!Q27*INVENTARIO!Q27,0) -> 0 | S27: =SUM(C27:R27) -> 0
A28: 26 | B28: Polera Bullying | C28: =IF(CostoTotal!C28>0,CostoTotal!C28*INVENTARIO!C28,0) -> 0 | D28: =IF(CostoTotal!D28>0,CostoTotal!D28*INVENTARIO!D28,0) -> 0 | E28: =IF(CostoTotal!E28>0,CostoTotal!E28*INVENTARIO!E28,0) -> 0 | F28: =IF(CostoTotal!F28>0,CostoTotal!F28*INVENTARIO!F28,0) -> 0 | G28: =IF(CostoTotal!G28>0,CostoTotal!G28*INVENTARIO!G28,0) -> 0 | H28: =IF(CostoTotal!H28>0,CostoTotal!H28*INVENTARIO!H28,0) -> 0 | I28: =IF(CostoTotal!I28>0,CostoTotal!I28*INVENTARIO!I28,0) -> 0 | J28: =IF(CostoTotal!J28>0,CostoTotal!J28*INVENTARIO!J28,0) -> 0 | ... Q28: =IF(CostoTotal!Q28>0,CostoTotal!Q28*INVENTARIO!Q28,0) -> 0 | S28: =SUM(C28:R28) -> 0
A29: 27 | B29: Saco | C29: =IF(CostoTotal!C29>0,CostoTotal!C29*INVENTARIO!C29,0) -> 0 | D29: =IF(CostoTotal!D29>0,CostoTotal!D29*INVENTARIO!D29,0) -> 0 | E29: =IF(CostoTotal!E29>0,CostoTotal!E29*INVENTARIO!E29,0) -> 0 | F29: =IF(CostoTotal!F29>0,CostoTotal!F29*INVENTARIO!F29,0) -> 0 | G29: =IF(CostoTotal!G29>0,CostoTotal!G29*INVENTARIO!G29,0) -> 0 | H29: =IF(CostoTotal!H29>0,CostoTotal!H29*INVENTARIO!H29,0) -> 0 | I29: =IF(CostoTotal!I29>0,CostoTotal!I29*INVENTARIO!I29,0) -> 0 | J29: =IF(CostoTotal!J29>0,CostoTotal!J29*INVENTARIO!J29,0) -> 0 | ... Q29: =IF(CostoTotal!Q29>0,CostoTotal!Q29*INVENTARIO!Q29,0) -> 0 | S29: =SUM(C29:R29) -> 0
S31: =SUM(S3:S30) -> 552276.22

Sheet PrecioAntiguos
A2: PRECIO DE VENTA
A3: ITEM | B3: DETALLE | C3: 2 | D3: 4 | E3: 6 | F3: 8 | G3: 10 | H3: 12 | I3: 14 | J3: 16/34 | K3: 36/XS | L3: 38/S | M3: 40/M | N3: 42/L | O3: 44/XL | P3: 46/2XL | Q3: 48/3XL | R3: 50/4XL
A4: 1 | B4: Pantalón de vestir | C4: 0 | D4: 0 | E4: 0 | F4: 0 | G4: 0 | H4: 0 | I4: 0 | J4: 170 | K4: 180 | L4: 180 | M4: 190 | N4: 200 | O4: 200 | P4: 220 | Q4: 230 | R4: 230
A5: 2 | B5: Camisa manga corta | C5: 85 | D5: 85 | E5: 90 | F5: 95 | G5: 100 | H5: 105 | I5: 110 | J5: 115 | K5: 0 | L5: 125 | M5: 125 | N5: 130 | O5: 135 | P5: 140 | Q5: 150 | R5: 0
A6: 3 | B6: Camisa manga larga | C6: 95 | D6: 95 | E6: 100 | F6: 105 | G6: 110 | H6: 115 | I6: 125 | J6: 130 | K6: 0 | L6: 135 | M6: 135 | N6: 140 | O6: 145 | P6: 150 | Q6: 160 | R6: 0
A7: 4 | B7: Corbata larga | C7: 0 | D7: 0 | E7: 0 | F7: 0 | G7: 0 | H7: 0 | I7: 0 | J7: 0 | K7: 45 | L7: 0 | M7: 0 | N7: 0 | O7: 0 | P7: 0 | Q7: 0 | R7: 0
A8: 5 | B8: Pantalón con elástico | C8: 95 | D8: 95 | E8: 100 | F8: 105 | G8: 110 | H8: 115 | I8: 150 | J8: 170 | K8: 0 | L8: 170 | M8: 0 | N8: 0 | O8: 0 | P8: 0 | Q8: 0 | R8: 0
A9: 6 | B9: Bermuda | C9: 90 | D9: 90 | E9: 95 | F9: 100 | G9: 105 | H9: 110 | I9: 145 | J9: 165 | K9: 0 | L9: 165 | M9: 0 | N9: 0 | O9: 0 | P9: 0 | Q9: 0 | R9: 0
A10: 7 | B10: Polera manga corta | C10: 65 | D10: 65 | E10: 65 | F10: 75 | G10: 75 | H10: 75 | I10: 85 | J10: 85 | K10: 0 | L10: 95 | M10: 95 | N10: 95 | O10: 100 | P10: 100 | Q10: 100 | R10: 0
A11: 8 | B11: Polera manga larga | C11: 75 | D11: 75 | E11: 75 | F11: 85 | G11: 85 | H11: 85 | I11: 95 | J11: 95 | K11: 0 | L11: 100 | M11: 100 | N11: 100 | O11: 110 | P11: 110 | Q11: 110 | R11: 0
A12: 9 | B12: Short | C12: 60 | D12: 60 | E12: 65 | F12: 65 | G12: 70 | H12: 70 | I12: 80 | J12: 80 | K12: 0 | L12: 85 | M12: 85 | N12: 85 | O12: 90 | P12: 90 | Q12: 90 | R12: 0
A13: 10 | B13: Calza corta | C13: 60 | D13: 60 | E13: 65 | F13: 65 | G13: 70 | H13: 70 | I13: 80 | J13: 80 | K13: 0 | L13: 85 | M13: 85 | N13: 85 | O13: 90 | P13: 90 | Q13: 90 | R13: 0
A14: 11 | B14: Calza larga | C14: 90 | D14: 90 | E14: 90 | F14: 95 | G14: 95 | H14: 95 | I14: 100 | J14: 100 | K14: 0 | L14: 105 | M14: 105 | N14: 105 | O14: 110 | P14: 110 | Q14: 110 | R14: 0
A15: 12 | B15: Pantalón para dama | C15: 0 | D15: 0 | E15: 0 | F15: 0 | G15: 0 | H15: 0 | I15: 0 | J15: 170 | K15: 170 | L15: 170 | M15: 180 | N15: 190 | O15: 200 | P15: 210 | Q15: 220 | R15: 0
A16: 13 | B16: Blusa manga corta | C16: 85 | D16: 85 | E16: 90 | F16: 95 | G16: 100 | H16: 105 | I16: 110 | J16: 115 | K16: 120 | L16: 125 | M16: 125 | N16: 130 | O16: 135 | P16: 140 | Q16: 150 | R16: 0
A17: 14 | B17: Blusa manga larga | C17: =C16+10 -> 95 | D17: =D16+10 -> 95 | E17: =E16+10 -> 100 | F17: =F16+10 -> 105 | G17: =G16+10 -> 110 | H17: =H16+10 -> 115 | I17: =I16+10 -> 120 | J17: =J16+10 -> 125 | ... Q17: =Q16+10 -> 160 | R17: 0
A18: 15 | B18: Corbata con elástico | C18: 30 | D18: 0 | E18: 0 | F18: 0 | G18: 0 | H18: 0 | I18: 0 | J18: 0 | K18: 0 | L18: 0 | M18: 0 | N18: 0 | O18: 0 | P18: 0 | Q18: 0 | R18: 0
A19: 16 | B19: Falda plisada | C19: 100 | D19: 110 | E19: 110 | F19: 110 | G19: 115 | H19: 155 | I19: 120 | J19: 120 | K19: 0 | L19: 125 | M19: 130 | N19: 135 | O19: 140 | P19: 150 | Q19: 170 | R19: 0
A20: 17 | B20: Jamper | C20: 100 | D20: 100 | E20: 110 | F20: 110 | G20: 120 | H20: 120 | I20: 0 | J20: 0 | K20: 0 | L20: 0 | M20: 0 | N20: 0 | O20: 0 | P20: 0 | Q20: 0 | R20: 0
A21: 18 | B21: Vestido | C21: 100 | D21: 100 | E21: 110 | F21: 110 | G21: 120 | H21: 120 | I21: 0 | J21: 0 | K21: 0 | L21: 0 | M21: 0 | N21: 0 | O21: 0 | P21: 0 | Q21: 0 | R21: 0
A22: 19 | B22: Chompa cuello en V | C22: 115 | D22: 115 | E22: 130 | F22: 145 | G22: 150 | H22: 155 | I22: 165 | J22: 170 | K22: 0 | L22: 180 | M22: 180 | N22: 180 | O22: 185 | P22: 185 | Q22: 190 | R22: 0
A23: 20 | B23: Chaleco cuello en V | C23: 115 | D23: 115 | E23: 125 | F23: 140 | G23: 145 | H23: 150 | I23: 155 | J23: 160 | K23: 0 | L23: 165 | M23: 170 | N23: 170 | O23: 175 | P23: 175 | Q23: 180 | R23: 0
A24: 21 | B24: Chamarra de verano | C24: 150 | D24: 150 | E24: 150 | F24: 160 | G24: 160 | H24: 160 | I24: 170 | J24: 170 | K24: 0 | L24: 170 | M24: 180 | N24: 180 | O24: 190 | P24: 200 | Q24: 200 | R24: 0
A25: 22 | B25: Chamarra deportiva | C25: 150 | D25: 150 | E25: 150 | F25: 160 | G25: 160 | H25: 160 | I25: 170 | J25: 170 | K25: 0 | L25: 170 | M25: 180 | N25: 180 | O25: 190 | P25: 200 | Q25: 200 | R25: 0
A26: 23 | B26: Chamarra de invierno | C26: 150 | D26: 150 | E26: 150 | F26: 160 | G26: 160 | H26: 160 | I26: 170 | J26: 170 | K26: 0 | L26: 170 | M26: 180 | N26: 180 | O26: 190 | P26: 200 | Q26: 200 | R26: 0
A27: 24 | B27: Buso Deportivo | C27: 90 | D27: 90 | E27: 95 | F27: 95 | G27: 100 | H27: 100 | I27: 105 | J27: 110 | K27: 0 | L27: 120 | M27: 135 | N27: 140 | O27: 145 | P27: 150 | Q27: 150 | R27: 0
A28: 25 | B28: Polera de colores | C28: 50 | D28: 50 | E28: 50 | F28: 60 | G28: 60 | H28: 65 | I28: 65 | J28: 65 | K28: 0 | L28: 0 | M28: 0 | N28: 0 | O28: 0 | P28: 0 | Q28: 0 | R28: 0
A29: 26 | B29: Polera Bullying | C29: 65 | D29: 0 | E29: 0 | F29: 0 | G29: 0 | H29: 0 | I29: 0 | J29: 0 | K29: 0 | L29: 0 | M29: 0 | N29: 0 | O29: 0 | P29: 0 | Q29: 0 | R29: 0
A30: 27 | B30: Saco | C30: 0 | D30: 0 | E30: 0 | F30: 0 | G30: 0 | H30: 0 | I30: 0 | J30: 0 | K30: 0 | L30: 0 | M30: 0 | N30: 0 | O30: 0 | P30: 0 | Q30: 0 | R30: 0

Sheet PrecioAgo2024
A2: ITEM | B2: DETALLE | C2: 2 | D2: 4 | E2: 6 | F2: 8 | G2: 10 | H2: 12 | I2: 14 | J2: 16/34 | K2: 36/XS | L2: 38/S | M2: 40/M | N2: 42/L | O2: 44/XL | P2: 46/2XL | Q2: 48/3XL | R2: 50/4XL
A3: 1 | B3: Pantalón de Varon | C3: - | D3: - | E3: - | F3: - | G3: - | H3: - | I3: - | J3: 200 | K3: 200 | L3: 210 | M3: 220 | N3: 220 | O3: 230 | P3: 240 | Q3: 260 | R3: 300
A4: 2 | B4: Camisa m/c | C4: 95 | D4: 95 | E4: 100 | F4: 105 | G4: 110 | H4: 115 | I4: 120 | J4: 125 | K4: - | L4: 135 | M4: 135 | N4: 140 | O4: 145 | P4: 150 | Q4: 165 | R4: -
A5: 3 | B5: Camisa m/l | C5: 105 | D5: 105 | E5: 110 | F5: 115 | G5: 120 | H5: 125 | I5: 135 | J5: 150 | K5: - | L5: 150 | M5: - | N5: - | O5: - | P5: - | Q5: - | R5: -
A6: 4 | B6: Corbata Larga | C6: 80 | D6: - | E6: - | F6: - | G6: - | H6: - | I6: - | J6: - | K6: - | L6: - | M6: - | N6: - | O6: - | P6: - | Q6: - | R6: -
A7: 5 | B7: Pantalón c/elas | C7: 110 | D7: 110 | E7: 115 | F7: 120 | G7: 125 | H7: 140 | I7: 170 | J7: 190 | K7: - | L7: 200 | M7: - | N7: - | O7: - | P7: - | Q7: - | R7: -
A8: 6 | B8: Bermuda | C8: 105 | D8: 105 | E8: 110 | F8: 115 | G8: 120 | H8: 135 | I8: 165 | J8: 185 | K8: - | L8: - | M8: - | N8: - | O8: - | P8: - | Q8: - | R8: -
A9: 7 | B9: Polera m/c | C9: 75 | D9: 75 | E9: 75 | F9: 85 | G9: 85 | H9: 85 | I9: 95 | J9: 95 | K9: - | L9: 105 | M9: 105 | N9: 105 | O9: 110 | P9: 110 | Q9: 110 | R9: -
A10: 8 | B10: Polera m/l | C10: 90 | D10: 90 | E10: 90 | F10: 100 | G10: 100 | H10: 100 | I10: 110 | J10: 110 | K10: - | L10: 115 | M10: 115 | N10: 115 | O10: 120 | P10: 120 | Q10: 125 | R10: -
A11: 9 | B11: Short | C11: 70 | D11: 70 | E11: 75 | F11: 75 | G11: 80 | H11: 80 | I11: 90 | J11: 90 | K11: - | L11: 95 | M11: 95 | N11: 95 | O11: 100 | P11: 100 | Q11: 100 | R11: -
A12: 10 | B12: Calza corta | C12: 70 | D12: 70 | E12: 75 | F12: 85 | G12: 85 | H12: 85 | I12: 95 | J12: 95 | K12: - | L12: 95 | M12: 105 | N12: 105 | O12: 105 | P12: 115 | Q12: 115 | R12: -
A13: 11 | B13: Calza larga | C13: 105 | D13: 105 | E13: 105 | F13: 115 | G13: 115 | H13: 115 | I13: 125 | J13: 125 | K13: - | L13: 125 | M13: 135 | N13: 135 | O13: 135 | P13: 145 | Q13: 145 | R13: -
A14: 12 | B14: Pantalón Dama | C14: - | D14: - | E14: - | F14: - | G14: - | H14: - | I14: - | J14: 200 | K14: 200 | L14: 200 | M14: 210 | N14: 220 | O14: 230 | P14: 240 | Q14: 250 | R14: -
A15: 13 | B15: Blusa m/c | C15: 95 | D15: 95 | E15: 100 | F15: 105 | G15: 110 | H15: 115 | I15: 120 | J15: 125 | K15: 125 | L15: 135 | M15: 135 | N15: 140 | O15: 145 | P15: 155 | Q15: 165 | R15: -
A16: 14 | B16: Blusa m/l | C16: 105 | D16: 105 | E16: 110 | F16: 115 | G16: 120 | H16: 125 | I16: 135 | J16: 150 | K16: - | L16: - | M16: - | N16: - | O16: - | P16: - | Q16: - | R16: -
A17: 15 | B17: Corbata c/elas | C17: 60 | D17: - | E17: - | F17: - | G17: - | H17: - | I17: - | J17: - | K17: - | L17: - | M17: - | N17: - | O17: - | P17: - | Q17: - | R17: -
A18: 16 | B18: Falda Plisada | C18: 140 | D18: 160 | E18: 160 | F18: 170 | G18: 170 | H18: 180 | I18: 180 | J18: 190 | K18: - | L18: 200 | M18: 210 | N18: 210 | O18: 210 | P18: 220 | Q18: 220 | R18: -
A19: 17 | B19: Jamper | C19: 150 | D19: 150 | E19: 160 | F19: 170 | G19: 180 | H19: 180 | I19: - | J19: - | K19: - | L19: - | M19: - | N19: - | O19: - | P19: - | Q19: - | R19: -
A20: 18 | B20: Vestido | C20: - | D20: 150 | E20: 160 | F20: 170 | G20: - | H20: - | I20: - | J20: - | K20: - | L20: - | M20: - | N20: - | O20: - | P20: - | Q20: - | R20: -
A21: 19 | B21: Chompa c/v | C21: 125 | D21: 130 | E21: 145 | F21: 155 | G21: 160 | H21: 170 | I21: 180 | J21: 185 | K21: - | L21: 190 | M21: 195 | N21: 195 | O21: 200 | P21: 200 | Q21: 210 | R21: -
A22: 20 | B22: Chaleco c/v | C22: 125 | D22: 130 | E22: 145 | F22: 155 | G22: 160 | H22: 170 | I22: 180 | J22: 185 | K22: - | L22: 190 | M22: 195 | N22: 195 | O22: 200 | P22: 200 | Q22: 210 | R22: -
A23: 21 | B23: Chamarra ver | C23: 170 | D23: 170 | E23: 170 | F23: 180 | G23: 180 | H23: 180 | I23: 190 | J23: 190 | K23: - | L23: 190 | M23: 200 | N23: 200 | O23: 210 | P23: 220 | Q23: 230 | R23: -
A24: 22 | B24: Chamarra dep | C24: 170 | D24: 170 | E24: 170 | F24: 180 | G24: 180 | H24: 180 | I24: 190 | J24: 190 | K24: - | L24: 190 | M24: 200 | N24: 200 | O24: 210 | P24: 220 | Q24: 230 | R24: -
A25: 23 | B25: Chamarra inv | C25: 190 | D25: 190 | E25: 190 | F25: 200 | G25: 200 | H25: 200 | I25: 210 | J25: 210 | K25: - | L25: 210 | M25: 220 | N25: 220 | O25: 230 | P25: 240 | Q25: 240 | R25: -
A26: 24 | B26: Buzo dep | C26: 100 | D26: 100 | E26: 105 | F26: 105 | G26: 110 | H26: 110 | I26: 120 | J26: 120 | K26: - | L26: 130 | M26: 145 | N26: 150 | O26: 160 | P26: 165 | Q26: 170 | R26: -
A27: 25 | B27: Polera de colores | C27: 75 | D27: 75 | E27: 75 | F27: 75 | G27: 75 | H27: 80 | I27: 80 | J27: 80 | K27: - | L27: 85 | M27: 85 | N27: 85 | O27: 85 | P27: 95 | Q27: 95 | R27: -
A28: 26 | B28: Polera Bullying | C28: 75 | D28: 75 | E28: 75 | F28: 75 | G28: 75 | H28: 80 | I28: 80 | J28: 80 | K28: - | L28: 85 | M28: 85 | N28: 85 | O28: 85 | P28: 95 | Q28: 95 | R28: -
A29: 27 | B29: Saco a medida Gde | C29: 780 | E29: Gorro | F29: 25 | H29: Sombrero | I29: 90 | K29: Riñonera | L29: 75 | M29: 0 | N29: 0 | O29: 0 | P29: 0 | Q29: 0 | R29: 0
A30: 28 | B30: Saco a medida Peq | C30: 480 | E30: Gorra | F30: 80 | H30: Lanyard | I30: 20 | K30: Cinturón | L30: 60
A32: * Actualizados a Agosto de 2024

Sheet INVENTARIO (2)
A1: INVENTARIO COLEGIO CAMBRIDGE AL 21/07/2026
A2: ITEM | B2: DETALLE | C2: 2 | D2: 4 | E2: 6 | F2: 8 | G2: 10 | H2: 12 | I2: 14 | J2: 16/34 | K2: 36/XS | L2: 38/S | M2: 40/M | N2: 42/L | O2: 44/XL | P2: 46/2XL | Q2: 48/3XL | R2: 50/4XL
A3: 1 | B3: Pantalón de vestir
A4: 2 | B4: Camisa manga corta
A5: 3 | B5: Camisa manga larga
A6: 4 | B6: Corbata larga
A7: 5 | B7: Pantalón con elástico
A8: 6 | B8: Bermuda
A9: 7 | B9: Polera manga corta
A10: 8 | B10: Polera manga larga
A11: 9 | B11: Short
A12: 10 | B12: Calza corta
A13: 11 | B13: Calza larga
A14: 12 | B14: Pantalón para dama
... A29: 27 | B29: Saco
